Workbook

Sheet 00_MAP
A1: نقشهٔ منطقی کارپوشه – مدل مالی و عملیاتی کارخانه بازیافت باتری سرب-اسید | B1: نقشه و راهنما
A2: معماری چندبوم: لایهٔ ورودی ← موتور محاسبات ← لایهٔ خروجی. هیچ عددی در شیت‌های محاسباتی سخت‌کد نشده است.
A4: الف) جریان داده (یک‌طرفه)
A5: لایهٔ ورودی‌ها | B5: تنها محل ورود اعداد و مفروضات؛ بدون هیچ فرمول
A6: ↓ | B6: جریان یک‌طرفه و شفاف
A7: موتور محاسبات (Engine) | B7: تبدیل ورودی‌ها به ظرفیت، هزینه، جریان نقد و ارزش‌گذاری
A8: ↓ | B8: جریان یک‌طرفه و شفاف
A9: لایهٔ خروجی‌ها | B9: داشبورد مدیریتی (Format A) و گزارش بانکی (Format B)
A11: ب) فهرست شیت‌ها به تفکیک لایه
A12: لایهٔ ورودی‌ها | B12: موتور محاسبات (مخفی) | C12: لایهٔ خروجی‌ها | D12: کنترل و راهنما
A13: =HYPERLINK("#'IN_MACRO'!A1","IN_MACRO") | B13: =HYPERLINK("#'ENG_SCEN'!A1","ENG_SCEN") | C13: =HYPERLINK("#'OUT_DASH'!A1","OUT_DASH") | D13: =HYPERLINK("#'00_MAP'!A1","00_MAP")
A14: =HYPERLINK("#'IN_TECH'!A1","IN_TECH") | B14: =HYPERLINK("#'ENG_OPS'!A1","ENG_OPS") | C14: =HYPERLINK("#'OUT_BANK'!A1","OUT_BANK") | D14: =HYPERLINK("#'99_CHECK'!A1","99_CHECK")
A15: =HYPERLINK("#'IN_SALES'!A1","IN_SALES") | B15: =HYPERLINK("#'ENG_ALLOC'!A1","ENG_ALLOC") | C15: =HYPERLINK("#'OUT_DEBT'!A1","OUT_DEBT")
A16: =HYPERLINK("#'IN_COST'!A1","IN_COST") | B16: =HYPERLINK("#'ENG_COST'!A1","ENG_COST") | C16: =HYPERLINK("#'OUT_SENS'!A1","OUT_SENS")
A17: =HYPERLINK("#'IN_WC'!A1","IN_WC") | B17: =HYPERLINK("#'ENG_WC'!A1","ENG_WC") | C17: =HYPERLINK("#'OUT_INVEST'!A1","OUT_INVEST")
A18: =HYPERLINK("#'IN_FIN'!A1","IN_FIN") | B18: =HYPERLINK("#'ENG_CAPEX'!A1","ENG_CAPEX")
A19: =HYPERLINK("#'IN_SCEN'!A1","IN_SCEN") | B19: =HYPERLINK("#'ENG_FCF'!A1","ENG_FCF")
B20: =HYPERLINK("#'ENG_DCF'!A1","ENG_DCF")
B21: =HYPERLINK("#'ENG_LEV'!A1","ENG_LEV")
B22: =HYPERLINK("#'ENG_SENS'!A1","ENG_SENS")
A24: ج) قواعد مدل‌سازی
A25: ۱. شیت‌های ورودی فقط عدد و متن دارند؛ هرگونه محاسبه در موتور انجام می‌شود.
A26: ۲. هر فرمول در موتور و خروجی به سلول‌های لایهٔ ورودی یا سایر شیت‌های موتور ارجاع می‌دهد.
A27: ۳. جریان داده یک‌طرفه است: ورودی ← موتور ← خروجی.
A28: ۴. سناریوها در IN_SCEN تعریف و در ENG_SCEN روی مفروضات کلیدی اعمال می‌شوند.
A29: ۵. ماتریس‌های حساسیت در ENG_SENS با بازمحاسبهٔ کامل FCF به ازای هر زوجِ انحراف ساخته می‌شوند.
A30: ۶. شیت‌های موتور به‌صورت پیش‌فرض مخفی‌اند؛ برای بازبینی از تب پایین صفحه نمایان شوند.
A31: ۷. واحد پول: میلیون ریال. واحد مقادیر: تن. واحد انرژی: کیلووات‌ساعت.
A33: د) نحوهٔ استفاده
A34: گام ۱: مفروضات را در هفت شیت ورودی (IN_*) وارد کنید.
A35: گام ۲: سناریوی فعال را در IN_SCEN انتخاب کنید (۱=پایه، ۲=خوش‌بینانه، ۳=بدبینانه).
A36: گام ۳: خروجی‌ها را در OUT_DASH (مدیریتی)، OUT_BANK و OUT_DEBT (بانکی) و OUT_SENS و OUT_INVEST (سرمایه‌گذار) بخوانید.
A37: گام ۴: کنترل‌های سلامت مدل را در 99_CHECK بررسی کنید.

Sheet IN_MACRO
A1: ۱. فرضیات کلان اقتصادی | B1: لایه ورودی
A2: تمام مفروضات اقتصاد کلان در این شیت وارد می‌شود؛ هیچ فرمولی مجاز نیست. واحد پول مدل: میلیون ریال.
A7: دوره (t) | D7: 0 | E7: 1 | F7: 2 | G7: 3 | H7: 4 | I7: 5 | J7: 6 | K7: 7 | L7: 8 | M7: 9 | N7: 10 | O7: 11 | P7: 12
A8: سال تقویمی | D8: 2026 | E8: 2027 | F8: 2028 | G8: 2029 | H8: 2030 | I8: 2031 | J8: 2032 | K8: 2033 | L8: 2034 | M8: 2035 | N8: 2036 | O8: 2037 | P8: 2038
A9: الف) پارامترهای کنترلی و ثابت مدل
A10: سال شروع مدل (میلادی) | B10: MAC.start_year | C10: سال | D10: 2026
A11: افق مدل (سال بهره‌برداری) | B11: MAC.horizon | C11: سال | D11: 12
A12: شاخص سال آغاز بهره‌برداری (t) | B12: MAC.ops_start | C12: شاخص | D12: 1
A13: شاخص سال پایان دوره ساخت (t) | B13: MAC.constr_end | C13: شاخص | D13: 1
A14: نرخ مالیات بر درآمد | B14: MAC.tax | C14: درصد | D14: 0.2
A15: صرف ریسک بازار سهام (ERP) | B15: MAC.erp | C15: درصد | D15: 0.06
A16: بتای سهام | B16: MAC.beta | C16: ضریب | D16: 1.15
A17: صرف ریسک کشور (CRP) | B17: MAC.crp | C17: درصد | D17: 0.04
A18: نرخ رشد دائمی اسمی | B18: MAC.g_term | C18: درصد | D18: 0.18
A19: روش ارزش پایانی (1=گوردون/2=ضریب خروج) | B19: MAC.tv_method | C19: 1/2 | D19: 2
A20: ضریب خروج (EV/EBITDA) | B20: MAC.exit_mult | C20: ضریب | D20: 6
A22: ب) مسیرهای سالانهٔ اقتصاد کلان (ورودی عددی)
A23: شاخص دوره (t) | B23: MAC.t | C23: شاخص | D23: 0 | E23: 1 | F23: 2 | G23: 3 | H23: 4 | I23: 5 | J23: 6 | K23: 7 | L23: 8 | M23: 9 | N23: 10 | O23: 11 | P23: 12
A24: سال تقویمی | B24: MAC.year | C24: سال | D24: 2026 | E24: 2027 | F24: 2028 | G24: 2029 | H24: 2030 | I24: 2031 | J24: 2032 | K24: 2033 | L24: 2034 | M24: 2035 | N24: 2036 | O24: 2037 | P24: 2038
A25: نرخ تورم عمومی | B25: MAC.infl | C25: درصد | D25: 0.25 | E25: 0.25 | F25: 0.23 | G25: 0.22 | H25: 0.2 | I25: 0.2 | J25: 0.18 | K25: 0.18 | L25: 0.16 | M25: 0.16 | N25: 0.15 | O25: 0.15 | P25: 0.15
A26: نرخ رشد دستمزد | B26: MAC.wage | C26: درصد | D26: 0.27 | E26: 0.26 | F26: 0.25 | G26: 0.23 | H26: 0.22 | I26: 0.21 | J26: 0.2 | K26: 0.19 | L26: 0.18 | M26: 0.17 | N26: 0.17 | O26: 0.16 | P26: 0.16
A27: نرخ رشد قیمت حامل‌های انرژی | B27: MAC.energy | C27: درصد | D27: 0.3 | E27: 0.28 | F27: 0.26 | G27: 0.25 | H27: 0.23 | I27: 0.22 | J27: 0.21 | K27: 0.2 | L27: 0.2 | M27: 0.19 | N27: 0.18 | O27: 0.18 | P27: 0.18
A28: نرخ ارز (ریال به ازای دلار) | B28: MAC.fx | C28: ریال/دلار | D28: 500000 | E28: 620000 | F28: 760000 | G28: 930000 | H28: 1120000 | I28: 1340000 | J28: 1590000 | K28: 1870000 | L28: 2180000 | M28: 2510000 | N28: 2860000 | O28: 3230000 | P28: 3610000
A29: قیمت جهانی سرب (LME) | B29: MAC.lme | C29: دلار/تن | D29: 2100 | E29: 2150 | F29: 2200 | G29: 2250 | H29: 2250 | I29: 2300 | J29: 2300 | K29: 2350 | L29: 2350 | M29: 2400 | N29: 2400 | O29: 2450 | P29: 2450
A30: نرخ سود بدون ریسک اسمی | B30: MAC.rf | C30: درصد | D30: 0.24 | E30: 0.24 | F30: 0.23 | G30: 0.23 | H30: 0.22 | I30: 0.22 | J30: 0.21 | K30: 0.21 | L30: 0.2 | M30: 0.2 | N30: 0.2 | O30: 0.19 | P30: 0.19
A31: رشد GDP بخش هدف | B31: MAC.gdp | C31: درصد | D31: 0.03 | E31: 0.03 | F31: 0.035 | G31: 0.035 | H31: 0.04 | I31: 0.04 | J31: 0.04 | K31: 0.035 | L31: 0.035 | M31: 0.03 | N31: 0.03 | O31: 0.03 | P31: 0.03
A32: شاخص قیمت تولیدکننده | B32: MAC.ppi | C32: درصد | D32: 0.24 | E32: 0.24 | F32: 0.22 | G32: 0.21 | H32: 0.2 | I32: 0.19 | J32: 0.18 | K32: 0.18 | L32: 0.17 | M32: 0.16 | N32: 0.16 | O32: 0.15 | P32: 0.15
A33: پرچم دوره ساخت (1=بله) | B33: MAC.constr_flg | C33: 1/0 | D33: 1 | E33: 0 | F33: 0 | G33: 0 | H33: 0 | I33: 0 | J33: 0 | K33: 0 | L33: 0 | M33: 0 | N33: 0 | O33: 0 | P33: 0
A34: پرچم دوره بهره‌برداری (1=بله) | B34: MAC.ops_flg | C34: 1/0 | D34: 0 | E34: 1 | F34: 1 | G34: 1 | H34: 1 | I34: 1 | J34: 1 | K34: 1 | L34: 1 | M34: 1 | N34: 1 | O34: 1 | P34: 1
A36: ج) یادداشت‌های روش‌شناختی
A37: ۱. شاخص‌های قیمتی از سال پایه (t=0) ساخته می‌شوند؛ مقدار شاخص در t=0 برابر یک است.
A38: ۲. نرخ ارز به‌صورت «ریال به ازای هر دلار» وارد می‌شود و مسیر آن مبنای تعدیل اقلام ارزی است.
A39: ۳. قیمت جهانی سرب (LME) مبنای قیمت‌گذاری محصولاتِ پیوند‌خورده و نیز قیمت خرید باتری ضایعاتی است.
A40: ۴. روش ارزش پایانی: ۱=رشد دائمی (گوردون)، ۲=ضریب خروج (EV/EBITDA).

Sheet IN_TECH
A1: ۲. پارامترهای فنی خط تولید (ایستگاه‌های ۱ تا ۶) | B1: لایه ورودی
A2: ظرفیت اسمی و مؤثر، راندمان، ضایعات، زمان‌های توقف و محرک‌های تخصیص هزینه.
A7: الف) پارامترهای سطح کارخانه
A8: ظرفیت اسمی ورودی باتری | B8: TECH.cap_in | C8: تن/سال | D8: 40000
A9: روزهای کاری در سال | B9: TECH.days | C9: روز | D9: 330
A10: شیفت در روز | B10: TECH.shifts | C10: شیفت | D10: 3
A11: ساعت در شیفت | B11: TECH.hshift | C11: ساعت | D11: 8
A12: توقف برنامه‌ریزی‌شده | B12: TECH.dt_plan | C12: ساعت/سال | D12: 400
A13: توقف اضطراری | B13: TECH.dt_unplan | C13: ساعت/سال | D13: 300
A15: ب) عوامل بازیابی و تبدیل مواد
A16: عیار سرب در خمیر | B16: TECH.pb_paste | C16: درصد | D16: 0.72
A17: عیار سرب در قطعات فلزی | B17: TECH.pb_metal | C17: درصد | D17: 0.95
A18: راندمان سولفات‌زدایی | B18: TECH.desulf | C18: درصد | D18: 0.95
A19: راندمان کوره ذوب و احیا | B19: TECH.smelt | C19: درصد | D19: 0.97
A20: راندمان تصفیه نهایی | B20: TECH.refine | C20: درصد | D20: 0.99
A21: راندمان بازیابی پلی‌پروپیلن | B21: TECH.pp_rec | C21: درصد | D21: 0.92
A22: ضریب تولید سولفات سدیم | B22: TECH.na2so4 | C22: تن/تن | D22: 0.13
A23: سهم سرب خالص از سرب تصفیه‌شده | B23: TECH.sp_soft | C23: درصد | D23: 0.6
A24: سهم آلیاژ از سرب تصفیه‌شده | B24: TECH.sp_alloy | C24: درصد | D24: 0.4
A26: ج) ترکیب جرمی باتری ورودی (سهم از هر تن)
A27: خمیر سرب (Paste) | B27: TECH.sh_paste | C27: درصد | D27: 0.38
A28: قطعات فلزی سربی (Grid / Posts) | B28: TECH.sh_metal | C28: درصد | D28: 0.26
A29: پلی‌پروپیلن | B29: TECH.sh_pp | C29: درصد | D29: 0.09
A30: الکترولیت (اسید سولفوریک) | B30: TECH.sh_elec | C30: درصد | D30: 0.12
A31: جداکننده‌ها و سایر پسماند | B31: TECH.sh_res | C31: درصد | D31: 0.15
A33: د) جدول پارامترهای ایستگاه‌ها
A34: ایستگاه | D34: S1 | E34: S2 | F34: S3 | G34: S4 | H34: S5 | I34: S6
D35: پذیرش، تخلیه و جداسازی الکترولیت | E35: خردایش و جدایش هیدرودینامیکی | F35: سولفات‌زدایی خمیر سرب | G35: کوره ذوب و احیا | H35: تصفیه و آلیاژسازی | I35: شمش‌ریزی، بسته‌بندی و انبار
A36: ظرفیت اسمی (تن در سال) | B36: TECH.cap_yr | C36: تن/سال | D36: 42000 | E36: 42000 | F36: 17000 | G36: 27000 | H36: 21000 | I36: 30000
A37: ظرفیت اسمی (تن در ساعت) | B37: TECH.cap_hr | C37: تن/ساعت | D37: 6.5 | E37: 6.5 | F37: 2.6 | G37: 4.2 | H37: 3.3 | I37: 4.7
A38: نرخ دسترسی (Availability) | B38: TECH.avail | C38: درصد | D38: 0.92 | E38: 0.9 | F38: 0.93 | G38: 0.91 | H38: 0.94 | I38: 0.95
A39: راندمان ایستگاه | B39: TECH.yield | C39: درصد | D39: 0.98 | E39: 0.97 | F39: 0.95 | G39: 0.97 | H39: 0.99 | I39: 0.99
A40: نرخ ضایعات / دورریز | B40: TECH.scrap | C40: درصد | D40: 0.005 | E40: 0.01 | F40: 0.01 | G40: 0.005 | H40: 0.005 | I40: 0.01
A41: انرژی ویژه الکتریکی | B41: TECH.kwh | C41: kWh/تن | D41: 8 | E41: 22 | F41: 18 | G41: 95 | H41: 40 | I41: 12
A42: آب ویژه | B42: TECH.water | C42: m3/تن | D42: 0.1 | E42: 0.6 | F42: 1.2 | G42: 0.25 | H42: 0.2 | I42: 0.35
A44: ه‍) جدول محرک‌های تخصیص هزینه به ایستگاه‌ها
A45: محرک / ایستگاه | D45: S1 | E45: S2 | F45: S3 | G45: S4 | H45: S5 | I45: S6
D46: پذیرش، تخلیه و جداسازی الکترولیت | E46: خردایش و جدایش هیدرودینامیکی | F46: سولفات‌زدایی خمیر سرب | G46: کوره ذوب و احیا | H46: تصفیه و آلیاژسازی | I46: شمش‌ریزی، بسته‌بندی و انبار
A47: جریان مواد (تن/سال در ظرفیت طراحی) | B47: THROUGHPUT | C47: تن/سال | D47: 40000 | E47: 40000 | F47: 15200 | G47: 24840 | H47: 19700 | I47: 27900
A48: ساعت کار ماشین در سال (طراحی) | B48: MACHINE_HOURS | C48: ساعت/سال | D48: 6000 | E48: 7200 | F48: 6600 | G48: 7920 | H48: 6600 | I48: 7200
A49: تعداد نیروی انسانی مستقر | B49: HEADCOUNT | C49: نفر | D49: 12 | E49: 18 | F49: 14 | G49: 24 | H49: 16 | I49: 22
A50: توان نصب‌شده | B50: POWER | C50: کیلووات | D50: 350 | E50: 900 | F50: 650 | G50: 1800 | H50: 900 | I50: 700
A51: مساحت اشغالی | B51: AREA | C51: m2 | D51: 1800 | E51: 1400 | F51: 1200 | G51: 2200 | H51: 1300 | I51: 2600
A52: مصرف آب در سال (طراحی) | B52: WATER | C52: m3/سال | D52: 3000 | E52: 24000 | F52: 18000 | G52: 6000 | H52: 4000 | I52: 9000
A54: توضیح: این جدول مبنای توزیع هزینه‌ها بین ایستگاه‌های ۱ تا ۶ است.
A56: و) منحنی بهره‌برداری از ظرفیت (سهم از ظرفیت اسمی)
A57: دوره (t) | D57: 0 | E57: 1 | F57: 2 | G57: 3 | H57: 4 | I57: 5 | J57: 6 | K57: 7 | L57: 8 | M57: 9 | N57: 10 | O57: 11 | P57: 12
A58: سال تقویمی | D58: 2026 | E58: 2027 | F58: 2028 | G58: 2029 | H58: 2030 | I58: 2031 | J58: 2032 | K58: 2033 | L58: 2034 | M58: 2035 | N58: 2036 | O58: 2037 | P58: 2038
A59: ضریب دستیابی به ظرفیت اسمی | B59: TECH.ramp | C59: درصد | D59: 0 | E59: 0.6 | F59: 0.8 | G59: 0.9 | H59: 1 | I59: 1 | J59: 1 | K59: 1 | L59: 1 | M59: 1 | N59: 1 | O59: 1 | P59: 1

Sheet IN_SALES
A1: ۳. مفروضات قیمت‌گذاری و فروش | B1: لایه ورودی
A2: قیمت پایه، پیوند به قیمت جهانی، ترکیب سبد محصولات و سیاست‌های تخفیف و اعتبار.
A7: الف) ویژگی‌های سبد محصولات
A8: محصول | D8: P1 | E8: P2 | F8: P3 | G8: P4
D9: شمش سرب خالص (Pb 99.97) | E9: شمش آلیاژ سرب (Pb-Sb / Pb-Ca) | F9: گرانول پلی‌پروپیلن بازیافتی | G9: سولفات سدیم (محصول جانبی)
A10: قیمت پایه (سال پایه) | B10: SAL.price | C10: میلیون ریال/تن | D10: 1050 | E10: 1082 | F10: 325 | G10: 60
A11: پیوند قیمت به LME (1=بله/0=خیر) | B11: SAL.lme | C11: 1/0 | D11: 1 | E11: 1 | F11: 0 | G11: 0
A12: ضریب تعدیل نسبت به LME | B12: SAL.lmef | C12: ضریب | D12: 1 | E12: 1.03 | F12: 1 | G12: 1
A13: نرخ رشد سالانه قیمت داخلی | B13: SAL.esc | C13: درصد | D13: 0.2 | E13: 0.2 | F13: 0.22 | G13: 0.2
A14: سهم ارزی (صادراتی/شاخص ارز) | B14: SAL.fxsh | C14: درصد | D14: 0.35 | E14: 0.35 | F14: 0.1 | G14: 0.5
A15: نرخ تخفیف و برگشت از فروش | B15: SAL.disc | C15: درصد | D15: 0.015 | E15: 0.015 | F15: 0.03 | G15: 0.05
A16: ضریب تحقق فروش (فروش/تولید) | B16: SAL.real | C16: ضریب | D16: 1 | E16: 1 | F16: 0.98 | G16: 0.95
A18: ب) سیاست‌های اعتباری و فروش
A19: نرخ برگشت از فروش و ادعاهای کیفی | B19: SAL.disc_late | C19: درصد | D19: 0.01
A20: دوره بازنگری قیمت‌ها (ماه) | B20: SAL.price_rev | C20: ماه | D20: 3
A21: سهم فروش قراردادی بلندمدت | B21: SAL.contract | C21: درصد | D21: 0.4
A22: سهم فروش نقدی/فوری | B22: SAL.spot | C22: درصد | D22: 0.6
A24: توضیح: «سهم ارزی» نشان می‌دهد چه بخشی از درآمدِ هر محصول با نرخ ارز تعدیل می‌شود (مبنای تحلیل حساسیت ارزی).

Sheet IN_COST
A1: ۴. پارامترهای هزینه‌ای (FPC / OPC / DPC) | B1: لایه ورودی
A2: نرخ‌های واحد، پرسنل، مراکز هزینهٔ خدماتی و ماتریس اقلام هزینه با مبنای محاسبه و تخصیص.
A7: الف) نرخ‌ها و پارامترهای پایه
A8: سهم ارزی هزینه‌های متغیر | B8: CST.fx_var | C8: درصد | D8: 0.2
A9: سهم ارزی هزینه‌های ثابت | B9: CST.fx_fix | C9: درصد | D9: 0.05
A10: ماه‌های پرداخت حقوق در سال | B10: CST.months | C10: ماه | D10: 12
A11: ضریب مزایا، عیدی و سنوات | B11: CST.bonus | C11: ضریب | D11: 1.08
A13: ب) پرسنل (تعداد و حقوق ماهانهٔ پایه)
D14: کد طبقه | E14: تعداد نفر | F14: حقوق ماهانه | G14: واحد
A15: تولید مستقیم | B15: PAY1 | D15: 96 | E15: 250 | F15: نفر / میلیون ریال
A16: تولید غیرمستقیم | B16: PAY2 | D16: 24 | E16: 320 | F16: نفر / میلیون ریال
A17: نگهداری و تعمیرات | B17: PAY3 | D17: 18 | E17: 300 | F17: نفر / میلیون ریال
A18: اداری و مالی | B18: PAY4 | D18: 22 | E18: 380 | F18: نفر / میلیون ریال
A19: فروش و بازاریابی | B19: PAY5 | D19: 8 | E19: 350 | F19: نفر / میلیون ریال
A21: ج) مراکز هزینهٔ خدماتی
D22: نام مرکز | E22: محرک تخصیص | F22: هزینه سالانهٔ پایه | G22: رفتار | H22: ترتیب
A23: نگهداری و تعمیرات مرکزی | B23: SC1 | D23: نگهداری و تعمیرات مرکزی | E23: MACHINE_HOURS | F23: 300000 | G23: F | H23: 1
A24: منابع انسانی و خدمات پشتیبانی | B24: SC2 | D24: منابع انسانی و خدمات پشتیبانی | E24: HEADCOUNT | F24: 100000 | G24: F | H24: 2
A25: لجستیک و انبارداری | B25: SC3 | D25: لجستیک و انبارداری | E25: THROUGHPUT | F25: 150000 | G25: F | H25: 3
A26: تصفیه‌خانه و محیط‌زیست | B26: SC4 | D26: تصفیه‌خانه و محیط‌زیست | E26: WATER | F26: 250000 | G26: V | H26: 4
A27: آزمایشگاه و کنترل کیفیت | B27: SC5 | D27: آزمایشگاه و کنترل کیفیت | E27: THROUGHPUT | F27: 80000 | G27: V | H27: 5
A29: رفتار هزینه: V = متغیر (تابع حجم)، F = ثابت (سالانه).
A31: د) ماتریس اقلام هزینه (مبنای محاسبه، تعدیل و تخصیص)
D32: طبقه | E32: مبنای محاسبه | F32: پارامتر / مرجع | G32: شاخص تعدیل | H32: مبنای تخصیص | I32: رفتار
A33: باتری ضایعاتی (مواد اولیه اصلی) | B33: DPC-01 | C33: میلیون ریال/تن | D33: DPC | E33: SCRAP_LME | F33: 348 | G33: NONE | H33: THROUGHPUT | I33: V
A34: مواد مصرفی و واکنشگرها | B34: DPC-02 | C34: میلیون ریال/تن | D34: DPC | E34: PER_TON_BATT | F34: 15 | G34: CPI | H34: THROUGHPUT | I34: V
A35: دستمزد مستقیم تولید | B35: DPC-03 | C35: ─ | D35: DPC | E35: PAY | F35: PAY:1 | G35: WAGE | H35: HEADCOUNT | I35: V
A36: مواد بسته‌بندی | B36: DPC-04 | C36: میلیون ریال/تن | D36: DPC | E36: PER_TON_PROD | F36: 4 | G36: CPI | H36: THROUGHPUT | I36: V
A37: حمل‌ونقل ورودی مواد | B37: DPC-05 | C37: میلیون ریال/تن | D37: DPC | E37: PER_TON_BATT | F37: 6 | G37: CPI | H37: THROUGHPUT | I37: V
A38: انرژی الکتریکی فرآیندی | B38: DPC-06 | C38: میلیون ریال/kWh | D38: DPC | E38: PER_KWH | F38: 0.006 | G38: ENERGY | H38: MACHINE_HOURS | I38: V
A39: سوخت و مواد احیاکننده | B39: OPC-01 | C39: میلیون ریال/تن | D39: OPC | E39: PER_TON_BATT | F39: 12.5 | G39: ENERGY | H39: THROUGHPUT | I39: V
A40: آب و پساب | B40: OPC-02 | C40: میلیون ریال/m3 | D40: OPC | E40: PER_M3 | F40: 0.25 | G40: CPI | H40: WATER | I40: V
A41: دفع پسماند و لجن | B41: OPC-03 | C41: میلیون ریال/تن | D41: OPC | E41: PER_TON_BATT | F41: 7.5 | G41: CPI | H41: THROUGHPUT | I41: V
A42: نگهداری و تعمیرات متغیر | B42: OPC-04 | C42: میلیون ریال/تن | D42: OPC | E42: PER_TON_BATT | F42: 9 | G42: CPI | H42: MACHINE_HOURS | I42: V
A43: مرکز خدماتی: نگهداری و تعمیرات | B43: OPC-05 | C43: ─ | D43: OPC | E43: SRV | F43: SRV:1 | G43: CPI | H43: SRV | I43: F
A44: مرکز خدماتی: لجستیک و انبارداری | B44: OPC-06 | C44: ─ | D44: OPC | E44: SRV | F44: SRV:3 | G44: CPI | H44: SRV | I44: F
A45: مرکز خدماتی: تصفیه‌خانه | B45: OPC-07 | C45: ─ | D45: OPC | E45: SRV | F45: SRV:4 | G45: CPI | H45: SRV | I45: V
A46: مرکز خدماتی: آزمایشگاه و QC | B46: OPC-08 | C46: ─ | D46: OPC | E46: SRV | F46: SRV:5 | G46: CPI | H46: SRV | I46: V
A47: هزینه فروش، توزیع و کارمزد فروش | B47: OPC-09 | C47: درصد از درآمد | D47: OPC | E47: PCT_REV | F47: 0.012 | G47: NONE | H47: THROUGHPUT | I47: V
A48: استهلاک دارایی‌های ثابت | B48: FPC-01 | C48: ─ | D48: FPC | E48: DEP | F48: DEP | G48: NONE | H48: POWER | I48: F
A49: بیمه دارایی‌ها | B49: FPC-02 | C49: درصد ارزش دفتری | D49: FPC | E49: PCT_ASSET | F49: 0.006 | G49: NONE | H49: POWER | I49: F
A50: اجاره و حق‌الامتیاز | B50: FPC-03 | C50: میلیون ریال/سال | D50: FPC | E50: ANNUAL | F50: 80000 | G50: CPI | H50: AREA | I50: F
A51: حقوق غیرمستقیم تولید | B51: FPC-04 | C51: ─ | D51: FPC | E51: PAY | F51: PAY:2 | G51: WAGE | H51: HEADCOUNT | I51: F
A52: حقوق نگهداری و تعمیرات | B52: FPC-05 | C52: ─ | D52: FPC | E52: PAY | F52: PAY:3 | G52: WAGE | H52: HEADCOUNT | I52: F
A53: حقوق اداری و مالی | B53: FPC-06 | C53: ─ | D53: FPC | E53: PAY | F53: PAY:4 | G53: WAGE | H53: HEADCOUNT | I53: F
A54: حقوق فروش و بازاریابی | B54: FPC-07 | C54: ─ | D54: FPC | E54: PAY | F54: PAY:5 | G54: WAGE | H54: HEADCOUNT | I54: F
A55: هزینه‌های عمومی و اداری غیرپرسنلی | B55: FPC-08 | C55: میلیون ریال/سال | D55: FPC | E55: ANNUAL | F55: 300000 | G55: CPI | H55: HEADCOUNT | I55: F
A56: تبلیغات و بازاریابی ثابت | B56: FPC-09 | C56: میلیون ریال/سال | D56: FPC | E56: ANNUAL | F56: 120000 | G56: CPI | H56: AREA | I56: F
A57: بار پایه انرژی | B57: FPC-10 | C57: میلیون ریال/سال | D57: FPC | E57: ANNUAL | F57: 400000 | G57: ENERGY | H57: POWER | I57: F
A58: مرکز خدماتی: منابع انسانی | B58: FPC-11 | C58: ─ | D58: FPC | E58: SRV | F58: SRV:2 | G58: CPI | H58: SRV | I58: F
A59: سایر هزینه‌های ثابت | B59: FPC-12 | C59: میلیون ریال/سال | D59: FPC | E59: ANNUAL | F59: 150000 | G59: CPI | H59: AREA | I59: F
A61: راهنما: مبنای محاسبه ← SCRAP_LME (خرید مواد اولیه، پیوند به LME×ارز)، PER_TON_BATT، PER_TON_PROD،
A62: PER_KWH، PER_M3، ANNUAL (مبلغ سالانه)، PCT_REV (درصد از درآمد)، PCT_ASSET (درصد ارزش دفتری)،
A63: DEP (استهلاک از موتور دارایی‌ها)، PAY:n (طبقه حقوقی n)، SRV:n (مرکز خدماتی n).
A64: شاخص تعدیل: CPI / WAGE / ENERGY / PPI / FX / NONE. مبنای تخصیص: THROUGHPUT / MACHINE_HOURS /
A65: HEADCOUNT / POWER / AREA / WATER / SRV (تخصیص از جدول مراکز خدماتی).

Sheet IN_WC
A1: ۵. سیاست‌های سرمایه در گردش و چرخه نقدینگی | B1: لایه ورودی
A2: روزهای موجودی، دریافتنی و پرداختنی برای محاسبهٔ چرخهٔ تبدیل نقد (CCC).
A7: الف) دوره‌های سرمایه در گردش (روز)
A8: موجودی مواد اولیه (باتری ضایعاتی) | B8: WC.dio_rm | C8: روز | D8: 25
A9: موجودی کالای در جریان ساخت | B9: WC.dio_wip | C9: روز | D9: 8
A10: موجودی محصول نهایی | B10: WC.dio_fg | C10: روز | D10: 15
A11: موجودی مواد مصرفی و قطعات یدکی | B11: WC.dio_cons | C11: روز | D11: 30
A12: دوره وصول مطالبات (DSO) | B12: WC.dso | C12: روز | D12: 45
A13: دوره پرداخت بدهی‌ها (DPO) | B13: WC.dpo | C13: روز | D13: 40
A14: دوره پرداخت مالیات | B14: WC.dpo_tax | C14: روز | D14: 30
A15: ذخیره نقدی عملیاتی (روز هزینه نقدی) | B15: WC.cashdays | C15: روز | D15: 15
A17: ب) سیاست‌های تأمین مالی سرمایه در گردش
A18: سهم سرمایه در گردش تأمین‌شده از تسهیلات کوتاه‌مدت | B18: WC.wc_loan_share | C18: درصد | D18: 0.3
A19: نرخ ذخیره مطالبات مشکوک‌الوصول | B19: WC.bad_debt | C19: درصد | D19: 0.01
A20: ضریب کاهش ارزش موجودی (کهنگی) | B20: WC.inv_obs | C20: درصد | D20: 0.005

Sheet IN_FIN
A1: ۶. ساختار سرمایه، تأمین مالی و برنامه CAPEX | B1: لایه ورودی
A2: درصد بدهی و حقوق صاحبان سهام، نرخ‌های بهره، دوره بازپرداخت، کارمزدها و برنامه تزریق سرمایه.
A7: الف) برنامه سرمایه‌گذاری ثابت (CAPEX)
D8: مبلغ کل | E8: سهم ارزی | F8: عمر مفید | G8: دوره جایگزینی | H8: درصد جایگزینی | I8: ارزش اسقاط | J8: تزریق t=0 | K8: تزریق t=1 | L8: تزریق t=2
A9: زمین | B9: CAP-01 | C9: میلیون ریال | D9: 300000 | E9: 0 | F9: 0 | G9: 0 | H9: 0 | I9: 1 | J9: 1 | K9: 0 | L9: 0
A10: محوطه‌سازی و ساختمان | B10: CAP-02 | C10: میلیون ریال | D10: 1600000 | E10: 0.1 | F10: 30 | G10: 0 | H10: 0 | I10: 0.3 | J10: 0.75 | K10: 0.25 | L10: 0
A11: ماشین‌آلات وارداتی | B11: CAP-03 | C11: میلیون ریال | D11: 4800000 | E11: 0.9 | F11: 15 | G11: 0 | H11: 0.6 | I11: 0.1 | J11: 0.75 | K11: 0.25 | L11: 0
A12: ماشین‌آلات داخلی | B12: CAP-04 | C12: میلیون ریال | D12: 1900000 | E12: 0.25 | F12: 12 | G12: 12 | H12: 0.7 | I12: 0.1 | J12: 0.75 | K12: 0.25 | L12: 0
A13: تأسیسات و تجهیزات جانبی | B13: CAP-05 | C13: میلیون ریال | D13: 1200000 | E13: 0.4 | F13: 15 | G13: 0 | H13: 0.5 | I13: 0.1 | J13: 0.75 | K13: 0.25 | L13: 0
A14: تصفیه‌خانه و تجهیزات زیست‌محیطی | B14: CAP-06 | C14: میلیون ریال | D14: 1050000 | E14: 0.3 | F14: 12 | G14: 12 | H14: 0.7 | I14: 0.1 | J14: 0.75 | K14: 0.25 | L14: 0
A15: تجهیزات حمل‌ونقل داخلی | B15: CAP-07 | C15: میلیون ریال | D15: 700000 | E15: 0.2 | F15: 8 | G15: 8 | H15: 0.8 | I15: 0.15 | J15: 0.6 | K15: 0.4 | L15: 0
A16: آزمایشگاه و ابزار دقیق | B16: CAP-08 | C16: میلیون ریال | D16: 450000 | E16: 0.6 | F16: 10 | G16: 10 | H16: 0.6 | I16: 0.1 | J16: 0.5 | K16: 0.5 | L16: 0
A17: مهندسی، نصب و راه‌اندازی | B17: CAP-09 | C17: میلیون ریال | D17: 900000 | E17: 0.1 | F17: 15 | G17: 0 | H17: 0 | I17: 0 | J17: 0.6 | K17: 0.4 | L17: 0
A18: هزینه‌های پیش از بهره‌برداری | B18: CAP-10 | C18: میلیون ریال | D18: 420000 | E18: 0.05 | F18: 5 | G18: 5 | H18: 0.5 | I18: 0 | J18: 0.3 | K18: 0.5 | L18: 0.2
A19: ذخیره احتیاطی فیزیکی | B19: CAP-11 | C19: میلیون ریال | D19: 1200000 | E19: 0.4 | F19: 15 | G19: 0 | H19: 0 | I19: 0.1 | J19: 0.4 | K19: 0.4 | L19: 0.2
A21: توضیح: عمر مفید صفر = مستهلک نمی‌شود (زمین). دوره جایگزینی صفر = جایگزینی در افق مدل ندارد.
A23: ب) ساختار تأمین مالی
A24: سهم تسهیلات بلندمدت از CAPEX | B24: FIN.debt_share | C24: درصد | D24: 0.6
A25: نرخ سود تسهیلات بلندمدت | B25: FIN.kd | C25: درصد | D25: 0.22
A26: کارمزد تخصیص/تعهد یکجا | B26: FIN.fee_arr | C26: درصد | D26: 0.015
A27: کارمزد تعهد روی مانده استفاده‌نشده | B27: FIN.fee_com | C27: درصد | D27: 0.005
A28: شاخص سال شروع بازپرداخت (t) | B28: FIN.repay_start | C28: شاخص | D28: 2
A29: دوره بازپرداخت (سال) | B29: FIN.repay_years | C29: سال | D29: 8
A30: روش بازپرداخت (1=اقساط مساوی اصل / 2=آنویتی) | B30: FIN.repay_method | C30: 1/2 | D30: 1
A31: نرخ سود تسهیلات کوتاه‌مدت (سرمایه در گردش) | B31: FIN.kd_st | C31: درصد | D31: 0.24
A32: حداقل DSCR قراردادی | B32: FIN.min_dscr | C32: ضریب | D32: 1.3
A33: سیاست تقسیم سود (درصد از سود خالص) | B33: FIN.payout | C33: درصد | D33: 0.4
A34: نرخ سود سپرده/درآمد غیرعملیاتی نقد | B34: FIN.i_income | C34: درصد | D34: 0.1

Sheet IN_SCEN
A1: ۷. تعریف سناریوها و محورهای حساسیت | B1: لایه ورودی
A2: ضرایب تعدیل مفروضات کلیدی در سناریوهای پایه / خوش‌بینانه / بدبینانه و محورهای ماتریس حساسیت.
A7: الف) انتخاب سناریوی فعال
A8: سناریوی فعال (۱=پایه، ۲=خوش‌بینانه، ۳=بدبینانه) | B8: SCEN.active_in | C8: شاخص | D8: 1
A9: تغییر این سلول کل مدل را به‌صورت زنجیره‌ای به‌روزرسانی می‌کند (ورودی ← موتور ← خروجی).
A11: ب) جدول ضرایب سناریوها
D12: پایه | E12: خوش‌بینانه | F12: بدبینانه
A13: ضریب حجم تولید و فروش | B13: VOL | C13: ضریب | D13: 1 | E13: 1.08 | F13: 0.88
A14: ضریب قیمت فروش محصولات | B14: PRICE | C14: ضریب | D14: 1 | E14: 1.1 | F14: 0.9
A15: ضریب قیمت خرید باتری ضایعاتی | B15: RM | C15: ضریب | D15: 1 | E15: 0.95 | F15: 1.08
A16: ضریب سایر هزینه‌های متغیر | B16: VAR | C16: ضریب | D16: 1 | E16: 0.97 | F16: 1.1
A17: ضریب هزینه‌های ثابت | B17: FIX | C17: ضریب | D17: 1 | E17: 0.95 | F17: 1.12
A18: ضریب سرمایه‌گذاری ثابت | B18: CAPEX | C18: ضریب | D18: 1 | E18: 0.95 | F18: 1.15
A19: ضریب نرخ ارز | B19: FX | C19: ضریب | D19: 1 | E19: 1.05 | F19: 0.95
A20: تعدیل نرخ تنزیل | B20: WACC | C20: واحد درصد | D20: 0 | E20: -0.02 | F20: 0.03
A21: تعدیل نرخ سود تسهیلات | B21: KD | C21: واحد درصد | D21: 0 | E21: -0.01 | F21: 0.03
A23: ج) محورهای ماتریس حساسیت
A24: انحراف نرخ بهره/تنزیل | B24: SCEN.ax_rate | C24: درصد | D24: -0.03 | E24: -0.015 | F24: 0 | G24: 0.015 | H24: 0.03
A25: انحراف نرخ ارز | B25: SCEN.ax_fx | C25: درصد | D25: -0.2 | E25: -0.1 | F25: 0 | G25: 0.1 | H25: 0.2
A26: انحراف قیمت فروش | B26: SCEN.ax_price | C26: درصد | D26: -0.15 | E26: -0.075 | F26: 0 | G26: 0.075 | H26: 0.15
A28: د) شرح سناریوها
A29: پایه: مفروضاتِ مندرج در شیت‌های ورودی بدون تعدیل (تمام ضرایب برابر یک یا صفر).
A30: خوش‌بینانه: رشد حجم و قیمت، کنترل هزینه‌ها و دسترسی بهتر به تأمین مالی.
A31: بدبینانه: افت حجم و قیمت، افزایش هزینه‌ها، افزایش CAPEX و نرخ تأمین مالی.

Sheet ENG_SCEN
A1: موتور سناریو و حساسیت | B1: موتور محاسبات
A2: اعمال ضرایب سناریوی فعال روی مفروضات کلیدی، ساخت مسیرهای تعدیل‌شده و شاخص‌های قیمتی.
A7: دوره (t) | D7: 0 | E7: 1 | F7: 2 | G7: 3 | H7: 4 | I7: 5 | J7: 6 | K7: 7 | L7: 8 | M7: 9 | N7: 10 | O7: 11 | P7: 12
A8: سال تقویمی | D8: 2026 | E8: 2027 | F8: 2028 | G8: 2029 | H8: 2030 | I8: 2031 | J8: 2032 | K8: 2033 | L8: 2034 | M8: 2035 | N8: 2036 | O8: 2037 | P8: 2038
A9: الف) سناریوی فعال و ضرایب تعدیل
A10: سناریوی فعال (۱=پایه / ۲=خوش‌بینانه / ۳=بدبینانه) | C10: شاخص | D10: ='IN_SCEN'!$D$8
A11: ضریب حجم تولید و فروش — مقدار فعال | B11: VOL | C11: ضریب | D11: ='IN_SCEN'!$D$13 | E11: ='IN_SCEN'!$E$13 | F11: ='IN_SCEN'!$F$13 | G11: =INDEX('IN_SCEN'!$D$13:$F$13,'ENG_SCEN'!$D$10)
A12: ضریب قیمت فروش محصولات — مقدار فعال | B12: PRICE | C12: ضریب | D12: ='IN_SCEN'!$D$14 | E12: ='IN_SCEN'!$E$14 | F12: ='IN_SCEN'!$F$14 | G12: =INDEX('IN_SCEN'!$D$14:$F$14,'ENG_SCEN'!$D$10)
A13: ضریب قیمت خرید باتری ضایعاتی — مقدار فعال | B13: RM | C13: ضریب | D13: ='IN_SCEN'!$D$15 | E13: ='IN_SCEN'!$E$15 | F13: ='IN_SCEN'!$F$15 | G13: =INDEX('IN_SCEN'!$D$15:$F$15,'ENG_SCEN'!$D$10)
A14: ضریب سایر هزینه‌های متغیر — مقدار فعال | B14: VAR | C14: ضریب | D14: ='IN_SCEN'!$D$16 | E14: ='IN_SCEN'!$E$16 | F14: ='IN_SCEN'!$F$16 | G14: =INDEX('IN_SCEN'!$D$16:$F$16,'ENG_SCEN'!$D$10)
A15: ضریب هزینه‌های ثابت — مقدار فعال | B15: FIX | C15: ضریب | D15: ='IN_SCEN'!$D$17 | E15: ='IN_SCEN'!$E$17 | F15: ='IN_SCEN'!$F$17 | G15: =INDEX('IN_SCEN'!$D$17:$F$17,'ENG_SCEN'!$D$10)
A16: ضریب سرمایه‌گذاری ثابت — مقدار فعال | B16: CAPEX | C16: ضریب | D16: ='IN_SCEN'!$D$18 | E16: ='IN_SCEN'!$E$18 | F16: ='IN_SCEN'!$F$18 | G16: =INDEX('IN_SCEN'!$D$18:$F$18,'ENG_SCEN'!$D$10)
A17: ضریب نرخ ارز — مقدار فعال | B17: FX | C17: ضریب | D17: ='IN_SCEN'!$D$19 | E17: ='IN_SCEN'!$E$19 | F17: ='IN_SCEN'!$F$19 | G17: =INDEX('IN_SCEN'!$D$19:$F$19,'ENG_SCEN'!$D$10)
A18: تعدیل نرخ تنزیل — مقدار فعال | B18: WACC | C18: واحد درصد | D18: ='IN_SCEN'!$D$20 | E18: ='IN_SCEN'!$E$20 | F18: ='IN_SCEN'!$F$20 | G18: =INDEX('IN_SCEN'!$D$20:$F$20,'ENG_SCEN'!$D$10)
A19: تعدیل نرخ سود تسهیلات — مقدار فعال | B19: KD | C19: واحد درصد | D19: ='IN_SCEN'!$D$21 | E19: ='IN_SCEN'!$E$21 | F19: ='IN_SCEN'!$F$21 | G19: =INDEX('IN_SCEN'!$D$21:$F$21,'ENG_SCEN'!$D$10)
A21: ب) مسیرهای تعدیل‌شدهٔ اقتصاد کلان
A22: شاخص تورم عمومی | B22: SCEN.infl | C22: ─ | D22: ='IN_MACRO'!$D$25 | E22: ='IN_MACRO'!$E$25 | F22: ='IN_MACRO'!$F$25 | G22: ='IN_MACRO'!$G$25 | H22: ='IN_MACRO'!$H$25 | I22: ='IN_MACRO'!$I$25 | J22: ='IN_MACRO'!$J$25 | K22: ='IN_MACRO'!$K$25 | L22: ='IN_MACRO'!$L$25 | M22: ='IN_MACRO'!$M$25 | N22: ='IN_MACRO'!$N$25 | O22: ='IN_MACRO'!$O$25 | P22: ='IN_MACRO'!$P$25
A23: شاخص رشد دستمزد | B23: SCEN.wage | C23: ─ | D23: ='IN_MACRO'!$D$26 | E23: ='IN_MACRO'!$E$26 | F23: ='IN_MACRO'!$F$26 | G23: ='IN_MACRO'!$G$26 | H23: ='IN_MACRO'!$H$26 | I23: ='IN_MACRO'!$I$26 | J23: ='IN_MACRO'!$J$26 | K23: ='IN_MACRO'!$K$26 | L23: ='IN_MACRO'!$L$26 | M23: ='IN_MACRO'!$M$26 | N23: ='IN_MACRO'!$N$26 | O23: ='IN_MACRO'!$O$26 | P23: ='IN_MACRO'!$P$26
A24: شاخص رشد قیمت انرژی | B24: SCEN.energy | C24: ─ | D24: ='IN_MACRO'!$D$27 | E24: ='IN_MACRO'!$E$27 | F24: ='IN_MACRO'!$F$27 | G24: ='IN_MACRO'!$G$27 | H24: ='IN_MACRO'!$H$27 | I24: ='IN_MACRO'!$I$27 | J24: ='IN_MACRO'!$J$27 | K24: ='IN_MACRO'!$K$27 | L24: ='IN_MACRO'!$L$27 | M24: ='IN_MACRO'!$M$27 | N24: ='IN_MACRO'!$N$27 | O24: ='IN_MACRO'!$O$27 | P24: ='IN_MACRO'!$P$27
A25: شاخص قیمت تولیدکننده | B25: SCEN.ppi | C25: ─ | D25: ='IN_MACRO'!$D$32 | E25: ='IN_MACRO'!$E$32 | F25: ='IN_MACRO'!$F$32 | G25: ='IN_MACRO'!$G$32 | H25: ='IN_MACRO'!$H$32 | I25: ='IN_MACRO'!$I$32 | J25: ='IN_MACRO'!$J$32 | K25: ='IN_MACRO'!$K$32 | L25: ='IN_MACRO'!$L$32 | M25: ='IN_MACRO'!$M$32 | N25: ='IN_MACRO'!$N$32 | O25: ='IN_MACRO'!$O$32 | P25: ='IN_MACRO'!$P$32
A26: نرخ سود بدون ریسک | B26: SCEN.rf | C26: ─ | D26: ='IN_MACRO'!$D$30 | E26: ='IN_MACRO'!$E$30 | F26: ='IN_MACRO'!$F$30 | G26: ='IN_MACRO'!$G$30 | H26: ='IN_MACRO'!$H$30 | I26: ='IN_MACRO'!$I$30 | J26: ='IN_MACRO'!$J$30 | K26: ='IN_MACRO'!$K$30 | L26: ='IN_MACRO'!$L$30 | M26: ='IN_MACRO'!$M$30 | N26: ='IN_MACRO'!$N$30 | O26: ='IN_MACRO'!$O$30 | P26: ='IN_MACRO'!$P$30
A27: رشد GDP بخش هدف | B27: SCEN.gdp | C27: ─ | D27: ='IN_MACRO'!$D$31 | E27: ='IN_MACRO'!$E$31 | F27: ='IN_MACRO'!$F$31 | G27: ='IN_MACRO'!$G$31 | H27: ='IN_MACRO'!$H$31 | I27: ='IN_MACRO'!$I$31 | J27: ='IN_MACRO'!$J$31 | K27: ='IN_MACRO'!$K$31 | L27: ='IN_MACRO'!$L$31 | M27: ='IN_MACRO'!$M$31 | N27: ='IN_MACRO'!$N$31 | O27: ='IN_MACRO'!$O$31 | P27: ='IN_MACRO'!$P$31
A28: قیمت جهانی سرب LME | B28: SCEN.lme | C28: ─ | D28: ='IN_MACRO'!$D$29 | E28: ='IN_MACRO'!$E$29 | F28: ='IN_MACRO'!$F$29 | G28: ='IN_MACRO'!$G$29 | H28: ='IN_MACRO'!$H$29 | I28: ='IN_MACRO'!$I$29 | J28: ='IN_MACRO'!$J$29 | K28: ='IN_MACRO'!$K$29 | L28: ='IN_MACRO'!$L$29 | M28: ='IN_MACRO'!$M$29 | N28: ='IN_MACRO'!$N$29 | O28: ='IN_MACRO'!$O$29 | P28: ='IN_MACRO'!$P$29
A29: نرخ ارز (تعدیل‌شده) | B29: SCEN.fx | C29: ─ | D29: ='IN_MACRO'!$D$28*'ENG_SCEN'!$G$17 | E29: ='IN_MACRO'!$E$28*'ENG_SCEN'!$G$17 | F29: ='IN_MACRO'!$F$28*'ENG_SCEN'!$G$17 | G29: ='IN_MACRO'!$G$28*'ENG_SCEN'!$G$17 | H29: ='IN_MACRO'!$H$28*'ENG_SCEN'!$G$17 | I29: ='IN_MACRO'!$I$28*'ENG_SCEN'!$G$17 | J29: ='IN_MACRO'!$J$28*'ENG_SCEN'!$G$17 | K29: ='IN_MACRO'!$K$28*'ENG_SCEN'!$G$17 | L29: ='IN_MACRO'!$L$28*'ENG_SCEN'!$G$17 | M29: ='IN_MACRO'!$M$28*'ENG_SCEN'!$G$17 | N29: ='IN_MACRO'!$N$28*'ENG_SCEN'!$G$17 | O29: ='IN_MACRO'!$O$28*'ENG_SCEN'!$G$17 | P29: ='IN_MACRO'!$P$28*'ENG_SCEN'!$G$17
A31: ج) شاخص‌های قیمتی تجمعی (سال پایه = ۱)
A32: شاخص تورم عمومی | C32: ضریب | D32: =1 | E32: =D32*(1+'ENG_SCEN'!$E$22) | F32: =E32*(1+'ENG_SCEN'!$F$22) | G32: =F32*(1+'ENG_SCEN'!$G$22) | H32: =G32*(1+'ENG_SCEN'!$H$22) | I32: =H32*(1+'ENG_SCEN'!$I$22) | J32: =I32*(1+'ENG_SCEN'!$J$22) | K32: =J32*(1+'ENG_SCEN'!$K$22) | L32: =K32*(1+'ENG_SCEN'!$L$22) | M32: =L32*(1+'ENG_SCEN'!$M$22) | N32: =M32*(1+'ENG_SCEN'!$N$22) | O32: =N32*(1+'ENG_SCEN'!$O$22) | P32: =O32*(1+'ENG_SCEN'!$P$22)
A33: شاخص دستمزد | C33: ضریب | D33: =1 | E33: =D33*(1+'ENG_SCEN'!$E$23) | F33: =E33*(1+'ENG_SCEN'!$F$23) | G33: =F33*(1+'ENG_SCEN'!$G$23) | H33: =G33*(1+'ENG_SCEN'!$H$23) | I33: =H33*(1+'ENG_SCEN'!$I$23) | J33: =I33*(1+'ENG_SCEN'!$J$23) | K33: =J33*(1+'ENG_SCEN'!$K$23) | L33: =K33*(1+'ENG_SCEN'!$L$23) | M33: =L33*(1+'ENG_SCEN'!$M$23) | N33: =M33*(1+'ENG_SCEN'!$N$23) | O33: =N33*(1+'ENG_SCEN'!$O$23) | P33: =O33*(1+'ENG_SCEN'!$P$23)
A34: شاخص قیمت انرژی | C34: ضریب | D34: =1 | E34: =D34*(1+'ENG_SCEN'!$E$24) | F34: =E34*(1+'ENG_SCEN'!$F$24) | G34: =F34*(1+'ENG_SCEN'!$G$24) | H34: =G34*(1+'ENG_SCEN'!$H$24) | I34: =H34*(1+'ENG_SCEN'!$I$24) | J34: =I34*(1+'ENG_SCEN'!$J$24) | K34: =J34*(1+'ENG_SCEN'!$K$24) | L34: =K34*(1+'ENG_SCEN'!$L$24) | M34: =L34*(1+'ENG_SCEN'!$M$24) | N34: =M34*(1+'ENG_SCEN'!$N$24) | O34: =N34*(1+'ENG_SCEN'!$O$24) | P34: =O34*(1+'ENG_SCEN'!$P$24)
A35: شاخص قیمت تولیدکننده | C35: ضریب | D35: =1 | E35: =D35*(1+'ENG_SCEN'!$E$25) | F35: =E35*(1+'ENG_SCEN'!$F$25) | G35: =F35*(1+'ENG_SCEN'!$G$25) | H35: =G35*(1+'ENG_SCEN'!$H$25) | I35: =H35*(1+'ENG_SCEN'!$I$25) | J35: =I35*(1+'ENG_SCEN'!$J$25) | K35: =J35*(1+'ENG_SCEN'!$K$25) | L35: =K35*(1+'ENG_SCEN'!$L$25) | M35: =L35*(1+'ENG_SCEN'!$M$25) | N35: =M35*(1+'ENG_SCEN'!$N$25) | O35: =N35*(1+'ENG_SCEN'!$O$25) | P35: =O35*(1+'ENG_SCEN'!$P$25)
A36: شاخص نرخ ارز | D36: ='ENG_SCEN'!$D$29/'ENG_SCEN'!$D$29 | E36: ='ENG_SCEN'!$E$29/'ENG_SCEN'!$D$29 | F36: ='ENG_SCEN'!$F$29/'ENG_SCEN'!$D$29 | G36: ='ENG_SCEN'!$G$29/'ENG_SCEN'!$D$29 | H36: ='ENG_SCEN'!$H$29/'ENG_SCEN'!$D$29 | I36: ='ENG_SCEN'!$I$29/'ENG_SCEN'!$D$29 | J36: ='ENG_SCEN'!$J$29/'ENG_SCEN'!$D$29 | K36: ='ENG_SCEN'!$K$29/'ENG_SCEN'!$D$29 | L36: ='ENG_SCEN'!$L$29/'ENG_SCEN'!$D$29 | M36: ='ENG_SCEN'!$M$29/'ENG_SCEN'!$D$29 | N36: ='ENG_SCEN'!$N$29/'ENG_SCEN'!$D$29 | O36: ='ENG_SCEN'!$O$29/'ENG_SCEN'!$D$29 | P36: ='ENG_SCEN'!$P$29/'ENG_SCEN'!$D$29
A37: شاخص ترکیبی LME×ارز | D37: =('ENG_SCEN'!$D$28*'ENG_SCEN'!$D$29)/('ENG_SCEN'!$D$28*'ENG_SCEN'!$D$29) | E37: =('ENG_SCEN'!$E$28*'ENG_SCEN'!$E$29)/('ENG_SCEN'!$D$28*'ENG_SCEN'!$D$29) | F37: =('ENG_SCEN'!$F$28*'ENG_SCEN'!$F$29)/('ENG_SCEN'!$D$28*'ENG_SCEN'!$D$29) | G37: =('ENG_SCEN'!$G$28*'ENG_SCEN'!$G$29)/('ENG_SCEN'!$D$28*'ENG_SCEN'!$D$29) | H37: =('ENG_SCEN'!$H$28*'ENG_SCEN'!$H$29)/('ENG_SCEN'!$D$28*'ENG_SCEN'!$D$29) | I37: =('ENG_SCEN'!$I$28*'ENG_SCEN'!$I$29)/('ENG_SCEN'!$D$28*'ENG_SCEN'!$D$29) | J37: =('ENG_SCEN'!$J$28*'ENG_SCEN'!$J$29)/('ENG_SCEN'!$D$28*'ENG_SCEN'!$D$29) | K37: =('ENG_SCEN'!$K$28*'ENG_SCEN'!$K$29)/('ENG_SCEN'!$D$28*'ENG_SCEN'!$D$29) | L37: =('ENG_SCEN'!$L$28*'ENG_SCEN'!$L$29)/('ENG_SCEN'!$D$28*'ENG_SCEN'!$D$29) | M37: =('ENG_SCEN'!$M$28*'ENG_SCEN'!$M$29)/('ENG_SCEN'!$D$28*'ENG_SCEN'!$D$29) | N37: =('ENG_SCEN'!$N$28*'ENG_SCEN'!$N$29)/('ENG_SCEN'!$D$28*'ENG_SCEN'!$D$29) | O37: =('ENG_SCEN'!$O$28*'ENG_SCEN'!$O$29)/('ENG_SCEN'!$D$28*'ENG_SCEN'!$D$29) | P37: =('ENG_SCEN'!$P$28*'ENG_SCEN'!$P$29)/('ENG_SCEN'!$D$28*'ENG_SCEN'!$D$29)
A39: د) مدل سایهٔ سه سناریو (پایه / خوش‌بینانه / بدبینانه)
A40: توضیح: مدل تفصیلی برای «سناریوی فعال» اجرا می‌شود؛ این مدل سایه با استفاده از نسبت‌های ساختاریِ استخراج‌شده از همان مدل تفصیلی (فرمول‌محور، بدون عدد ثابت) شاخص‌های هر سه سناریو را هم‌زمان محاسبه می‌کند.
A41: سناریوی 1: پایه
A42: [1] حجم فروش محصولات (تن) | B42: SB1.vol | C42: تن | D42: ='ENG_OPS'!$D$82*'IN_SCEN'!$D$13 | E42: ='ENG_OPS'!$E$82*'IN_SCEN'!$D$13 | F42: ='ENG_OPS'!$F$82*'IN_SCEN'!$D$13 | G42: ='ENG_OPS'!$G$82*'IN_SCEN'!$D$13 | H42: ='ENG_OPS'!$H$82*'IN_SCEN'!$D$13 | I42: ='ENG_OPS'!$I$82*'IN_SCEN'!$D$13 | J42: ='ENG_OPS'!$J$82*'IN_SCEN'!$D$13 | K42: ='ENG_OPS'!$K$82*'IN_SCEN'!$D$13 | L42: ='ENG_OPS'!$L$82*'IN_SCEN'!$D$13 | M42: ='ENG_OPS'!$M$82*'IN_SCEN'!$D$13 | N42: ='ENG_OPS'!$N$82*'IN_SCEN'!$D$13 | O42: ='ENG_OPS'!$O$82*'IN_SCEN'!$D$13 | P42: ='ENG_OPS'!$P$82*'IN_SCEN'!$D$13
A43: [1] درآمد خالص هر تن | B43: SB1.price | C43: میلیون ریال/تن | D43: ='ENG_OPS'!$D$83*'IN_SCEN'!$D$14 | E43: ='ENG_OPS'!$E$83*'IN_SCEN'!$D$14 | F43: ='ENG_OPS'!$F$83*'IN_SCEN'!$D$14 | G43: ='ENG_OPS'!$G$83*'IN_SCEN'!$D$14 | H43: ='ENG_OPS'!$H$83*'IN_SCEN'!$D$14 | I43: ='ENG_OPS'!$I$83*'IN_SCEN'!$D$14 | J43: ='ENG_OPS'!$J$83*'IN_SCEN'!$D$14 | K43: ='ENG_OPS'!$K$83*'IN_SCEN'!$D$14 | L43: ='ENG_OPS'!$L$83*'IN_SCEN'!$D$14 | M43: ='ENG_OPS'!$M$83*'IN_SCEN'!$D$14 | N43: ='ENG_OPS'!$N$83*'IN_SCEN'!$D$14 | O43: ='ENG_OPS'!$O$83*'IN_SCEN'!$D$14 | P43: ='ENG_OPS'!$P$83*'IN_SCEN'!$D$14
A44: [1] درآمد خالص | B44: SB1.rev | C44: میلیون ریال | D44: ='ENG_SCEN'!$D$42*'ENG_SCEN'!$D$43 | E44: ='ENG_SCEN'!$E$42*'ENG_SCEN'!$E$43 | F44: ='ENG_SCEN'!$F$42*'ENG_SCEN'!$F$43 | G44: ='ENG_SCEN'!$G$42*'ENG_SCEN'!$G$43 | H44: ='ENG_SCEN'!$H$42*'ENG_SCEN'!$H$43 | I44: ='ENG_SCEN'!$I$42*'ENG_SCEN'!$I$43 | J44: ='ENG_SCEN'!$J$42*'ENG_SCEN'!$J$43 | K44: ='ENG_SCEN'!$K$42*'ENG_SCEN'!$K$43 | L44: ='ENG_SCEN'!$L$42*'ENG_SCEN'!$L$43 | M44: ='ENG_SCEN'!$M$42*'ENG_SCEN'!$M$43 | N44: ='ENG_SCEN'!$N$42*'ENG_SCEN'!$N$43 | O44: ='ENG_SCEN'!$O$42*'ENG_SCEN'!$O$43 | P44: ='ENG_SCEN'!$P$42*'ENG_SCEN'!$P$43
A45: [1] هزینه مواد اولیه | B45: SB1.rm | C45: میلیون ریال | D45: ='ENG_COST'!$D$264*'IN_SCEN'!$D$13*'IN_SCEN'!$D$15 | E45: ='ENG_COST'!$E$264*'IN_SCEN'!$D$13*'IN_SCEN'!$D$15 | F45: ='ENG_COST'!$F$264*'IN_SCEN'!$D$13*'IN_SCEN'!$D$15 | G45: ='ENG_COST'!$G$264*'IN_SCEN'!$D$13*'IN_SCEN'!$D$15 | H45: ='ENG_COST'!$H$264*'IN_SCEN'!$D$13*'IN_SCEN'!$D$15 | I45: ='ENG_COST'!$I$264*'IN_SCEN'!$D$13*'IN_SCEN'!$D$15 | J45: ='ENG_COST'!$J$264*'IN_SCEN'!$D$13*'IN_SCEN'!$D$15 | K45: ='ENG_COST'!$K$264*'IN_SCEN'!$D$13*'IN_SCEN'!$D$15 | L45: ='ENG_COST'!$L$264*'IN_SCEN'!$D$13*'IN_SCEN'!$D$15 | M45: ='ENG_COST'!$M$264*'IN_SCEN'!$D$13*'IN_SCEN'!$D$15 | N45: ='ENG_COST'!$N$264*'IN_SCEN'!$D$13*'IN_SCEN'!$D$15 | O45: ='ENG_COST'!$O$264*'IN_SCEN'!$D$13*'IN_SCEN'!$D$15 | P45: ='ENG_COST'!$P$264*'IN_SCEN'!$D$13*'IN_SCEN'!$D$15
A46: [1] سایر هزینه‌های متغیر | B46: SB1.var | C46: میلیون ریال | D46: ='ENG_COST'!$D$265*'IN_SCEN'!$D$13*'IN_SCEN'!$D$16 | E46: ='ENG_COST'!$E$265*'IN_SCEN'!$D$13*'IN_SCEN'!$D$16 | F46: ='ENG_COST'!$F$265*'IN_SCEN'!$D$13*'IN_SCEN'!$D$16 | G46: ='ENG_COST'!$G$265*'IN_SCEN'!$D$13*'IN_SCEN'!$D$16 | H46: ='ENG_COST'!$H$265*'IN_SCEN'!$D$13*'IN_SCEN'!$D$16 | I46: ='ENG_COST'!$I$265*'IN_SCEN'!$D$13*'IN_SCEN'!$D$16 | J46: ='ENG_COST'!$J$265*'IN_SCEN'!$D$13*'IN_SCEN'!$D$16 | K46: ='ENG_COST'!$K$265*'IN_SCEN'!$D$13*'IN_SCEN'!$D$16 | L46: ='ENG_COST'!$L$265*'IN_SCEN'!$D$13*'IN_SCEN'!$D$16 | M46: ='ENG_COST'!$M$265*'IN_SCEN'!$D$13*'IN_SCEN'!$D$16 | N46: ='ENG_COST'!$N$265*'IN_SCEN'!$D$13*'IN_SCEN'!$D$16 | O46: ='ENG_COST'!$O$265*'IN_SCEN'!$D$13*'IN_SCEN'!$D$16 | P46: ='ENG_COST'!$P$265*'IN_SCEN'!$D$13*'IN_SCEN'!$D$16
A47: [1] هزینه‌های ثابت نقدی | B47: SB1.fix | C47: میلیون ریال | D47: ='ENG_COST'!$D$268*'IN_SCEN'!$D$17 | E47: ='ENG_COST'!$E$268*'IN_SCEN'!$D$17 | F47: ='ENG_COST'!$F$268*'IN_SCEN'!$D$17 | G47: ='ENG_COST'!$G$268*'IN_SCEN'!$D$17 | H47: ='ENG_COST'!$H$268*'IN_SCEN'!$D$17 | I47: ='ENG_COST'!$I$268*'IN_SCEN'!$D$17 | J47: ='ENG_COST'!$J$268*'IN_SCEN'!$D$17 | K47: ='ENG_COST'!$K$268*'IN_SCEN'!$D$17 | L47: ='ENG_COST'!$L$268*'IN_SCEN'!$D$17 | M47: ='ENG_COST'!$M$268*'IN_SCEN'!$D$17 | N47: ='ENG_COST'!$N$268*'IN_SCEN'!$D$17 | O47: ='ENG_COST'!$O$268*'IN_SCEN'!$D$17 | P47: ='ENG_COST'!$P$268*'IN_SCEN'!$D$17
A48: [1] استهلاک | B48: SB1.dep | C48: میلیون ریال | D48: ='ENG_CAPEX'!$D$81*'IN_SCEN'!$D$18 | E48: ='ENG_CAPEX'!$E$81*'IN_SCEN'!$D$18 | F48: ='ENG_CAPEX'!$F$81*'IN_SCEN'!$D$18 | G48: ='ENG_CAPEX'!$G$81*'IN_SCEN'!$D$18 | H48: ='ENG_CAPEX'!$H$81*'IN_SCEN'!$D$18 | I48: ='ENG_CAPEX'!$I$81*'IN_SCEN'!$D$18 | J48: ='ENG_CAPEX'!$J$81*'IN_SCEN'!$D$18 | K48: ='ENG_CAPEX'!$K$81*'IN_SCEN'!$D$18 | L48: ='ENG_CAPEX'!$L$81*'IN_SCEN'!$D$18 | M48: ='ENG_CAPEX'!$M$81*'IN_SCEN'!$D$18 | N48: ='ENG_CAPEX'!$N$81*'IN_SCEN'!$D$18 | O48: ='ENG_CAPEX'!$O$81*'IN_SCEN'!$D$18 | P48: ='ENG_CAPEX'!$P$81*'IN_SCEN'!$D$18
A49: [1] EBITDA | B49: SB1.ebitda | C49: میلیون ریال | D49: ='ENG_SCEN'!$D$44-'ENG_SCEN'!$D$45-'ENG_SCEN'!$D$46-'ENG_SCEN'!$D$47 | E49: ='ENG_SCEN'!$E$44-'ENG_SCEN'!$E$45-'ENG_SCEN'!$E$46-'ENG_SCEN'!$E$47 | F49: ='ENG_SCEN'!$F$44-'ENG_SCEN'!$F$45-'ENG_SCEN'!$F$46-'ENG_SCEN'!$F$47 | G49: ='ENG_SCEN'!$G$44-'ENG_SCEN'!$G$45-'ENG_SCEN'!$G$46-'ENG_SCEN'!$G$47 | H49: ='ENG_SCEN'!$H$44-'ENG_SCEN'!$H$45-'ENG_SCEN'!$H$46-'ENG_SCEN'!$H$47 | I49: ='ENG_SCEN'!$I$44-'ENG_SCEN'!$I$45-'ENG_SCEN'!$I$46-'ENG_SCEN'!$I$47 | J49: ='ENG_SCEN'!$J$44-'ENG_SCEN'!$J$45-'ENG_SCEN'!$J$46-'ENG_SCEN'!$J$47 | K49: ='ENG_SCEN'!$K$44-'ENG_SCEN'!$K$45-'ENG_SCEN'!$K$46-'ENG_SCEN'!$K$47 | L49: ='ENG_SCEN'!$L$44-'ENG_SCEN'!$L$45-'ENG_SCEN'!$L$46-'ENG_SCEN'!$L$47 | M49: ='ENG_SCEN'!$M$44-'ENG_SCEN'!$M$45-'ENG_SCEN'!$M$46-'ENG_SCEN'!$M$47 | N49: ='ENG_SCEN'!$N$44-'ENG_SCEN'!$N$45-'ENG_SCEN'!$N$46-'ENG_SCEN'!$N$47 | O49: ='ENG_SCEN'!$O$44-'ENG_SCEN'!$O$45-'ENG_SCEN'!$O$46-'ENG_SCEN'!$O$47 | P49: ='ENG_SCEN'!$P$44-'ENG_SCEN'!$P$45-'ENG_SCEN'!$P$46-'ENG_SCEN'!$P$47
A50: [1] EBIT | B50: SB1.ebit | C50: میلیون ریال | D50: ='ENG_SCEN'!$D$49-'ENG_SCEN'!$D$48 | E50: ='ENG_SCEN'!$E$49-'ENG_SCEN'!$E$48 | F50: ='ENG_SCEN'!$F$49-'ENG_SCEN'!$F$48 | G50: ='ENG_SCEN'!$G$49-'ENG_SCEN'!$G$48 | H50: ='ENG_SCEN'!$H$49-'ENG_SCEN'!$H$48 | I50: ='ENG_SCEN'!$I$49-'ENG_SCEN'!$I$48 | J50: ='ENG_SCEN'!$J$49-'ENG_SCEN'!$J$48 | K50: ='ENG_SCEN'!$K$49-'ENG_SCEN'!$K$48 | L50: ='ENG_SCEN'!$L$49-'ENG_SCEN'!$L$48 | M50: ='ENG_SCEN'!$M$49-'ENG_SCEN'!$M$48 | N50: ='ENG_SCEN'!$N$49-'ENG_SCEN'!$N$48 | O50: ='ENG_SCEN'!$O$49-'ENG_SCEN'!$O$48 | P50: ='ENG_SCEN'!$P$49-'ENG_SCEN'!$P$48
A51: [1] مالیات | B51: SB1.tax | C51: میلیون ریال | D51: =MAX(0,'ENG_SCEN'!$D$50)*'IN_MACRO'!$D$14 | E51: =MAX(0,'ENG_SCEN'!$E$50)*'IN_MACRO'!$D$14 | F51: =MAX(0,'ENG_SCEN'!$F$50)*'IN_MACRO'!$D$14 | G51: =MAX(0,'ENG_SCEN'!$G$50)*'IN_MACRO'!$D$14 | H51: =MAX(0,'ENG_SCEN'!$H$50)*'IN_MACRO'!$D$14 | I51: =MAX(0,'ENG_SCEN'!$I$50)*'IN_MACRO'!$D$14 | J51: =MAX(0,'ENG_SCEN'!$J$50)*'IN_MACRO'!$D$14 | K51: =MAX(0,'ENG_SCEN'!$K$50)*'IN_MACRO'!$D$14 | L51: =MAX(0,'ENG_SCEN'!$L$50)*'IN_MACRO'!$D$14 | M51: =MAX(0,'ENG_SCEN'!$M$50)*'IN_MACRO'!$D$14 | N51: =MAX(0,'ENG_SCEN'!$N$50)*'IN_MACRO'!$D$14 | O51: =MAX(0,'ENG_SCEN'!$O$50)*'IN_MACRO'!$D$14 | P51: =MAX(0,'ENG_SCEN'!$P$50)*'IN_MACRO'!$D$14
A52: [1] NOPAT | B52: SB1.nopat | C52: میلیون ریال | D52: ='ENG_SCEN'!$D$50-'ENG_SCEN'!$D$51 | E52: ='ENG_SCEN'!$E$50-'ENG_SCEN'!$E$51 | F52: ='ENG_SCEN'!$F$50-'ENG_SCEN'!$F$51 | G52: ='ENG_SCEN'!$G$50-'ENG_SCEN'!$G$51 | H52: ='ENG_SCEN'!$H$50-'ENG_SCEN'!$H$51 | I52: ='ENG_SCEN'!$I$50-'ENG_SCEN'!$I$51 | J52: ='ENG_SCEN'!$J$50-'ENG_SCEN'!$J$51 | K52: ='ENG_SCEN'!$K$50-'ENG_SCEN'!$K$51 | L52: ='ENG_SCEN'!$L$50-'ENG_SCEN'!$L$51 | M52: ='ENG_SCEN'!$M$50-'ENG_SCEN'!$M$51 | N52: ='ENG_SCEN'!$N$50-'ENG_SCEN'!$N$51 | O52: ='ENG_SCEN'!$O$50-'ENG_SCEN'!$O$51 | P52: ='ENG_SCEN'!$P$50-'ENG_SCEN'!$P$51
A53: [1] CAPEX و جایگزینی | B53: SB1.capex | C53: میلیون ریال | D53: =('ENG_CAPEX'!$D$21+'ENG_CAPEX'!$D$42)*'IN_SCEN'!$D$18 | E53: =('ENG_CAPEX'!$E$21+'ENG_CAPEX'!$E$42)*'IN_SCEN'!$D$18 | F53: =('ENG_CAPEX'!$F$21+'ENG_CAPEX'!$F$42)*'IN_SCEN'!$D$18 | G53: =('ENG_CAPEX'!$G$21+'ENG_CAPEX'!$G$42)*'IN_SCEN'!$D$18 | H53: =('ENG_CAPEX'!$H$21+'ENG_CAPEX'!$H$42)*'IN_SCEN'!$D$18 | I53: =('ENG_CAPEX'!$I$21+'ENG_CAPEX'!$I$42)*'IN_SCEN'!$D$18 | J53: =('ENG_CAPEX'!$J$21+'ENG_CAPEX'!$J$42)*'IN_SCEN'!$D$18 | K53: =('ENG_CAPEX'!$K$21+'ENG_CAPEX'!$K$42)*'IN_SCEN'!$D$18 | L53: =('ENG_CAPEX'!$L$21+'ENG_CAPEX'!$L$42)*'IN_SCEN'!$D$18 | M53: =('ENG_CAPEX'!$M$21+'ENG_CAPEX'!$M$42)*'IN_SCEN'!$D$18 | N53: =('ENG_CAPEX'!$N$21+'ENG_CAPEX'!$N$42)*'IN_SCEN'!$D$18 | O53: =('ENG_CAPEX'!$O$21+'ENG_CAPEX'!$O$42)*'IN_SCEN'!$D$18 | P53: =('ENG_CAPEX'!$P$21+'ENG_CAPEX'!$P$42)*'IN_SCEN'!$D$18
A54: [1] تغییرات سرمایه در گردش | B54: SB1.dwc | C54: میلیون ریال | D54: ='ENG_WC'!$D$19*'IN_SCEN'!$D$13*'IN_SCEN'!$D$14 | E54: ='ENG_WC'!$E$19*'IN_SCEN'!$D$13*'IN_SCEN'!$D$14 | F54: ='ENG_WC'!$F$19*'IN_SCEN'!$D$13*'IN_SCEN'!$D$14 | G54: ='ENG_WC'!$G$19*'IN_SCEN'!$D$13*'IN_SCEN'!$D$14 | H54: ='ENG_WC'!$H$19*'IN_SCEN'!$D$13*'IN_SCEN'!$D$14 | I54: ='ENG_WC'!$I$19*'IN_SCEN'!$D$13*'IN_SCEN'!$D$14 | J54: ='ENG_WC'!$J$19*'IN_SCEN'!$D$13*'IN_SCEN'!$D$14 | K54: ='ENG_WC'!$K$19*'IN_SCEN'!$D$13*'IN_SCEN'!$D$14 | L54: ='ENG_WC'!$L$19*'IN_SCEN'!$D$13*'IN_SCEN'!$D$14 | M54: ='ENG_WC'!$M$19*'IN_SCEN'!$D$13*'IN_SCEN'!$D$14 | N54: ='ENG_WC'!$N$19*'IN_SCEN'!$D$13*'IN_SCEN'!$D$14 | O54: ='ENG_WC'!$O$19*'IN_SCEN'!$D$13*'IN_SCEN'!$D$14 | P54: ='ENG_WC'!$P$19*'IN_SCEN'!$D$13*'IN_SCEN'!$D$14
A55: [1] جریان نقد آزاد (FCFF) | B55: SB1.fcf | C55: میلیون ریال | D55: ='ENG_SCEN'!$D$52+'ENG_SCEN'!$D$48-'ENG_SCEN'!$D$53-'ENG_SCEN'!$D$54 | E55: ='ENG_SCEN'!$E$52+'ENG_SCEN'!$E$48-'ENG_SCEN'!$E$53-'ENG_SCEN'!$E$54 | F55: ='ENG_SCEN'!$F$52+'ENG_SCEN'!$F$48-'ENG_SCEN'!$F$53-'ENG_SCEN'!$F$54 | G55: ='ENG_SCEN'!$G$52+'ENG_SCEN'!$G$48-'ENG_SCEN'!$G$53-'ENG_SCEN'!$G$54 | H55: ='ENG_SCEN'!$H$52+'ENG_SCEN'!$H$48-'ENG_SCEN'!$H$53-'ENG_SCEN'!$H$54 | I55: ='ENG_SCEN'!$I$52+'ENG_SCEN'!$I$48-'ENG_SCEN'!$I$53-'ENG_SCEN'!$I$54 | J55: ='ENG_SCEN'!$J$52+'ENG_SCEN'!$J$48-'ENG_SCEN'!$J$53-'ENG_SCEN'!$J$54 | K55: ='ENG_SCEN'!$K$52+'ENG_SCEN'!$K$48-'ENG_SCEN'!$K$53-'ENG_SCEN'!$K$54 | L55: ='ENG_SCEN'!$L$52+'ENG_SCEN'!$L$48-'ENG_SCEN'!$L$53-'ENG_SCEN'!$L$54 | M55: ='ENG_SCEN'!$M$52+'ENG_SCEN'!$M$48-'ENG_SCEN'!$M$53-'ENG_SCEN'!$M$54 | N55: ='ENG_SCEN'!$N$52+'ENG_SCEN'!$N$48-'ENG_SCEN'!$N$53-'ENG_SCEN'!$N$54 | O55: ='ENG_SCEN'!$O$52+'ENG_SCEN'!$O$48-'ENG_SCEN'!$O$53-'ENG_SCEN'!$O$54 | P55: ='ENG_SCEN'!$P$52+'ENG_SCEN'!$P$48-'ENG_SCEN'!$P$53-'ENG_SCEN'!$P$54
A56: [1] FCFF تکرارپذیر | B56: SB1.fcf_rep | C56: میلیون ریال | D56: ='ENG_SCEN'!$D$52+'ENG_SCEN'!$D$48-'ENG_SCEN'!$D$54 | E56: ='ENG_SCEN'!$E$52+'ENG_SCEN'!$E$48-'ENG_SCEN'!$E$54 | F56: ='ENG_SCEN'!$F$52+'ENG_SCEN'!$F$48-'ENG_SCEN'!$F$54 | G56: ='ENG_SCEN'!$G$52+'ENG_SCEN'!$G$48-'ENG_SCEN'!$G$54 | H56: ='ENG_SCEN'!$H$52+'ENG_SCEN'!$H$48-'ENG_SCEN'!$H$54 | I56: ='ENG_SCEN'!$I$52+'ENG_SCEN'!$I$48-'ENG_SCEN'!$I$54 | J56: ='ENG_SCEN'!$J$52+'ENG_SCEN'!$J$48-'ENG_SCEN'!$J$54 | K56: ='ENG_SCEN'!$K$52+'ENG_SCEN'!$K$48-'ENG_SCEN'!$K$54 | L56: ='ENG_SCEN'!$L$52+'ENG_SCEN'!$L$48-'ENG_SCEN'!$L$54 | M56: ='ENG_SCEN'!$M$52+'ENG_SCEN'!$M$48-'ENG_SCEN'!$M$54 | N56: ='ENG_SCEN'!$N$52+'ENG_SCEN'!$N$48-'ENG_SCEN'!$N$54 | O56: ='ENG_SCEN'!$O$52+'ENG_SCEN'!$O$48-'ENG_SCEN'!$O$54 | P56: ='ENG_SCEN'!$P$52+'ENG_SCEN'!$P$48-'ENG_SCEN'!$P$54
A57: [1] FCFF تجمعی | B57: SB1.cum | C57: میلیون ریال | D57: ='ENG_SCEN'!$D$55 | E57: ='ENG_SCEN'!$D$57+'ENG_SCEN'!$E$55 | F57: ='ENG_SCEN'!$E$57+'ENG_SCEN'!$F$55 | G57: ='ENG_SCEN'!$F$57+'ENG_SCEN'!$G$55 | H57: ='ENG_SCEN'!$G$57+'ENG_SCEN'!$H$55 | I57: ='ENG_SCEN'!$H$57+'ENG_SCEN'!$I$55 | J57: ='ENG_SCEN'!$I$57+'ENG_SCEN'!$J$55 | K57: ='ENG_SCEN'!$J$57+'ENG_SCEN'!$K$55 | L57: ='ENG_SCEN'!$K$57+'ENG_SCEN'!$L$55 | M57: ='ENG_SCEN'!$L$57+'ENG_SCEN'!$M$55 | N57: ='ENG_SCEN'!$M$57+'ENG_SCEN'!$N$55 | O57: ='ENG_SCEN'!$N$57+'ENG_SCEN'!$O$55 | P57: ='ENG_SCEN'!$O$57+'ENG_SCEN'!$P$55
A58: [1] نرخ تنزیل (WACC) | B58: SB1.wacc | C58: درصد | D58: ='ENG_DCF'!$D$14+'IN_SCEN'!$D$20 | E58: ='ENG_DCF'!$E$14+'IN_SCEN'!$D$20 | F58: ='ENG_DCF'!$F$14+'IN_SCEN'!$D$20 | G58: ='ENG_DCF'!$G$14+'IN_SCEN'!$D$20 | H58: ='ENG_DCF'!$H$14+'IN_SCEN'!$D$20 | I58: ='ENG_DCF'!$I$14+'IN_SCEN'!$D$20 | J58: ='ENG_DCF'!$J$14+'IN_SCEN'!$D$20 | K58: ='ENG_DCF'!$K$14+'IN_SCEN'!$D$20 | L58: ='ENG_DCF'!$L$14+'IN_SCEN'!$D$20 | M58: ='ENG_DCF'!$M$14+'IN_SCEN'!$D$20 | N58: ='ENG_DCF'!$N$14+'IN_SCEN'!$D$20 | O58: ='ENG_DCF'!$O$14+'IN_SCEN'!$D$20 | P58: ='ENG_DCF'!$P$14+'IN_SCEN'!$D$20
A59: [1] ضریب تنزیل | B59: SB1.df | C59: ضریب | D59: =1 | E59: ='ENG_SCEN'!$D$59/(1+'ENG_SCEN'!$E$58) | F59: ='ENG_SCEN'!$E$59/(1+'ENG_SCEN'!$F$58) | G59: ='ENG_SCEN'!$F$59/(1+'ENG_SCEN'!$G$58) | H59: ='ENG_SCEN'!$G$59/(1+'ENG_SCEN'!$H$58) | I59: ='ENG_SCEN'!$H$59/(1+'ENG_SCEN'!$I$58) | J59: ='ENG_SCEN'!$I$59/(1+'ENG_SCEN'!$J$58) | K59: ='ENG_SCEN'!$J$59/(1+'ENG_SCEN'!$K$58) | L59: ='ENG_SCEN'!$K$59/(1+'ENG_SCEN'!$L$58) | M59: ='ENG_SCEN'!$L$59/(1+'ENG_SCEN'!$M$58) | N59: ='ENG_SCEN'!$M$59/(1+'ENG_SCEN'!$N$58) | O59: ='ENG_SCEN'!$N$59/(1+'ENG_SCEN'!$O$58) | P59: ='ENG_SCEN'!$O$59/(1+'ENG_SCEN'!$P$58)
A60: [1] ارزش فعلی FCFF | B60: SB1.pv | C60: میلیون ریال | D60: ='ENG_SCEN'!$D$55*'ENG_SCEN'!$D$59 | E60: ='ENG_SCEN'!$E$55*'ENG_SCEN'!$E$59 | F60: ='ENG_SCEN'!$F$55*'ENG_SCEN'!$F$59 | G60: ='ENG_SCEN'!$G$55*'ENG_SCEN'!$G$59 | H60: ='ENG_SCEN'!$H$55*'ENG_SCEN'!$H$59 | I60: ='ENG_SCEN'!$I$55*'ENG_SCEN'!$I$59 | J60: ='ENG_SCEN'!$J$55*'ENG_SCEN'!$J$59 | K60: ='ENG_SCEN'!$K$55*'ENG_SCEN'!$K$59 | L60: ='ENG_SCEN'!$L$55*'ENG_SCEN'!$L$59 | M60: ='ENG_SCEN'!$M$55*'ENG_SCEN'!$M$59 | N60: ='ENG_SCEN'!$N$55*'ENG_SCEN'!$N$59 | O60: ='ENG_SCEN'!$O$55*'ENG_SCEN'!$O$59 | P60: ='ENG_SCEN'!$P$55*'ENG_SCEN'!$P$59
A61: [1] ارزش فعلی تجمعی | B61: SB1.pvc | C61: میلیون ریال | D61: ='ENG_SCEN'!$D$60 | E61: ='ENG_SCEN'!$D$61+'ENG_SCEN'!$E$60 | F61: ='ENG_SCEN'!$E$61+'ENG_SCEN'!$F$60 | G61: ='ENG_SCEN'!$F$61+'ENG_SCEN'!$G$60 | H61: ='ENG_SCEN'!$G$61+'ENG_SCEN'!$H$60 | I61: ='ENG_SCEN'!$H$61+'ENG_SCEN'!$I$60 | J61: ='ENG_SCEN'!$I$61+'ENG_SCEN'!$J$60 | K61: ='ENG_SCEN'!$J$61+'ENG_SCEN'!$K$60 | L61: ='ENG_SCEN'!$K$61+'ENG_SCEN'!$L$60 | M61: ='ENG_SCEN'!$L$61+'ENG_SCEN'!$M$60 | N61: ='ENG_SCEN'!$M$61+'ENG_SCEN'!$N$60 | O61: ='ENG_SCEN'!$N$61+'ENG_SCEN'!$O$60 | P61: ='ENG_SCEN'!$O$61+'ENG_SCEN'!$P$60
A62: [1] ارزش پایانی | B62: SB1.tv | C62: میلیون ریال | D62: =IF('IN_MACRO'!$D$23<'IN_MACRO'!$D$11,0,IF('IN_MACRO'!$D$19=1,MAX(0,'ENG_SCEN'!$P$56)*(1+'IN_MACRO'!$D$18)/MAX(0.005,'ENG_SCEN'!$P$58-'IN_MACRO'!$D$18),'ENG_SCEN'!$P$49*'IN_MACRO'!$D$20)) | E62: =IF('IN_MACRO'!$E$23<'IN_MACRO'!$D$11,0,IF('IN_MACRO'!$D$19=1,MAX(0,'ENG_SCEN'!$P$56)*(1+'IN_MACRO'!$D$18)/MAX(0.005,'ENG_SCEN'!$P$58-'IN_MACRO'!$D$18),'ENG_SCEN'!$P$49*'IN_MACRO'!$D$20)) | F62: =IF('IN_MACRO'!$F$23<'IN_MACRO'!$D$11,0,IF('IN_MACRO'!$D$19=1,MAX(0,'ENG_SCEN'!$P$56)*(1+'IN_MACRO'!$D$18)/MAX(0.005,'ENG_SCEN'!$P$58-'IN_MACRO'!$D$18),'ENG_SCEN'!$P$49*'IN_MACRO'!$D$20)) | G62: =IF('IN_MACRO'!$G$23<'IN_MACRO'!$D$11,0,IF('IN_MACRO'!$D$19=1,MAX(0,'ENG_SCEN'!$P$56)*(1+'IN_MACRO'!$D$18)/MAX(0.005,'ENG_SCEN'!$P$58-'IN_MACRO'!$D$18),'ENG_SCEN'!$P$49*'IN_MACRO'!$D$20)) | H62: =IF('IN_MACRO'!$H$23<'IN_MACRO'!$D$11,0,IF('IN_MACRO'!$D$19=1,MAX(0,'ENG_SCEN'!$P$56)*(1+'IN_MACRO'!$D$18)/MAX(0.005,'ENG_SCEN'!$P$58-'IN_MACRO'!$D$18),'ENG_SCEN'!$P$49*'IN_MACRO'!$D$20)) | I62: =IF('IN_MACRO'!$I$23<'IN_MACRO'!$D$11,0,IF('IN_MACRO'!$D$19=1,MAX(0,'ENG_SCEN'!$P$56)*(1+'IN_MACRO'!$D$18)/MAX(0.005,'ENG_SCEN'!$P$58-'IN_MACRO'!$D$18),'ENG_SCEN'!$P$49*'IN_MACRO'!$D$20)) | J62: =IF('IN_MACRO'!$J$23<'IN_MACRO'!$D$11,0,IF('IN_MACRO'!$D$19=1,MAX(0,'ENG_SCEN'!$P$56)*(1+'IN_MACRO'!$D$18)/MAX(0.005,'ENG_SCEN'!$P$58-'IN_MACRO'!$D$18),'ENG_SCEN'!$P$49*'IN_MACRO'!$D$20)) | K62: =IF('IN_MACRO'!$K$23<'IN_MACRO'!$D$11,0,IF('IN_MACRO'!$D$19=1,MAX(0,'ENG_SCEN'!$P$56)*(1+'IN_MACRO'!$D$18)/MAX(0.005,'ENG_SCEN'!$P$58-'IN_MACRO'!$D$18),'ENG_SCEN'!$P$49*'IN_MACRO'!$D$20)) | L62: =IF('IN_MACRO'!$L$23<'IN_MACRO'!$D$11,0,IF('IN_MACRO'!$D$19=1,MAX(0,'ENG_SCEN'!$P$56)*(1+'IN_MACRO'!$D$18)/MAX(0.005,'ENG_SCEN'!$P$58-'IN_MACRO'!$D$18),'ENG_SCEN'!$P$49*'IN_MACRO'!$D$20)) | M62: =IF('IN_MACRO'!$M$23<'IN_MACRO'!$D$11,0,IF('IN_MACRO'!$D$19=1,MAX(0,'ENG_SCEN'!$P$56)*(1+'IN_MACRO'!$D$18)/MAX(0.005,'ENG_SCEN'!$P$58-'IN_MACRO'!$D$18),'ENG_SCEN'!$P$49*'IN_MACRO'!$D$20)) | N62: =IF('IN_MACRO'!$N$23<'IN_MACRO'!$D$11,0,IF('IN_MACRO'!$D$19=1,MAX(0,'ENG_SCEN'!$P$56)*(1+'IN_MACRO'!$D$18)/MAX(0.005,'ENG_SCEN'!$P$58-'IN_MACRO'!$D$18),'ENG_SCEN'!$P$49*'IN_MACRO'!$D$20)) | O62: =IF('IN_MACRO'!$O$23<'IN_MACRO'!$D$11,0,IF('IN_MACRO'!$D$19=1,MAX(0,'ENG_SCEN'!$P$56)*(1+'IN_MACRO'!$D$18)/MAX(0.005,'ENG_SCEN'!$P$58-'IN_MACRO'!$D$18),'ENG_SCEN'!$P$49*'IN_MACRO'!$D$20)) | P62: =IF('IN_MACRO'!$P$23<'IN_MACRO'!$D$11,0,IF('IN_MACRO'!$D$19=1,MAX(0,'ENG_SCEN'!$P$56)*(1+'IN_MACRO'!$D$18)/MAX(0.005,'ENG_SCEN'!$P$58-'IN_MACRO'!$D$18),'ENG_SCEN'!$P$49*'IN_MACRO'!$D$20))
A63: [1] ارزش فعلی ارزش پایانی | B63: SB1.pvtv | C63: میلیون ریال | D63: ='ENG_SCEN'!$D$62*'ENG_SCEN'!$D$59 | E63: ='ENG_SCEN'!$E$62*'ENG_SCEN'!$E$59 | F63: ='ENG_SCEN'!$F$62*'ENG_SCEN'!$F$59 | G63: ='ENG_SCEN'!$G$62*'ENG_SCEN'!$G$59 | H63: ='ENG_SCEN'!$H$62*'ENG_SCEN'!$H$59 | I63: ='ENG_SCEN'!$I$62*'ENG_SCEN'!$I$59 | J63: ='ENG_SCEN'!$J$62*'ENG_SCEN'!$J$59 | K63: ='ENG_SCEN'!$K$62*'ENG_SCEN'!$K$59 | L63: ='ENG_SCEN'!$L$62*'ENG_SCEN'!$L$59 | M63: ='ENG_SCEN'!$M$62*'ENG_SCEN'!$M$59 | N63: ='ENG_SCEN'!$N$62*'ENG_SCEN'!$N$59 | O63: ='ENG_SCEN'!$O$62*'ENG_SCEN'!$O$59 | P63: ='ENG_SCEN'!$P$62*'ENG_SCEN'!$P$59
A64: [1] جریان قابل بازدهی (FCF + TV) | B64: SB1.fcf_tv | C64: میلیون ریال | D64: ='ENG_SCEN'!$D$55+'ENG_SCEN'!$D$62 | E64: ='ENG_SCEN'!$E$55+'ENG_SCEN'!$E$62 | F64: ='ENG_SCEN'!$F$55+'ENG_SCEN'!$F$62 | G64: ='ENG_SCEN'!$G$55+'ENG_SCEN'!$G$62 | H64: ='ENG_SCEN'!$H$55+'ENG_SCEN'!$H$62 | I64: ='ENG_SCEN'!$I$55+'ENG_SCEN'!$I$62 | J64: ='ENG_SCEN'!$J$55+'ENG_SCEN'!$J$62 | K64: ='ENG_SCEN'!$K$55+'ENG_SCEN'!$K$62 | L64: ='ENG_SCEN'!$L$55+'ENG_SCEN'!$L$62 | M64: ='ENG_SCEN'!$M$55+'ENG_SCEN'!$M$62 | N64: ='ENG_SCEN'!$N$55+'ENG_SCEN'!$N$62 | O64: ='ENG_SCEN'!$O$55+'ENG_SCEN'!$O$62 | P64: ='ENG_SCEN'!$P$55+'ENG_SCEN'!$P$62
A65: [1] CFADS | B65: SB1.cfads | C65: میلیون ریال | D65: ='ENG_SCEN'!$D$49-'ENG_SCEN'!$D$51-'ENG_SCEN'!$D$54 | E65: ='ENG_SCEN'!$E$49-'ENG_SCEN'!$E$51-'ENG_SCEN'!$E$54 | F65: ='ENG_SCEN'!$F$49-'ENG_SCEN'!$F$51-'ENG_SCEN'!$F$54 | G65: ='ENG_SCEN'!$G$49-'ENG_SCEN'!$G$51-'ENG_SCEN'!$G$54 | H65: ='ENG_SCEN'!$H$49-'ENG_SCEN'!$H$51-'ENG_SCEN'!$H$54 | I65: ='ENG_SCEN'!$I$49-'ENG_SCEN'!$I$51-'ENG_SCEN'!$I$54 | J65: ='ENG_SCEN'!$J$49-'ENG_SCEN'!$J$51-'ENG_SCEN'!$J$54 | K65: ='ENG_SCEN'!$K$49-'ENG_SCEN'!$K$51-'ENG_SCEN'!$K$54 | L65: ='ENG_SCEN'!$L$49-'ENG_SCEN'!$L$51-'ENG_SCEN'!$L$54 | M65: ='ENG_SCEN'!$M$49-'ENG_SCEN'!$M$51-'ENG_SCEN'!$M$54 | N65: ='ENG_SCEN'!$N$49-'ENG_SCEN'!$N$51-'ENG_SCEN'!$N$54 | O65: ='ENG_SCEN'!$O$49-'ENG_SCEN'!$O$51-'ENG_SCEN'!$O$54 | P65: ='ENG_SCEN'!$P$49-'ENG_SCEN'!$P$51-'ENG_SCEN'!$P$54
A66: [1] خدمت دین | B66: SB1.debt_service | C66: میلیون ریال | D66: ='ENG_FCF'!$D$24+'ENG_FCF'!$D$20*('IN_FIN'!$D$25+'IN_SCEN'!$D$21)+'ENG_FCF'!$D$27 | E66: ='ENG_FCF'!$E$24+'ENG_FCF'!$E$20*('IN_FIN'!$D$25+'IN_SCEN'!$D$21)+'ENG_FCF'!$E$27 | F66: ='ENG_FCF'!$F$24+'ENG_FCF'!$F$20*('IN_FIN'!$D$25+'IN_SCEN'!$D$21)+'ENG_FCF'!$F$27 | G66: ='ENG_FCF'!$G$24+'ENG_FCF'!$G$20*('IN_FIN'!$D$25+'IN_SCEN'!$D$21)+'ENG_FCF'!$G$27 | H66: ='ENG_FCF'!$H$24+'ENG_FCF'!$H$20*('IN_FIN'!$D$25+'IN_SCEN'!$D$21)+'ENG_FCF'!$H$27 | I66: ='ENG_FCF'!$I$24+'ENG_FCF'!$I$20*('IN_FIN'!$D$25+'IN_SCEN'!$D$21)+'ENG_FCF'!$I$27 | J66: ='ENG_FCF'!$J$24+'ENG_FCF'!$J$20*('IN_FIN'!$D$25+'IN_SCEN'!$D$21)+'ENG_FCF'!$J$27 | K66: ='ENG_FCF'!$K$24+'ENG_FCF'!$K$20*('IN_FIN'!$D$25+'IN_SCEN'!$D$21)+'ENG_FCF'!$K$27 | L66: ='ENG_FCF'!$L$24+'ENG_FCF'!$L$20*('IN_FIN'!$D$25+'IN_SCEN'!$D$21)+'ENG_FCF'!$L$27 | M66: ='ENG_FCF'!$M$24+'ENG_FCF'!$M$20*('IN_FIN'!$D$25+'IN_SCEN'!$D$21)+'ENG_FCF'!$M$27 | N66: ='ENG_FCF'!$N$24+'ENG_FCF'!$N$20*('IN_FIN'!$D$25+'IN_SCEN'!$D$21)+'ENG_FCF'!$N$27 | O66: ='ENG_FCF'!$O$24+'ENG_FCF'!$O$20*('IN_FIN'!$D$25+'IN_SCEN'!$D$21)+'ENG_FCF'!$O$27 | P66: ='ENG_FCF'!$P$24+'ENG_FCF'!$P$20*('IN_FIN'!$D$25+'IN_SCEN'!$D$21)+'ENG_FCF'!$P$27
A67: [1] DSCR | B67: SB1.dscr | C67: ضریب | D67: =IFERROR('ENG_SCEN'!$D$65/'ENG_SCEN'!$D$66,"─") | E67: =IFERROR('ENG_SCEN'!$E$65/'ENG_SCEN'!$E$66,"─") | F67: =IFERROR('ENG_SCEN'!$F$65/'ENG_SCEN'!$F$66,"─") | G67: =IFERROR('ENG_SCEN'!$G$65/'ENG_SCEN'!$G$66,"─") | H67: =IFERROR('ENG_SCEN'!$H$65/'ENG_SCEN'!$H$66,"─") | I67: =IFERROR('ENG_SCEN'!$I$65/'ENG_SCEN'!$I$66,"─") | J67: =IFERROR('ENG_SCEN'!$J$65/'ENG_SCEN'!$J$66,"─") | K67: =IFERROR('ENG_SCEN'!$K$65/'ENG_SCEN'!$K$66,"─") | L67: =IFERROR('ENG_SCEN'!$L$65/'ENG_SCEN'!$L$66,"─") | M67: =IFERROR('ENG_SCEN'!$M$65/'ENG_SCEN'!$M$66,"─") | N67: =IFERROR('ENG_SCEN'!$N$65/'ENG_SCEN'!$N$66,"─") | O67: =IFERROR('ENG_SCEN'!$O$65/'ENG_SCEN'!$O$66,"─") | P67: =IFERROR('ENG_SCEN'!$P$65/'ENG_SCEN'!$P$66,"─")
A68: [1] ارزش فعلی خالص (NPV) | C68: میلیون ریال | D68: =SUM('ENG_SCEN'!$D$60:$P$60)+SUM('ENG_SCEN'!$D$63:$P$63)
A69: [1] IRR پروژه | C69: درصد | D69: =IFERROR(IRR('ENG_SCEN'!$D$64:$P$64),NA())
A70: [1] دوره بازپرداشت (سال) | C70: سال | D70: =IF(COUNTIF('ENG_SCEN'!$D$57:$P$57,"<0")=0,0,IF(COUNTIF('ENG_SCEN'!$D$57:$P$57,"<0")>=13,NA(),INDEX('IN_MACRO'!$D$23:$P$23,COUNTIF('ENG_SCEN'!$D$57:$P$57,"<0"))+(0-INDEX('ENG_SCEN'!$D$57:$P$57,COUNTIF('ENG_SCEN'!$D$57:$P$57,"<0")))/(INDEX('ENG_SCEN'!$D$57:$P$57,COUNTIF('ENG_SCEN'!$D$57:$P$57,"<0")+1)-INDEX('ENG_SCEN'!$D$57:$P$57,COUNTIF('ENG_SCEN'!$D$57:$P$57,"<0")))))
A71: [1] شاخص سودآوری | C71: ضریب | D71: =IFERROR((SUMIF('ENG_SCEN'!$D$60:$P$60,">0")+SUM('ENG_SCEN'!$D$63:$P$63))/ABS(SUMIF('ENG_SCEN'!$D$60:$P$60,"<0")),NA())
A72: [1] حداقل DSCR | C72: ضریب | D72: =IFERROR(IF(COUNT('ENG_SCEN'!$D$67:$P$67)=0,NA(),MIN('ENG_SCEN'!$D$67:$P$67)),NA())
A73: [1] میانگین DSCR دوره بازپرداخت | C73: ضریب | D73: =IFERROR(AVERAGEIF('ENG_SCEN'!$D$66:$P$66,">0",'ENG_SCEN'!$D$67:$P$67),NA())
A75: سناریوی 2: خوش‌بینانه
A76: [2] حجم فروش محصولات (تن) | B76: SB2.vol | C76: تن | D76: ='ENG_OPS'!$D$82*'IN_SCEN'!$E$13 | E76: ='ENG_OPS'!$E$82*'IN_SCEN'!$E$13 | F76: ='ENG_OPS'!$F$82*'IN_SCEN'!$E$13 | G76: ='ENG_OPS'!$G$82*'IN_SCEN'!$E$13 | H76: ='ENG_OPS'!$H$82*'IN_SCEN'!$E$13 | I76: ='ENG_OPS'!$I$82*'IN_SCEN'!$E$13 | J76: ='ENG_OPS'!$J$82*'IN_SCEN'!$E$13 | K76: ='ENG_OPS'!$K$82*'IN_SCEN'!$E$13 | L76: ='ENG_OPS'!$L$82*'IN_SCEN'!$E$13 | M76: ='ENG_OPS'!$M$82*'IN_SCEN'!$E$13 | N76: ='ENG_OPS'!$N$82*'IN_SCEN'!$E$13 | O76: ='ENG_OPS'!$O$82*'IN_SCEN'!$E$13 | P76: ='ENG_OPS'!$P$82*'IN_SCEN'!$E$13
A77: [2] درآمد خالص هر تن | B77: SB2.price | C77: میلیون ریال/تن | D77: ='ENG_OPS'!$D$83*'IN_SCEN'!$E$14 | E77: ='ENG_OPS'!$E$83*'IN_SCEN'!$E$14 | F77: ='ENG_OPS'!$F$83*'IN_SCEN'!$E$14 | G77: ='ENG_OPS'!$G$83*'IN_SCEN'!$E$14 | H77: ='ENG_OPS'!$H$83*'IN_SCEN'!$E$14 | I77: ='ENG_OPS'!$I$83*'IN_SCEN'!$E$14 | J77: ='ENG_OPS'!$J$83*'IN_SCEN'!$E$14 | K77: ='ENG_OPS'!$K$83*'IN_SCEN'!$E$14 | L77: ='ENG_OPS'!$L$83*'IN_SCEN'!$E$14 | M77: ='ENG_OPS'!$M$83*'IN_SCEN'!$E$14 | N77: ='ENG_OPS'!$N$83*'IN_SCEN'!$E$14 | O77: ='ENG_OPS'!$O$83*'IN_SCEN'!$E$14 | P77: ='ENG_OPS'!$P$83*'IN_SCEN'!$E$14
A78: [2] درآمد خالص | B78: SB2.rev | C78: میلیون ریال | D78: ='ENG_SCEN'!$D$76*'ENG_SCEN'!$D$77 | E78: ='ENG_SCEN'!$E$76*'ENG_SCEN'!$E$77 | F78: ='ENG_SCEN'!$F$76*'ENG_SCEN'!$F$77 | G78: ='ENG_SCEN'!$G$76*'ENG_SCEN'!$G$77 | H78: ='ENG_SCEN'!$H$76*'ENG_SCEN'!$H$77 | I78: ='ENG_SCEN'!$I$76*'ENG_SCEN'!$I$77 | J78: ='ENG_SCEN'!$J$76*'ENG_SCEN'!$J$77 | K78: ='ENG_SCEN'!$K$76*'ENG_SCEN'!$K$77 | L78: ='ENG_SCEN'!$L$76*'ENG_SCEN'!$L$77 | M78: ='ENG_SCEN'!$M$76*'ENG_SCEN'!$M$77 | N78: ='ENG_SCEN'!$N$76*'ENG_SCEN'!$N$77 | O78: ='ENG_SCEN'!$O$76*'ENG_SCEN'!$O$77 | P78: ='ENG_SCEN'!$P$76*'ENG_SCEN'!$P$77
A79: [2] هزینه مواد اولیه | B79: SB2.rm | C79: میلیون ریال | D79: ='ENG_COST'!$D$264*'IN_SCEN'!$E$13*'IN_SCEN'!$E$15 | E79: ='ENG_COST'!$E$264*'IN_SCEN'!$E$13*'IN_SCEN'!$E$15 | F79: ='ENG_COST'!$F$264*'IN_SCEN'!$E$13*'IN_SCEN'!$E$15 | G79: ='ENG_COST'!$G$264*'IN_SCEN'!$E$13*'IN_SCEN'!$E$15 | H79: ='ENG_COST'!$H$264*'IN_SCEN'!$E$13*'IN_SCEN'!$E$15 | I79: ='ENG_COST'!$I$264*'IN_SCEN'!$E$13*'IN_SCEN'!$E$15 | J79: ='ENG_COST'!$J$264*'IN_SCEN'!$E$13*'IN_SCEN'!$E$15 | K79: ='ENG_COST'!$K$264*'IN_SCEN'!$E$13*'IN_SCEN'!$E$15 | L79: ='ENG_COST'!$L$264*'IN_SCEN'!$E$13*'IN_SCEN'!$E$15 | M79: ='ENG_COST'!$M$264*'IN_SCEN'!$E$13*'IN_SCEN'!$E$15 | N79: ='ENG_COST'!$N$264*'IN_SCEN'!$E$13*'IN_SCEN'!$E$15 | O79: ='ENG_COST'!$O$264*'IN_SCEN'!$E$13*'IN_SCEN'!$E$15 | P79: ='ENG_COST'!$P$264*'IN_SCEN'!$E$13*'IN_SCEN'!$E$15
A80: [2] سایر هزینه‌های متغیر | B80: SB2.var | C80: میلیون ریال | D80: ='ENG_COST'!$D$265*'IN_SCEN'!$E$13*'IN_SCEN'!$E$16 | E80: ='ENG_COST'!$E$265*'IN_SCEN'!$E$13*'IN_SCEN'!$E$16 | F80: ='ENG_COST'!$F$265*'IN_SCEN'!$E$13*'IN_SCEN'!$E$16 | G80: ='ENG_COST'!$G$265*'IN_SCEN'!$E$13*'IN_SCEN'!$E$16 | H80: ='ENG_COST'!$H$265*'IN_SCEN'!$E$13*'IN_SCEN'!$E$16 | I80: ='ENG_COST'!$I$265*'IN_SCEN'!$E$13*'IN_SCEN'!$E$16 | J80: ='ENG_COST'!$J$265*'IN_SCEN'!$E$13*'IN_SCEN'!$E$16 | K80: ='ENG_COST'!$K$265*'IN_SCEN'!$E$13*'IN_SCEN'!$E$16 | L80: ='ENG_COST'!$L$265*'IN_SCEN'!$E$13*'IN_SCEN'!$E$16 | M80: ='ENG_COST'!$M$265*'IN_SCEN'!$E$13*'IN_SCEN'!$E$16 | N80: ='ENG_COST'!$N$265*'IN_SCEN'!$E$13*'IN_SCEN'!$E$16 | O80: ='ENG_COST'!$O$265*'IN_SCEN'!$E$13*'IN_SCEN'!$E$16 | P80: ='ENG_COST'!$P$265*'IN_SCEN'!$E$13*'IN_SCEN'!$E$16
A81: [2] هزینه‌های ثابت نقدی | B81: SB2.fix | C81: میلیون ریال | D81: ='ENG_COST'!$D$268*'IN_SCEN'!$E$17 | E81: ='ENG_COST'!$E$268*'IN_SCEN'!$E$17 | F81: ='ENG_COST'!$F$268*'IN_SCEN'!$E$17 | G81: ='ENG_COST'!$G$268*'IN_SCEN'!$E$17 | H81: ='ENG_COST'!$H$268*'IN_SCEN'!$E$17 | I81: ='ENG_COST'!$I$268*'IN_SCEN'!$E$17 | J81: ='ENG_COST'!$J$268*'IN_SCEN'!$E$17 | K81: ='ENG_COST'!$K$268*'IN_SCEN'!$E$17 | L81: ='ENG_COST'!$L$268*'IN_SCEN'!$E$17 | M81: ='ENG_COST'!$M$268*'IN_SCEN'!$E$17 | N81: ='ENG_COST'!$N$268*'IN_SCEN'!$E$17 | O81: ='ENG_COST'!$O$268*'IN_SCEN'!$E$17 | P81: ='ENG_COST'!$P$268*'IN_SCEN'!$E$17
A82: [2] استهلاک | B82: SB2.dep | C82: میلیون ریال | D82: ='ENG_CAPEX'!$D$81*'IN_SCEN'!$E$18 | E82: ='ENG_CAPEX'!$E$81*'IN_SCEN'!$E$18 | F82: ='ENG_CAPEX'!$F$81*'IN_SCEN'!$E$18 | G82: ='ENG_CAPEX'!$G$81*'IN_SCEN'!$E$18 | H82: ='ENG_CAPEX'!$H$81*'IN_SCEN'!$E$18 | I82: ='ENG_CAPEX'!$I$81*'IN_SCEN'!$E$18 | J82: ='ENG_CAPEX'!$J$81*'IN_SCEN'!$E$18 | K82: ='ENG_CAPEX'!$K$81*'IN_SCEN'!$E$18 | L82: ='ENG_CAPEX'!$L$81*'IN_SCEN'!$E$18 | M82: ='ENG_CAPEX'!$M$81*'IN_SCEN'!$E$18 | N82: ='ENG_CAPEX'!$N$81*'IN_SCEN'!$E$18 | O82: ='ENG_CAPEX'!$O$81*'IN_SCEN'!$E$18 | P82: ='ENG_CAPEX'!$P$81*'IN_SCEN'!$E$18
A83: [2] EBITDA | B83: SB2.ebitda | C83: میلیون ریال | D83: ='ENG_SCEN'!$D$78-'ENG_SCEN'!$D$79-'ENG_SCEN'!$D$80-'ENG_SCEN'!$D$81 | E83: ='ENG_SCEN'!$E$78-'ENG_SCEN'!$E$79-'ENG_SCEN'!$E$80-'ENG_SCEN'!$E$81 | F83: ='ENG_SCEN'!$F$78-'ENG_SCEN'!$F$79-'ENG_SCEN'!$F$80-'ENG_SCEN'!$F$81 | G83: ='ENG_SCEN'!$G$78-'ENG_SCEN'!$G$79-'ENG_SCEN'!$G$80-'ENG_SCEN'!$G$81 | H83: ='ENG_SCEN'!$H$78-'ENG_SCEN'!$H$79-'ENG_SCEN'!$H$80-'ENG_SCEN'!$H$81 | I83: ='ENG_SCEN'!$I$78-'ENG_SCEN'!$I$79-'ENG_SCEN'!$I$80-'ENG_SCEN'!$I$81 | J83: ='ENG_SCEN'!$J$78-'ENG_SCEN'!$J$79-'ENG_SCEN'!$J$80-'ENG_SCEN'!$J$81 | K83: ='ENG_SCEN'!$K$78-'ENG_SCEN'!$K$79-'ENG_SCEN'!$K$80-'ENG_SCEN'!$K$81 | L83: ='ENG_SCEN'!$L$78-'ENG_SCEN'!$L$79-'ENG_SCEN'!$L$80-'ENG_SCEN'!$L$81 | M83: ='ENG_SCEN'!$M$78-'ENG_SCEN'!$M$79-'ENG_SCEN'!$M$80-'ENG_SCEN'!$M$81 | N83: ='ENG_SCEN'!$N$78-'ENG_SCEN'!$N$79-'ENG_SCEN'!$N$80-'ENG_SCEN'!$N$81 | O83: ='ENG_SCEN'!$O$78-'ENG_SCEN'!$O$79-'ENG_SCEN'!$O$80-'ENG_SCEN'!$O$81 | P83: ='ENG_SCEN'!$P$78-'ENG_SCEN'!$P$79-'ENG_SCEN'!$P$80-'ENG_SCEN'!$P$81
A84: [2] EBIT | B84: SB2.ebit | C84: میلیون ریال | D84: ='ENG_SCEN'!$D$83-'ENG_SCEN'!$D$82 | E84: ='ENG_SCEN'!$E$83-'ENG_SCEN'!$E$82 | F84: ='ENG_SCEN'!$F$83-'ENG_SCEN'!$F$82 | G84: ='ENG_SCEN'!$G$83-'ENG_SCEN'!$G$82 | H84: ='ENG_SCEN'!$H$83-'ENG_SCEN'!$H$82 | I84: ='ENG_SCEN'!$I$83-'ENG_SCEN'!$I$82 | J84: ='ENG_SCEN'!$J$83-'ENG_SCEN'!$J$82 | K84: ='ENG_SCEN'!$K$83-'ENG_SCEN'!$K$82 | L84: ='ENG_SCEN'!$L$83-'ENG_SCEN'!$L$82 | M84: ='ENG_SCEN'!$M$83-'ENG_SCEN'!$M$82 | N84: ='ENG_SCEN'!$N$83-'ENG_SCEN'!$N$82 | O84: ='ENG_SCEN'!$O$83-'ENG_SCEN'!$O$82 | P84: ='ENG_SCEN'!$P$83-'ENG_SCEN'!$P$82
A85: [2] مالیات | B85: SB2.tax | C85: میلیون ریال | D85: =MAX(0,'ENG_SCEN'!$D$84)*'IN_MACRO'!$D$14 | E85: =MAX(0,'ENG_SCEN'!$E$84)*'IN_MACRO'!$D$14 | F85: =MAX(0,'ENG_SCEN'!$F$84)*'IN_MACRO'!$D$14 | G85: =MAX(0,'ENG_SCEN'!$G$84)*'IN_MACRO'!$D$14 | H85: =MAX(0,'ENG_SCEN'!$H$84)*'IN_MACRO'!$D$14 | I85: =MAX(0,'ENG_SCEN'!$I$84)*'IN_MACRO'!$D$14 | J85: =MAX(0,'ENG_SCEN'!$J$84)*'IN_MACRO'!$D$14 | K85: =MAX(0,'ENG_SCEN'!$K$84)*'IN_MACRO'!$D$14 | L85: =MAX(0,'ENG_SCEN'!$L$84)*'IN_MACRO'!$D$14 | M85: =MAX(0,'ENG_SCEN'!$M$84)*'IN_MACRO'!$D$14 | N85: =MAX(0,'ENG_SCEN'!$N$84)*'IN_MACRO'!$D$14 | O85: =MAX(0,'ENG_SCEN'!$O$84)*'IN_MACRO'!$D$14 | P85: =MAX(0,'ENG_SCEN'!$P$84)*'IN_MACRO'!$D$14
A86: [2] NOPAT | B86: SB2.nopat | C86: میلیون ریال | D86: ='ENG_SCEN'!$D$84-'ENG_SCEN'!$D$85 | E86: ='ENG_SCEN'!$E$84-'ENG_SCEN'!$E$85 | F86: ='ENG_SCEN'!$F$84-'ENG_SCEN'!$F$85 | G86: ='ENG_SCEN'!$G$84-'ENG_SCEN'!$G$85 | H86: ='ENG_SCEN'!$H$84-'ENG_SCEN'!$H$85 | I86: ='ENG_SCEN'!$I$84-'ENG_SCEN'!$I$85 | J86: ='ENG_SCEN'!$J$84-'ENG_SCEN'!$J$85 | K86: ='ENG_SCEN'!$K$84-'ENG_SCEN'!$K$85 | L86: ='ENG_SCEN'!$L$84-'ENG_SCEN'!$L$85 | M86: ='ENG_SCEN'!$M$84-'ENG_SCEN'!$M$85 | N86: ='ENG_SCEN'!$N$84-'ENG_SCEN'!$N$85 | O86: ='ENG_SCEN'!$O$84-'ENG_SCEN'!$O$85 | P86: ='ENG_SCEN'!$P$84-'ENG_SCEN'!$P$85
A87: [2] CAPEX و جایگزینی | B87: SB2.capex | C87: میلیون ریال | D87: =('ENG_CAPEX'!$D$21+'ENG_CAPEX'!$D$42)*'IN_SCEN'!$E$18 | E87: =('ENG_CAPEX'!$E$21+'ENG_CAPEX'!$E$42)*'IN_SCEN'!$E$18 | F87: =('ENG_CAPEX'!$F$21+'ENG_CAPEX'!$F$42)*'IN_SCEN'!$E$18 | G87: =('ENG_CAPEX'!$G$21+'ENG_CAPEX'!$G$42)*'IN_SCEN'!$E$18 | H87: =('ENG_CAPEX'!$H$21+'ENG_CAPEX'!$H$42)*'IN_SCEN'!$E$18 | I87: =('ENG_CAPEX'!$I$21+'ENG_CAPEX'!$I$42)*'IN_SCEN'!$E$18 | J87: =('ENG_CAPEX'!$J$21+'ENG_CAPEX'!$J$42)*'IN_SCEN'!$E$18 | K87: =('ENG_CAPEX'!$K$21+'ENG_CAPEX'!$K$42)*'IN_SCEN'!$E$18 | L87: =('ENG_CAPEX'!$L$21+'ENG_CAPEX'!$L$42)*'IN_SCEN'!$E$18 | M87: =('ENG_CAPEX'!$M$21+'ENG_CAPEX'!$M$42)*'IN_SCEN'!$E$18 | N87: =('ENG_CAPEX'!$N$21+'ENG_CAPEX'!$N$42)*'IN_SCEN'!$E$18 | O87: =('ENG_CAPEX'!$O$21+'ENG_CAPEX'!$O$42)*'IN_SCEN'!$E$18 | P87: =('ENG_CAPEX'!$P$21+'ENG_CAPEX'!$P$42)*'IN_SCEN'!$E$18
A88: [2] تغییرات سرمایه در گردش | B88: SB2.dwc | C88: میلیون ریال | D88: ='ENG_WC'!$D$19*'IN_SCEN'!$E$13*'IN_SCEN'!$E$14 | E88: ='ENG_WC'!$E$19*'IN_SCEN'!$E$13*'IN_SCEN'!$E$14 | F88: ='ENG_WC'!$F$19*'IN_SCEN'!$E$13*'IN_SCEN'!$E$14 | G88: ='ENG_WC'!$G$19*'IN_SCEN'!$E$13*'IN_SCEN'!$E$14 | H88: ='ENG_WC'!$H$19*'IN_SCEN'!$E$13*'IN_SCEN'!$E$14 | I88: ='ENG_WC'!$I$19*'IN_SCEN'!$E$13*'IN_SCEN'!$E$14 | J88: ='ENG_WC'!$J$19*'IN_SCEN'!$E$13*'IN_SCEN'!$E$14 | K88: ='ENG_WC'!$K$19*'IN_SCEN'!$E$13*'IN_SCEN'!$E$14 | L88: ='ENG_WC'!$L$19*'IN_SCEN'!$E$13*'IN_SCEN'!$E$14 | M88: ='ENG_WC'!$M$19*'IN_SCEN'!$E$13*'IN_SCEN'!$E$14 | N88: ='ENG_WC'!$N$19*'IN_SCEN'!$E$13*'IN_SCEN'!$E$14 | O88: ='ENG_WC'!$O$19*'IN_SCEN'!$E$13*'IN_SCEN'!$E$14 | P88: ='ENG_WC'!$P$19*'IN_SCEN'!$E$13*'IN_SCEN'!$E$14
A89: [2] جریان نقد آزاد (FCFF) | B89: SB2.fcf | C89: میلیون ریال | D89: ='ENG_SCEN'!$D$86+'ENG_SCEN'!$D$82-'ENG_SCEN'!$D$87-'ENG_SCEN'!$D$88 | E89: ='ENG_SCEN'!$E$86+'ENG_SCEN'!$E$82-'ENG_SCEN'!$E$87-'ENG_SCEN'!$E$88 | F89: ='ENG_SCEN'!$F$86+'ENG_SCEN'!$F$82-'ENG_SCEN'!$F$87-'ENG_SCEN'!$F$88 | G89: ='ENG_SCEN'!$G$86+'ENG_SCEN'!$G$82-'ENG_SCEN'!$G$87-'ENG_SCEN'!$G$88 | H89: ='ENG_SCEN'!$H$86+'ENG_SCEN'!$H$82-'ENG_SCEN'!$H$87-'ENG_SCEN'!$H$88 | I89: ='ENG_SCEN'!$I$86+'ENG_SCEN'!$I$82-'ENG_SCEN'!$I$87-'ENG_SCEN'!$I$88 | J89: ='ENG_SCEN'!$J$86+'ENG_SCEN'!$J$82-'ENG_SCEN'!$J$87-'ENG_SCEN'!$J$88 | K89: ='ENG_SCEN'!$K$86+'ENG_SCEN'!$K$82-'ENG_SCEN'!$K$87-'ENG_SCEN'!$K$88 | L89: ='ENG_SCEN'!$L$86+'ENG_SCEN'!$L$82-'ENG_SCEN'!$L$87-'ENG_SCEN'!$L$88 | M89: ='ENG_SCEN'!$M$86+'ENG_SCEN'!$M$82-'ENG_SCEN'!$M$87-'ENG_SCEN'!$M$88 | N89: ='ENG_SCEN'!$N$86+'ENG_SCEN'!$N$82-'ENG_SCEN'!$N$87-'ENG_SCEN'!$N$88 | O89: ='ENG_SCEN'!$O$86+'ENG_SCEN'!$O$82-'ENG_SCEN'!$O$87-'ENG_SCEN'!$O$88 | P89: ='ENG_SCEN'!$P$86+'ENG_SCEN'!$P$82-'ENG_SCEN'!$P$87-'ENG_SCEN'!$P$88
A90: [2] FCFF تکرارپذیر | B90: SB2.fcf_rep | C90: میلیون ریال | D90: ='ENG_SCEN'!$D$86+'ENG_SCEN'!$D$82-'ENG_SCEN'!$D$88 | E90: ='ENG_SCEN'!$E$86+'ENG_SCEN'!$E$82-'ENG_SCEN'!$E$88 | F90: ='ENG_SCEN'!$F$86+'ENG_SCEN'!$F$82-'ENG_SCEN'!$F$88 | G90: ='ENG_SCEN'!$G$86+'ENG_SCEN'!$G$82-'ENG_SCEN'!$G$88 | H90: ='ENG_SCEN'!$H$86+'ENG_SCEN'!$H$82-'ENG_SCEN'!$H$88 | I90: ='ENG_SCEN'!$I$86+'ENG_SCEN'!$I$82-'ENG_SCEN'!$I$88 | J90: ='ENG_SCEN'!$J$86+'ENG_SCEN'!$J$82-'ENG_SCEN'!$J$88 | K90: ='ENG_SCEN'!$K$86+'ENG_SCEN'!$K$82-'ENG_SCEN'!$K$88 | L90: ='ENG_SCEN'!$L$86+'ENG_SCEN'!$L$82-'ENG_SCEN'!$L$88 | M90: ='ENG_SCEN'!$M$86+'ENG_SCEN'!$M$82-'ENG_SCEN'!$M$88 | N90: ='ENG_SCEN'!$N$86+'ENG_SCEN'!$N$82-'ENG_SCEN'!$N$88 | O90: ='ENG_SCEN'!$O$86+'ENG_SCEN'!$O$82-'ENG_SCEN'!$O$88 | P90: ='ENG_SCEN'!$P$86+'ENG_SCEN'!$P$82-'ENG_SCEN'!$P$88
A91: [2] FCFF تجمعی | B91: SB2.cum | C91: میلیون ریال | D91: ='ENG_SCEN'!$D$89 | E91: ='ENG_SCEN'!$D$91+'ENG_SCEN'!$E$89 | F91: ='ENG_SCEN'!$E$91+'ENG_SCEN'!$F$89 | G91: ='ENG_SCEN'!$F$91+'ENG_SCEN'!$G$89 | H91: ='ENG_SCEN'!$G$91+'ENG_SCEN'!$H$89 | I91: ='ENG_SCEN'!$H$91+'ENG_SCEN'!$I$89 | J91: ='ENG_SCEN'!$I$91+'ENG_SCEN'!$J$89 | K91: ='ENG_SCEN'!$J$91+'ENG_SCEN'!$K$89 | L91: ='ENG_SCEN'!$K$91+'ENG_SCEN'!$L$89 | M91: ='ENG_SCEN'!$L$91+'ENG_SCEN'!$M$89 | N91: ='ENG_SCEN'!$M$91+'ENG_SCEN'!$N$89 | O91: ='ENG_SCEN'!$N$91+'ENG_SCEN'!$O$89 | P91: ='ENG_SCEN'!$O$91+'ENG_SCEN'!$P$89
A92: [2] نرخ تنزیل (WACC) | B92: SB2.wacc | C92: درصد | D92: ='ENG_DCF'!$D$14+'IN_SCEN'!$E$20 | E92: ='ENG_DCF'!$E$14+'IN_SCEN'!$E$20 | F92: ='ENG_DCF'!$F$14+'IN_SCEN'!$E$20 | G92: ='ENG_DCF'!$G$14+'IN_SCEN'!$E$20 | H92: ='ENG_DCF'!$H$14+'IN_SCEN'!$E$20 | I92: ='ENG_DCF'!$I$14+'IN_SCEN'!$E$20 | J92: ='ENG_DCF'!$J$14+'IN_SCEN'!$E$20 | K92: ='ENG_DCF'!$K$14+'IN_SCEN'!$E$20 | L92: ='ENG_DCF'!$L$14+'IN_SCEN'!$E$20 | M92: ='ENG_DCF'!$M$14+'IN_SCEN'!$E$20 | N92: ='ENG_DCF'!$N$14+'IN_SCEN'!$E$20 | O92: ='ENG_DCF'!$O$14+'IN_SCEN'!$E$20 | P92: ='ENG_DCF'!$P$14+'IN_SCEN'!$E$20
A93: [2] ضریب تنزیل | B93: SB2.df | C93: ضریب | D93: =1 | E93: ='ENG_SCEN'!$D$93/(1+'ENG_SCEN'!$E$92) | F93: ='ENG_SCEN'!$E$93/(1+'ENG_SCEN'!$F$92) | G93: ='ENG_SCEN'!$F$93/(1+'ENG_SCEN'!$G$92) | H93: ='ENG_SCEN'!$G$93/(1+'ENG_SCEN'!$H$92) | I93: ='ENG_SCEN'!$H$93/(1+'ENG_SCEN'!$I$92) | J93: ='ENG_SCEN'!$I$93/(1+'ENG_SCEN'!$J$92) | K93: ='ENG_SCEN'!$J$93/(1+'ENG_SCEN'!$K$92) | L93: ='ENG_SCEN'!$K$93/(1+'ENG_SCEN'!$L$92) | M93: ='ENG_SCEN'!$L$93/(1+'ENG_SCEN'!$M$92) | N93: ='ENG_SCEN'!$M$93/(1+'ENG_SCEN'!$N$92) | O93: ='ENG_SCEN'!$N$93/(1+'ENG_SCEN'!$O$92) | P93: ='ENG_SCEN'!$O$93/(1+'ENG_SCEN'!$P$92)
A94: [2] ارزش فعلی FCFF | B94: SB2.pv | C94: میلیون ریال | D94: ='ENG_SCEN'!$D$89*'ENG_SCEN'!$D$93 | E94: ='ENG_SCEN'!$E$89*'ENG_SCEN'!$E$93 | F94: ='ENG_SCEN'!$F$89*'ENG_SCEN'!$F$93 | G94: ='ENG_SCEN'!$G$89*'ENG_SCEN'!$G$93 | H94: ='ENG_SCEN'!$H$89*'ENG_SCEN'!$H$93 | I94: ='ENG_SCEN'!$I$89*'ENG_SCEN'!$I$93 | J94: ='ENG_SCEN'!$J$89*'ENG_SCEN'!$J$93 | K94: ='ENG_SCEN'!$K$89*'ENG_SCEN'!$K$93 | L94: ='ENG_SCEN'!$L$89*'ENG_SCEN'!$L$93 | M94: ='ENG_SCEN'!$M$89*'ENG_SCEN'!$M$93 | N94: ='ENG_SCEN'!$N$89*'ENG_SCEN'!$N$93 | O94: ='ENG_SCEN'!$O$89*'ENG_SCEN'!$O$93 | P94: ='ENG_SCEN'!$P$89*'ENG_SCEN'!$P$93
A95: [2] ارزش فعلی تجمعی | B95: SB2.pvc | C95: میلیون ریال | D95: ='ENG_SCEN'!$D$94 | E95: ='ENG_SCEN'!$D$95+'ENG_SCEN'!$E$94 | F95: ='ENG_SCEN'!$E$95+'ENG_SCEN'!$F$94 | G95: ='ENG_SCEN'!$F$95+'ENG_SCEN'!$G$94 | H95: ='ENG_SCEN'!$G$95+'ENG_SCEN'!$H$94 | I95: ='ENG_SCEN'!$H$95+'ENG_SCEN'!$I$94 | J95: ='ENG_SCEN'!$I$95+'ENG_SCEN'!$J$94 | K95: ='ENG_SCEN'!$J$95+'ENG_SCEN'!$K$94 | L95: ='ENG_SCEN'!$K$95+'ENG_SCEN'!$L$94 | M95: ='ENG_SCEN'!$L$95+'ENG_SCEN'!$M$94 | N95: ='ENG_SCEN'!$M$95+'ENG_SCEN'!$N$94 | O95: ='ENG_SCEN'!$N$95+'ENG_SCEN'!$O$94 | P95: ='ENG_SCEN'!$O$95+'ENG_SCEN'!$P$94
A96: [2] ارزش پایانی | B96: SB2.tv | C96: میلیون ریال | D96: =IF('IN_MACRO'!$D$23<'IN_MACRO'!$D$11,0,IF('IN_MACRO'!$D$19=1,MAX(0,'ENG_SCEN'!$P$90)*(1+'IN_MACRO'!$D$18)/MAX(0.005,'ENG_SCEN'!$P$92-'IN_MACRO'!$D$18),'ENG_SCEN'!$P$83*'IN_MACRO'!$D$20)) | E96: =IF('IN_MACRO'!$E$23<'IN_MACRO'!$D$11,0,IF('IN_MACRO'!$D$19=1,MAX(0,'ENG_SCEN'!$P$90)*(1+'IN_MACRO'!$D$18)/MAX(0.005,'ENG_SCEN'!$P$92-'IN_MACRO'!$D$18),'ENG_SCEN'!$P$83*'IN_MACRO'!$D$20)) | F96: =IF('IN_MACRO'!$F$23<'IN_MACRO'!$D$11,0,IF('IN_MACRO'!$D$19=1,MAX(0,'ENG_SCEN'!$P$90)*(1+'IN_MACRO'!$D$18)/MAX(0.005,'ENG_SCEN'!$P$92-'IN_MACRO'!$D$18),'ENG_SCEN'!$P$83*'IN_MACRO'!$D$20)) | G96: =IF('IN_MACRO'!$G$23<'IN_MACRO'!$D$11,0,IF('IN_MACRO'!$D$19=1,MAX(0,'ENG_SCEN'!$P$90)*(1+'IN_MACRO'!$D$18)/MAX(0.005,'ENG_SCEN'!$P$92-'IN_MACRO'!$D$18),'ENG_SCEN'!$P$83*'IN_MACRO'!$D$20)) | H96: =IF('IN_MACRO'!$H$23<'IN_MACRO'!$D$11,0,IF('IN_MACRO'!$D$19=1,MAX(0,'ENG_SCEN'!$P$90)*(1+'IN_MACRO'!$D$18)/MAX(0.005,'ENG_SCEN'!$P$92-'IN_MACRO'!$D$18),'ENG_SCEN'!$P$83*'IN_MACRO'!$D$20)) | I96: =IF('IN_MACRO'!$I$23<'IN_MACRO'!$D$11,0,IF('IN_MACRO'!$D$19=1,MAX(0,'ENG_SCEN'!$P$90)*(1+'IN_MACRO'!$D$18)/MAX(0.005,'ENG_SCEN'!$P$92-'IN_MACRO'!$D$18),'ENG_SCEN'!$P$83*'IN_MACRO'!$D$20)) | J96: =IF('IN_MACRO'!$J$23<'IN_MACRO'!$D$11,0,IF('IN_MACRO'!$D$19=1,MAX(0,'ENG_SCEN'!$P$90)*(1+'IN_MACRO'!$D$18)/MAX(0.005,'ENG_SCEN'!$P$92-'IN_MACRO'!$D$18),'ENG_SCEN'!$P$83*'IN_MACRO'!$D$20)) | K96: =IF('IN_MACRO'!$K$23<'IN_MACRO'!$D$11,0,IF('IN_MACRO'!$D$19=1,MAX(0,'ENG_SCEN'!$P$90)*(1+'IN_MACRO'!$D$18)/MAX(0.005,'ENG_SCEN'!$P$92-'IN_MACRO'!$D$18),'ENG_SCEN'!$P$83*'IN_MACRO'!$D$20)) | L96: =IF('IN_MACRO'!$L$23<'IN_MACRO'!$D$11,0,IF('IN_MACRO'!$D$19=1,MAX(0,'ENG_SCEN'!$P$90)*(1+'IN_MACRO'!$D$18)/MAX(0.005,'ENG_SCEN'!$P$92-'IN_MACRO'!$D$18),'ENG_SCEN'!$P$83*'IN_MACRO'!$D$20)) | M96: =IF('IN_MACRO'!$M$23<'IN_MACRO'!$D$11,0,IF('IN_MACRO'!$D$19=1,MAX(0,'ENG_SCEN'!$P$90)*(1+'IN_MACRO'!$D$18)/MAX(0.005,'ENG_SCEN'!$P$92-'IN_MACRO'!$D$18),'ENG_SCEN'!$P$83*'IN_MACRO'!$D$20)) | N96: =IF('IN_MACRO'!$N$23<'IN_MACRO'!$D$11,0,IF('IN_MACRO'!$D$19=1,MAX(0,'ENG_SCEN'!$P$90)*(1+'IN_MACRO'!$D$18)/MAX(0.005,'ENG_SCEN'!$P$92-'IN_MACRO'!$D$18),'ENG_SCEN'!$P$83*'IN_MACRO'!$D$20)) | O96: =IF('IN_MACRO'!$O$23<'IN_MACRO'!$D$11,0,IF('IN_MACRO'!$D$19=1,MAX(0,'ENG_SCEN'!$P$90)*(1+'IN_MACRO'!$D$18)/MAX(0.005,'ENG_SCEN'!$P$92-'IN_MACRO'!$D$18),'ENG_SCEN'!$P$83*'IN_MACRO'!$D$20)) | P96: =IF('IN_MACRO'!$P$23<'IN_MACRO'!$D$11,0,IF('IN_MACRO'!$D$19=1,MAX(0,'ENG_SCEN'!$P$90)*(1+'IN_MACRO'!$D$18)/MAX(0.005,'ENG_SCEN'!$P$92-'IN_MACRO'!$D$18),'ENG_SCEN'!$P$83*'IN_MACRO'!$D$20))
A97: [2] ارزش فعلی ارزش پایانی | B97: SB2.pvtv | C97: میلیون ریال | D97: ='ENG_SCEN'!$D$96*'ENG_SCEN'!$D$93 | E97: ='ENG_SCEN'!$E$96*'ENG_SCEN'!$E$93 | F97: ='ENG_SCEN'!$F$96*'ENG_SCEN'!$F$93 | G97: ='ENG_SCEN'!$G$96*'ENG_SCEN'!$G$93 | H97: ='ENG_SCEN'!$H$96*'ENG_SCEN'!$H$93 | I97: ='ENG_SCEN'!$I$96*'ENG_SCEN'!$I$93 | J97: ='ENG_SCEN'!$J$96*'ENG_SCEN'!$J$93 | K97: ='ENG_SCEN'!$K$96*'ENG_SCEN'!$K$93 | L97: ='ENG_SCEN'!$L$96*'ENG_SCEN'!$L$93 | M97: ='ENG_SCEN'!$M$96*'ENG_SCEN'!$M$93 | N97: ='ENG_SCEN'!$N$96*'ENG_SCEN'!$N$93 | O97: ='ENG_SCEN'!$O$96*'ENG_SCEN'!$O$93 | P97: ='ENG_SCEN'!$P$96*'ENG_SCEN'!$P$93
A98: [2] جریان قابل بازدهی (FCF + TV) | B98: SB2.fcf_tv | C98: میلیون ریال | D98: ='ENG_SCEN'!$D$89+'ENG_SCEN'!$D$96 | E98: ='ENG_SCEN'!$E$89+'ENG_SCEN'!$E$96 | F98: ='ENG_SCEN'!$F$89+'ENG_SCEN'!$F$96 | G98: ='ENG_SCEN'!$G$89+'ENG_SCEN'!$G$96 | H98: ='ENG_SCEN'!$H$89+'ENG_SCEN'!$H$96 | I98: ='ENG_SCEN'!$I$89+'ENG_SCEN'!$I$96 | J98: ='ENG_SCEN'!$J$89+'ENG_SCEN'!$J$96 | K98: ='ENG_SCEN'!$K$89+'ENG_SCEN'!$K$96 | L98: ='ENG_SCEN'!$L$89+'ENG_SCEN'!$L$96 | M98: ='ENG_SCEN'!$M$89+'ENG_SCEN'!$M$96 | N98: ='ENG_SCEN'!$N$89+'ENG_SCEN'!$N$96 | O98: ='ENG_SCEN'!$O$89+'ENG_SCEN'!$O$96 | P98: ='ENG_SCEN'!$P$89+'ENG_SCEN'!$P$96
A99: [2] CFADS | B99: SB2.cfads | C99: میلیون ریال | D99: ='ENG_SCEN'!$D$83-'ENG_SCEN'!$D$85-'ENG_SCEN'!$D$88 | E99: ='ENG_SCEN'!$E$83-'ENG_SCEN'!$E$85-'ENG_SCEN'!$E$88 | F99: ='ENG_SCEN'!$F$83-'ENG_SCEN'!$F$85-'ENG_SCEN'!$F$88 | G99: ='ENG_SCEN'!$G$83-'ENG_SCEN'!$G$85-'ENG_SCEN'!$G$88 | H99: ='ENG_SCEN'!$H$83-'ENG_SCEN'!$H$85-'ENG_SCEN'!$H$88 | I99: ='ENG_SCEN'!$I$83-'ENG_SCEN'!$I$85-'ENG_SCEN'!$I$88 | J99: ='ENG_SCEN'!$J$83-'ENG_SCEN'!$J$85-'ENG_SCEN'!$J$88 | K99: ='ENG_SCEN'!$K$83-'ENG_SCEN'!$K$85-'ENG_SCEN'!$K$88 | L99: ='ENG_SCEN'!$L$83-'ENG_SCEN'!$L$85-'ENG_SCEN'!$L$88 | M99: ='ENG_SCEN'!$M$83-'ENG_SCEN'!$M$85-'ENG_SCEN'!$M$88 | N99: ='ENG_SCEN'!$N$83-'ENG_SCEN'!$N$85-'ENG_SCEN'!$N$88 | O99: ='ENG_SCEN'!$O$83-'ENG_SCEN'!$O$85-'ENG_SCEN'!$O$88 | P99: ='ENG_SCEN'!$P$83-'ENG_SCEN'!$P$85-'ENG_SCEN'!$P$88
A100: [2] خدمت دین | B100: SB2.debt_service | C100: میلیون ریال | D100: ='ENG_FCF'!$D$24+'ENG_FCF'!$D$20*('IN_FIN'!$D$25+'IN_SCEN'!$E$21)+'ENG_FCF'!$D$27 | E100: ='ENG_FCF'!$E$24+'ENG_FCF'!$E$20*('IN_FIN'!$D$25+'IN_SCEN'!$E$21)+'ENG_FCF'!$E$27 | F100: ='ENG_FCF'!$F$24+'ENG_FCF'!$F$20*('IN_FIN'!$D$25+'IN_SCEN'!$E$21)+'ENG_FCF'!$F$27 | G100: ='ENG_FCF'!$G$24+'ENG_FCF'!$G$20*('IN_FIN'!$D$25+'IN_SCEN'!$E$21)+'ENG_FCF'!$G$27 | H100: ='ENG_FCF'!$H$24+'ENG_FCF'!$H$20*('IN_FIN'!$D$25+'IN_SCEN'!$E$21)+'ENG_FCF'!$H$27 | I100: ='ENG_FCF'!$I$24+'ENG_FCF'!$I$20*('IN_FIN'!$D$25+'IN_SCEN'!$E$21)+'ENG_FCF'!$I$27 | J100: ='ENG_FCF'!$J$24+'ENG_FCF'!$J$20*('IN_FIN'!$D$25+'IN_SCEN'!$E$21)+'ENG_FCF'!$J$27 | K100: ='ENG_FCF'!$K$24+'ENG_FCF'!$K$20*('IN_FIN'!$D$25+'IN_SCEN'!$E$21)+'ENG_FCF'!$K$27 | L100: ='ENG_FCF'!$L$24+'ENG_FCF'!$L$20*('IN_FIN'!$D$25+'IN_SCEN'!$E$21)+'ENG_FCF'!$L$27 | M100: ='ENG_FCF'!$M$24+'ENG_FCF'!$M$20*('IN_FIN'!$D$25+'IN_SCEN'!$E$21)+'ENG_FCF'!$M$27 | N100: ='ENG_FCF'!$N$24+'ENG_FCF'!$N$20*('IN_FIN'!$D$25+'IN_SCEN'!$E$21)+'ENG_FCF'!$N$27 | O100: ='ENG_FCF'!$O$24+'ENG_FCF'!$O$20*('IN_FIN'!$D$25+'IN_SCEN'!$E$21)+'ENG_FCF'!$O$27 | P100: ='ENG_FCF'!$P$24+'ENG_FCF'!$P$20*('IN_FIN'!$D$25+'IN_SCEN'!$E$21)+'ENG_FCF'!$P$27
A101: [2] DSCR | B101: SB2.dscr | C101: ضریب | D101: =IFERROR('ENG_SCEN'!$D$99/'ENG_SCEN'!$D$100,"─") | E101: =IFERROR('ENG_SCEN'!$E$99/'ENG_SCEN'!$E$100,"─") | F101: =IFERROR('ENG_SCEN'!$F$99/'ENG_SCEN'!$F$100,"─") | G101: =IFERROR('ENG_SCEN'!$G$99/'ENG_SCEN'!$G$100,"─") | H101: =IFERROR('ENG_SCEN'!$H$99/'ENG_SCEN'!$H$100,"─") | I101: =IFERROR('ENG_SCEN'!$I$99/'ENG_SCEN'!$I$100,"─") | J101: =IFERROR('ENG_SCEN'!$J$99/'ENG_SCEN'!$J$100,"─") | K101: =IFERROR('ENG_SCEN'!$K$99/'ENG_SCEN'!$K$100,"─") | L101: =IFERROR('ENG_SCEN'!$L$99/'ENG_SCEN'!$L$100,"─") | M101: =IFERROR('ENG_SCEN'!$M$99/'ENG_SCEN'!$M$100,"─") | N101: =IFERROR('ENG_SCEN'!$N$99/'ENG_SCEN'!$N$100,"─") | O101: =IFERROR('ENG_SCEN'!$O$99/'ENG_SCEN'!$O$100,"─") | P101: =IFERROR('ENG_SCEN'!$P$99/'ENG_SCEN'!$P$100,"─")
A102: [2] ارزش فعلی خالص (NPV) | C102: میلیون ریال | D102: =SUM('ENG_SCEN'!$D$94:$P$94)+SUM('ENG_SCEN'!$D$97:$P$97)
A103: [2] IRR پروژه | C103: درصد | D103: =IFERROR(IRR('ENG_SCEN'!$D$98:$P$98),NA())
A104: [2] دوره بازپرداشت (سال) | C104: سال | D104: =IF(COUNTIF('ENG_SCEN'!$D$91:$P$91,"<0")=0,0,IF(COUNTIF('ENG_SCEN'!$D$91:$P$91,"<0")>=13,NA(),INDEX('IN_MACRO'!$D$23:$P$23,COUNTIF('ENG_SCEN'!$D$91:$P$91,"<0"))+(0-INDEX('ENG_SCEN'!$D$91:$P$91,COUNTIF('ENG_SCEN'!$D$91:$P$91,"<0")))/(INDEX('ENG_SCEN'!$D$91:$P$91,COUNTIF('ENG_SCEN'!$D$91:$P$91,"<0")+1)-INDEX('ENG_SCEN'!$D$91:$P$91,COUNTIF('ENG_SCEN'!$D$91:$P$91,"<0")))))
A105: [2] شاخص سودآوری | C105: ضریب | D105: =IFERROR((SUMIF('ENG_SCEN'!$D$94:$P$94,">0")+SUM('ENG_SCEN'!$D$97:$P$97))/ABS(SUMIF('ENG_SCEN'!$D$94:$P$94,"<0")),NA())
A106: [2] حداقل DSCR | C106: ضریب | D106: =IFERROR(IF(COUNT('ENG_SCEN'!$D$101:$P$101)=0,NA(),MIN('ENG_SCEN'!$D$101:$P$101)),NA())
A107: [2] میانگین DSCR دوره بازپرداخت | C107: ضریب | D107: =IFERROR(AVERAGEIF('ENG_SCEN'!$D$100:$P$100,">0",'ENG_SCEN'!$D$101:$P$101),NA())
A109: سناریوی 3: بدبینانه
...

Sheet ENG_OPS
A1: موتور محاسبات عملیاتی | B1: موتور محاسبات
A2: تبدیل ورودی‌های فنی ایستگاه‌ها به ظرفیت، جریان مواد، محصول قابل فروش و درآمد.
A7: دوره (t) | D7: 0 | E7: 1 | F7: 2 | G7: 3 | H7: 4 | I7: 5 | J7: 6 | K7: 7 | L7: 8 | M7: 9 | N7: 10 | O7: 11 | P7: 12
A8: سال تقویمی | D8: 2026 | E8: 2027 | F8: 2028 | G8: 2029 | H8: 2030 | I8: 2031 | J8: 2032 | K8: 2033 | L8: 2034 | M8: 2035 | N8: 2036 | O8: 2037 | P8: 2038
A9: الف) ظرفیت و بارگذاری
A10: ضریب دستیابی به ظرفیت (Ramp) | B10: OPS.ramp | C10: درصد | D10: ='IN_TECH'!$D$59*'IN_MACRO'!$D$34 | E10: ='IN_TECH'!$E$59*'IN_MACRO'!$E$34 | F10: ='IN_TECH'!$F$59*'IN_MACRO'!$F$34 | G10: ='IN_TECH'!$G$59*'IN_MACRO'!$G$34 | H10: ='IN_TECH'!$H$59*'IN_MACRO'!$H$34 | I10: ='IN_TECH'!$I$59*'IN_MACRO'!$I$34 | J10: ='IN_TECH'!$J$59*'IN_MACRO'!$J$34 | K10: ='IN_TECH'!$K$59*'IN_MACRO'!$K$34 | L10: ='IN_TECH'!$L$59*'IN_MACRO'!$L$34 | M10: ='IN_TECH'!$M$59*'IN_MACRO'!$M$34 | N10: ='IN_TECH'!$N$59*'IN_MACRO'!$N$34 | O10: ='IN_TECH'!$O$59*'IN_MACRO'!$O$34 | P10: ='IN_TECH'!$P$59*'IN_MACRO'!$P$34
A11: نرخ دسترسی کل خط (کمینهٔ ایستگاه‌ها) | B11: OPS.avail | C11: درصد | D11: =MIN('IN_TECH'!$D$38,'IN_TECH'!$E$38,'IN_TECH'!$F$38,'IN_TECH'!$G$38,'IN_TECH'!$H$38,'IN_TECH'!$I$38) | E11: =MIN('IN_TECH'!$D$38,'IN_TECH'!$E$38,'IN_TECH'!$F$38,'IN_TECH'!$G$38,'IN_TECH'!$H$38,'IN_TECH'!$I$38) | F11: =MIN('IN_TECH'!$D$38,'IN_TECH'!$E$38,'IN_TECH'!$F$38,'IN_TECH'!$G$38,'IN_TECH'!$H$38,'IN_TECH'!$I$38) | G11: =MIN('IN_TECH'!$D$38,'IN_TECH'!$E$38,'IN_TECH'!$F$38,'IN_TECH'!$G$38,'IN_TECH'!$H$38,'IN_TECH'!$I$38) | H11: =MIN('IN_TECH'!$D$38,'IN_TECH'!$E$38,'IN_TECH'!$F$38,'IN_TECH'!$G$38,'IN_TECH'!$H$38,'IN_TECH'!$I$38) | I11: =MIN('IN_TECH'!$D$38,'IN_TECH'!$E$38,'IN_TECH'!$F$38,'IN_TECH'!$G$38,'IN_TECH'!$H$38,'IN_TECH'!$I$38) | J11: =MIN('IN_TECH'!$D$38,'IN_TECH'!$E$38,'IN_TECH'!$F$38,'IN_TECH'!$G$38,'IN_TECH'!$H$38,'IN_TECH'!$I$38) | K11: =MIN('IN_TECH'!$D$38,'IN_TECH'!$E$38,'IN_TECH'!$F$38,'IN_TECH'!$G$38,'IN_TECH'!$H$38,'IN_TECH'!$I$38) | ... P11: =MIN('IN_TECH'!$D$38,'IN_TECH'!$E$38,'IN_TECH'!$F$38,'IN_TECH'!$G$38,'IN_TECH'!$H$38,'IN_TECH'!$I$38)
A12: ضریب بهره‌برداری مؤثر | B12: OPS.util | C12: درصد | D12: ='ENG_OPS'!$D$10*'ENG_OPS'!$D$11*'ENG_SCEN'!$G$11 | E12: ='ENG_OPS'!$E$10*'ENG_OPS'!$E$11*'ENG_SCEN'!$G$11 | F12: ='ENG_OPS'!$F$10*'ENG_OPS'!$F$11*'ENG_SCEN'!$G$11 | G12: ='ENG_OPS'!$G$10*'ENG_OPS'!$G$11*'ENG_SCEN'!$G$11 | H12: ='ENG_OPS'!$H$10*'ENG_OPS'!$H$11*'ENG_SCEN'!$G$11 | I12: ='ENG_OPS'!$I$10*'ENG_OPS'!$I$11*'ENG_SCEN'!$G$11 | J12: ='ENG_OPS'!$J$10*'ENG_OPS'!$J$11*'ENG_SCEN'!$G$11 | K12: ='ENG_OPS'!$K$10*'ENG_OPS'!$K$11*'ENG_SCEN'!$G$11 | L12: ='ENG_OPS'!$L$10*'ENG_OPS'!$L$11*'ENG_SCEN'!$G$11 | M12: ='ENG_OPS'!$M$10*'ENG_OPS'!$M$11*'ENG_SCEN'!$G$11 | N12: ='ENG_OPS'!$N$10*'ENG_OPS'!$N$11*'ENG_SCEN'!$G$11 | O12: ='ENG_OPS'!$O$10*'ENG_OPS'!$O$11*'ENG_SCEN'!$G$11 | P12: ='ENG_OPS'!$P$10*'ENG_OPS'!$P$11*'ENG_SCEN'!$G$11
A13: سهم خوراک ایستگاه 1 (به‌ازای هر تن ورودی) | B13: OPS.split.0 | C13: تن/تن | D13: =1 | E13: =1 | F13: =1 | G13: =1 | H13: =1 | I13: =1 | J13: =1 | K13: =1 | ... P13: =1
A14: سهم خوراک ایستگاه 2 (به‌ازای هر تن ورودی) | B14: OPS.split.1 | C14: تن/تن | D14: =(1-'IN_TECH'!$D$40) | E14: =(1-'IN_TECH'!$D$40) | F14: =(1-'IN_TECH'!$D$40) | G14: =(1-'IN_TECH'!$D$40) | H14: =(1-'IN_TECH'!$D$40) | I14: =(1-'IN_TECH'!$D$40) | J14: =(1-'IN_TECH'!$D$40) | K14: =(1-'IN_TECH'!$D$40) | ... P14: =(1-'IN_TECH'!$D$40)
A15: سهم خوراک ایستگاه 3 (به‌ازای هر تن ورودی) | B15: OPS.split.2 | C15: تن/تن | D15: =(((1-'IN_TECH'!$D$40)*(1-'IN_TECH'!$E$40))*'IN_TECH'!$D$27) | E15: =(((1-'IN_TECH'!$D$40)*(1-'IN_TECH'!$E$40))*'IN_TECH'!$D$27) | F15: =(((1-'IN_TECH'!$D$40)*(1-'IN_TECH'!$E$40))*'IN_TECH'!$D$27) | G15: =(((1-'IN_TECH'!$D$40)*(1-'IN_TECH'!$E$40))*'IN_TECH'!$D$27) | H15: =(((1-'IN_TECH'!$D$40)*(1-'IN_TECH'!$E$40))*'IN_TECH'!$D$27) | I15: =(((1-'IN_TECH'!$D$40)*(1-'IN_TECH'!$E$40))*'IN_TECH'!$D$27) | J15: =(((1-'IN_TECH'!$D$40)*(1-'IN_TECH'!$E$40))*'IN_TECH'!$D$27) | K15: =(((1-'IN_TECH'!$D$40)*(1-'IN_TECH'!$E$40))*'IN_TECH'!$D$27) | ... P15: =(((1-'IN_TECH'!$D$40)*(1-'IN_TECH'!$E$40))*'IN_TECH'!$D$27)
A16: سهم خوراک ایستگاه 4 (به‌ازای هر تن ورودی) | B16: OPS.split.3 | C16: تن/تن | D16: =(((((1-'IN_TECH'!$D$40)*(1-'IN_TECH'!$E$40))*'IN_TECH'!$D$27)*'IN_TECH'!$D$18*(1-'IN_TECH'!$F$40))+(((1-'IN_TECH'!$D$40)*(1-'IN_TECH'!$E$40))*'IN_TECH'!$D$28)) | E16: =(((((1-'IN_TECH'!$D$40)*(1-'IN_TECH'!$E$40))*'IN_TECH'!$D$27)*'IN_TECH'!$D$18*(1-'IN_TECH'!$F$40))+(((1-'IN_TECH'!$D$40)*(1-'IN_TECH'!$E$40))*'IN_TECH'!$D$28)) | F16: =(((((1-'IN_TECH'!$D$40)*(1-'IN_TECH'!$E$40))*'IN_TECH'!$D$27)*'IN_TECH'!$D$18*(1-'IN_TECH'!$F$40))+(((1-'IN_TECH'!$D$40)*(1-'IN_TECH'!$E$40))*'IN_TECH'!$D$28)) | G16: =(((((1-'IN_TECH'!$D$40)*(1-'IN_TECH'!$E$40))*'IN_TECH'!$D$27)*'IN_TECH'!$D$18*(1-'IN_TECH'!$F$40))+(((1-'IN_TECH'!$D$40)*(1-'IN_TECH'!$E$40))*'IN_TECH'!$D$28)) | H16: =(((((1-'IN_TECH'!$D$40)*(1-'IN_TECH'!$E$40))*'IN_TECH'!$D$27)*'IN_TECH'!$D$18*(1-'IN_TECH'!$F$40))+(((1-'IN_TECH'!$D$40)*(1-'IN_TECH'!$E$40))*'IN_TECH'!$D$28)) | I16: =(((((1-'IN_TECH'!$D$40)*(1-'IN_TECH'!$E$40))*'IN_TECH'!$D$27)*'IN_TECH'!$D$18*(1-'IN_TECH'!$F$40))+(((1-'IN_TECH'!$D$40)*(1-'IN_TECH'!$E$40))*'IN_TECH'!$D$28)) | J16: =(((((1-'IN_TECH'!$D$40)*(1-'IN_TECH'!$E$40))*'IN_TECH'!$D$27)*'IN_TECH'!$D$18*(1-'IN_TECH'!$F$40))+(((1-'IN_TECH'!$D$40)*(1-'IN_TECH'!$E$40))*'IN_TECH'!$D$28)) | K16: =(((((1-'IN_TECH'!$D$40)*(1-'IN_TECH'!$E$40))*'IN_TECH'!$D$27)*'IN_TECH'!$D$18*(1-'IN_TECH'!$F$40))+(((1-'IN_TECH'!$D$40)*(1-'IN_TECH'!$E$40))*'IN_TECH'!$D$28)) | ... P16: =(((((1-'IN_TECH'!$D$40)*(1-'IN_TECH'!$E$40))*'IN_TECH'!$D$27)*'IN_TECH'!$D$18*(1-'IN_TECH'!$F$40))+(((1-'IN_TECH'!$D$40)*(1-'IN_TECH'!$E$40))*'IN_TECH'!$D$28))
A17: سهم خوراک ایستگاه 5 (به‌ازای هر تن ورودی) | B17: OPS.split.4 | C17: تن/تن | D17: =((((((1-'IN_TECH'!$D$40)*(1-'IN_TECH'!$E$40))*'IN_TECH'!$D$27)*'IN_TECH'!$D$18*(1-'IN_TECH'!$F$40))*'IN_TECH'!$D$16+(((1-'IN_TECH'!$D$40)*(1-'IN_TECH'!$E$40))*'IN_TECH'!$D$28)*'IN_TECH'!$D$17)*'IN_TECH'!$D$19*(1-'IN_TECH'!$G$40)) | E17: =((((((1-'IN_TECH'!$D$40)*(1-'IN_TECH'!$E$40))*'IN_TECH'!$D$27)*'IN_TECH'!$D$18*(1-'IN_TECH'!$F$40))*'IN_TECH'!$D$16+(((1-'IN_TECH'!$D$40)*(1-'IN_TECH'!$E$40))*'IN_TECH'!$D$28)*'IN_TECH'!$D$17)*'IN_TECH'!$D$19*(1-'IN_TECH'!$G$40)) | F17: =((((((1-'IN_TECH'!$D$40)*(1-'IN_TECH'!$E$40))*'IN_TECH'!$D$27)*'IN_TECH'!$D$18*(1-'IN_TECH'!$F$40))*'IN_TECH'!$D$16+(((1-'IN_TECH'!$D$40)*(1-'IN_TECH'!$E$40))*'IN_TECH'!$D$28)*'IN_TECH'!$D$17)*'IN_TECH'!$D$19*(1-'IN_TECH'!$G$40)) | G17: =((((((1-'IN_TECH'!$D$40)*(1-'IN_TECH'!$E$40))*'IN_TECH'!$D$27)*'IN_TECH'!$D$18*(1-'IN_TECH'!$F$40))*'IN_TECH'!$D$16+(((1-'IN_TECH'!$D$40)*(1-'IN_TECH'!$E$40))*'IN_TECH'!$D$28)*'IN_TECH'!$D$17)*'IN_TECH'!$D$19*(1-'IN_TECH'!$G$40)) | H17: =((((((1-'IN_TECH'!$D$40)*(1-'IN_TECH'!$E$40))*'IN_TECH'!$D$27)*'IN_TECH'!$D$18*(1-'IN_TECH'!$F$40))*'IN_TECH'!$D$16+(((1-'IN_TECH'!$D$40)*(1-'IN_TECH'!$E$40))*'IN_TECH'!$D$28)*'IN_TECH'!$D$17)*'IN_TECH'!$D$19*(1-'IN_TECH'!$G$40)) | I17: =((((((1-'IN_TECH'!$D$40)*(1-'IN_TECH'!$E$40))*'IN_TECH'!$D$27)*'IN_TECH'!$D$18*(1-'IN_TECH'!$F$40))*'IN_TECH'!$D$16+(((1-'IN_TECH'!$D$40)*(1-'IN_TECH'!$E$40))*'IN_TECH'!$D$28)*'IN_TECH'!$D$17)*'IN_TECH'!$D$19*(1-'IN_TECH'!$G$40)) | J17: =((((((1-'IN_TECH'!$D$40)*(1-'IN_TECH'!$E$40))*'IN_TECH'!$D$27)*'IN_TECH'!$D$18*(1-'IN_TECH'!$F$40))*'IN_TECH'!$D$16+(((1-'IN_TECH'!$D$40)*(1-'IN_TECH'!$E$40))*'IN_TECH'!$D$28)*'IN_TECH'!$D$17)*'IN_TECH'!$D$19*(1-'IN_TECH'!$G$40)) | K17: =((((((1-'IN_TECH'!$D$40)*(1-'IN_TECH'!$E$40))*'IN_TECH'!$D$27)*'IN_TECH'!$D$18*(1-'IN_TECH'!$F$40))*'IN_TECH'!$D$16+(((1-'IN_TECH'!$D$40)*(1-'IN_TECH'!$E$40))*'IN_TECH'!$D$28)*'IN_TECH'!$D$17)*'IN_TECH'!$D$19*(1-'IN_TECH'!$G$40)) | ... P17: =((((((1-'IN_TECH'!$D$40)*(1-'IN_TECH'!$E$40))*'IN_TECH'!$D$27)*'IN_TECH'!$D$18*(1-'IN_TECH'!$F$40))*'IN_TECH'!$D$16+(((1-'IN_TECH'!$D$40)*(1-'IN_TECH'!$E$40))*'IN_TECH'!$D$28)*'IN_TECH'!$D$17)*'IN_TECH'!$D$19*(1-'IN_TECH'!$G$40))
A18: سهم خوراک ایستگاه 6 (به‌ازای هر تن ورودی) | B18: OPS.split.5 | C18: تن/تن | D18: =((((((((1-'IN_TECH'!$D$40)*(1-'IN_TECH'!$E$40))*'IN_TECH'!$D$27)*'IN_TECH'!$D$18*(1-'IN_TECH'!$F$40))*'IN_TECH'!$D$16+(((1-'IN_TECH'!$D$40)*(1-'IN_TECH'!$E$40))*'IN_TECH'!$D$28)*'IN_TECH'!$D$17)*'IN_TECH'!$D$19*(1-'IN_TECH'!$G$40))*'IN_TECH'!$D$20*(1-'IN_TECH'!$H$40))+(((1-'IN_TECH'!$D$40)*(1-'IN_TECH'!$E$40))*'IN_TECH'!$D$29)*'IN_TECH'!$D$21+'IN_TECH'!$D$22) | E18: =((((((((1-'IN_TECH'!$D$40)*(1-'IN_TECH'!$E$40))*'IN_TECH'!$D$27)*'IN_TECH'!$D$18*(1-'IN_TECH'!$F$40))*'IN_TECH'!$D$16+(((1-'IN_TECH'!$D$40)*(1-'IN_TECH'!$E$40))*'IN_TECH'!$D$28)*'IN_TECH'!$D$17)*'IN_TECH'!$D$19*(1-'IN_TECH'!$G$40))*'IN_TECH'!$D$20*(1-'IN_TECH'!$H$40))+(((1-'IN_TECH'!$D$40)*(1-'IN_TECH'!$E$40))*'IN_TECH'!$D$29)*'IN_TECH'!$D$21+'IN_TECH'!$D$22) | F18: =((((((((1-'IN_TECH'!$D$40)*(1-'IN_TECH'!$E$40))*'IN_TECH'!$D$27)*'IN_TECH'!$D$18*(1-'IN_TECH'!$F$40))*'IN_TECH'!$D$16+(((1-'IN_TECH'!$D$40)*(1-'IN_TECH'!$E$40))*'IN_TECH'!$D$28)*'IN_TECH'!$D$17)*'IN_TECH'!$D$19*(1-'IN_TECH'!$G$40))*'IN_TECH'!$D$20*(1-'IN_TECH'!$H$40))+(((1-'IN_TECH'!$D$40)*(1-'IN_TECH'!$E$40))*'IN_TECH'!$D$29)*'IN_TECH'!$D$21+'IN_TECH'!$D$22) | G18: =((((((((1-'IN_TECH'!$D$40)*(1-'IN_TECH'!$E$40))*'IN_TECH'!$D$27)*'IN_TECH'!$D$18*(1-'IN_TECH'!$F$40))*'IN_TECH'!$D$16+(((1-'IN_TECH'!$D$40)*(1-'IN_TECH'!$E$40))*'IN_TECH'!$D$28)*'IN_TECH'!$D$17)*'IN_TECH'!$D$19*(1-'IN_TECH'!$G$40))*'IN_TECH'!$D$20*(1-'IN_TECH'!$H$40))+(((1-'IN_TECH'!$D$40)*(1-'IN_TECH'!$E$40))*'IN_TECH'!$D$29)*'IN_TECH'!$D$21+'IN_TECH'!$D$22) | H18: =((((((((1-'IN_TECH'!$D$40)*(1-'IN_TECH'!$E$40))*'IN_TECH'!$D$27)*'IN_TECH'!$D$18*(1-'IN_TECH'!$F$40))*'IN_TECH'!$D$16+(((1-'IN_TECH'!$D$40)*(1-'IN_TECH'!$E$40))*'IN_TECH'!$D$28)*'IN_TECH'!$D$17)*'IN_TECH'!$D$19*(1-'IN_TECH'!$G$40))*'IN_TECH'!$D$20*(1-'IN_TECH'!$H$40))+(((1-'IN_TECH'!$D$40)*(1-'IN_TECH'!$E$40))*'IN_TECH'!$D$29)*'IN_TECH'!$D$21+'IN_TECH'!$D$22) | I18: =((((((((1-'IN_TECH'!$D$40)*(1-'IN_TECH'!$E$40))*'IN_TECH'!$D$27)*'IN_TECH'!$D$18*(1-'IN_TECH'!$F$40))*'IN_TECH'!$D$16+(((1-'IN_TECH'!$D$40)*(1-'IN_TECH'!$E$40))*'IN_TECH'!$D$28)*'IN_TECH'!$D$17)*'IN_TECH'!$D$19*(1-'IN_TECH'!$G$40))*'IN_TECH'!$D$20*(1-'IN_TECH'!$H$40))+(((1-'IN_TECH'!$D$40)*(1-'IN_TECH'!$E$40))*'IN_TECH'!$D$29)*'IN_TECH'!$D$21+'IN_TECH'!$D$22) | J18: =((((((((1-'IN_TECH'!$D$40)*(1-'IN_TECH'!$E$40))*'IN_TECH'!$D$27)*'IN_TECH'!$D$18*(1-'IN_TECH'!$F$40))*'IN_TECH'!$D$16+(((1-'IN_TECH'!$D$40)*(1-'IN_TECH'!$E$40))*'IN_TECH'!$D$28)*'IN_TECH'!$D$17)*'IN_TECH'!$D$19*(1-'IN_TECH'!$G$40))*'IN_TECH'!$D$20*(1-'IN_TECH'!$H$40))+(((1-'IN_TECH'!$D$40)*(1-'IN_TECH'!$E$40))*'IN_TECH'!$D$29)*'IN_TECH'!$D$21+'IN_TECH'!$D$22) | K18: =((((((((1-'IN_TECH'!$D$40)*(1-'IN_TECH'!$E$40))*'IN_TECH'!$D$27)*'IN_TECH'!$D$18*(1-'IN_TECH'!$F$40))*'IN_TECH'!$D$16+(((1-'IN_TECH'!$D$40)*(1-'IN_TECH'!$E$40))*'IN_TECH'!$D$28)*'IN_TECH'!$D$17)*'IN_TECH'!$D$19*(1-'IN_TECH'!$G$40))*'IN_TECH'!$D$20*(1-'IN_TECH'!$H$40))+(((1-'IN_TECH'!$D$40)*(1-'IN_TECH'!$E$40))*'IN_TECH'!$D$29)*'IN_TECH'!$D$21+'IN_TECH'!$D$22) | ... P18: =((((((((1-'IN_TECH'!$D$40)*(1-'IN_TECH'!$E$40))*'IN_TECH'!$D$27)*'IN_TECH'!$D$18*(1-'IN_TECH'!$F$40))*'IN_TECH'!$D$16+(((1-'IN_TECH'!$D$40)*(1-'IN_TECH'!$E$40))*'IN_TECH'!$D$28)*'IN_TECH'!$D$17)*'IN_TECH'!$D$19*(1-'IN_TECH'!$G$40))*'IN_TECH'!$D$20*(1-'IN_TECH'!$H$40))+(((1-'IN_TECH'!$D$40)*(1-'IN_TECH'!$E$40))*'IN_TECH'!$D$29)*'IN_TECH'!$D$21+'IN_TECH'!$D$22)
A19: بیشینهٔ ورودی قابل پردازش (محدودیت گلوگاه) | B19: OPS.intake_cap | C19: تن | D19: =MIN(IFERROR('IN_TECH'!$D$36/'ENG_OPS'!$D$13,1E+15),IFERROR('IN_TECH'!$E$36/'ENG_OPS'!$D$14,1E+15),IFERROR('IN_TECH'!$F$36/'ENG_OPS'!$D$15,1E+15),IFERROR('IN_TECH'!$G$36/'ENG_OPS'!$D$16,1E+15),IFERROR('IN_TECH'!$H$36/'ENG_OPS'!$D$17,1E+15),IFERROR('IN_TECH'!$I$36/'ENG_OPS'!$D$18,1E+15)) | E19: =MIN(IFERROR('IN_TECH'!$D$36/'ENG_OPS'!$E$13,1E+15),IFERROR('IN_TECH'!$E$36/'ENG_OPS'!$E$14,1E+15),IFERROR('IN_TECH'!$F$36/'ENG_OPS'!$E$15,1E+15),IFERROR('IN_TECH'!$G$36/'ENG_OPS'!$E$16,1E+15),IFERROR('IN_TECH'!$H$36/'ENG_OPS'!$E$17,1E+15),IFERROR('IN_TECH'!$I$36/'ENG_OPS'!$E$18,1E+15)) | F19: =MIN(IFERROR('IN_TECH'!$D$36/'ENG_OPS'!$F$13,1E+15),IFERROR('IN_TECH'!$E$36/'ENG_OPS'!$F$14,1E+15),IFERROR('IN_TECH'!$F$36/'ENG_OPS'!$F$15,1E+15),IFERROR('IN_TECH'!$G$36/'ENG_OPS'!$F$16,1E+15),IFERROR('IN_TECH'!$H$36/'ENG_OPS'!$F$17,1E+15),IFERROR('IN_TECH'!$I$36/'ENG_OPS'!$F$18,1E+15)) | G19: =MIN(IFERROR('IN_TECH'!$D$36/'ENG_OPS'!$G$13,1E+15),IFERROR('IN_TECH'!$E$36/'ENG_OPS'!$G$14,1E+15),IFERROR('IN_TECH'!$F$36/'ENG_OPS'!$G$15,1E+15),IFERROR('IN_TECH'!$G$36/'ENG_OPS'!$G$16,1E+15),IFERROR('IN_TECH'!$H$36/'ENG_OPS'!$G$17,1E+15),IFERROR('IN_TECH'!$I$36/'ENG_OPS'!$G$18,1E+15)) | H19: =MIN(IFERROR('IN_TECH'!$D$36/'ENG_OPS'!$H$13,1E+15),IFERROR('IN_TECH'!$E$36/'ENG_OPS'!$H$14,1E+15),IFERROR('IN_TECH'!$F$36/'ENG_OPS'!$H$15,1E+15),IFERROR('IN_TECH'!$G$36/'ENG_OPS'!$H$16,1E+15),IFERROR('IN_TECH'!$H$36/'ENG_OPS'!$H$17,1E+15),IFERROR('IN_TECH'!$I$36/'ENG_OPS'!$H$18,1E+15)) | I19: =MIN(IFERROR('IN_TECH'!$D$36/'ENG_OPS'!$I$13,1E+15),IFERROR('IN_TECH'!$E$36/'ENG_OPS'!$I$14,1E+15),IFERROR('IN_TECH'!$F$36/'ENG_OPS'!$I$15,1E+15),IFERROR('IN_TECH'!$G$36/'ENG_OPS'!$I$16,1E+15),IFERROR('IN_TECH'!$H$36/'ENG_OPS'!$I$17,1E+15),IFERROR('IN_TECH'!$I$36/'ENG_OPS'!$I$18,1E+15)) | J19: =MIN(IFERROR('IN_TECH'!$D$36/'ENG_OPS'!$J$13,1E+15),IFERROR('IN_TECH'!$E$36/'ENG_OPS'!$J$14,1E+15),IFERROR('IN_TECH'!$F$36/'ENG_OPS'!$J$15,1E+15),IFERROR('IN_TECH'!$G$36/'ENG_OPS'!$J$16,1E+15),IFERROR('IN_TECH'!$H$36/'ENG_OPS'!$J$17,1E+15),IFERROR('IN_TECH'!$I$36/'ENG_OPS'!$J$18,1E+15)) | K19: =MIN(IFERROR('IN_TECH'!$D$36/'ENG_OPS'!$K$13,1E+15),IFERROR('IN_TECH'!$E$36/'ENG_OPS'!$K$14,1E+15),IFERROR('IN_TECH'!$F$36/'ENG_OPS'!$K$15,1E+15),IFERROR('IN_TECH'!$G$36/'ENG_OPS'!$K$16,1E+15),IFERROR('IN_TECH'!$H$36/'ENG_OPS'!$K$17,1E+15),IFERROR('IN_TECH'!$I$36/'ENG_OPS'!$K$18,1E+15)) | L19: =MIN(IFERROR('IN_TECH'!$D$36/'ENG_OPS'!$L$13,1E+15),IFERROR('IN_TECH'!$E$36/'ENG_OPS'!$L$14,1E+15),IFERROR('IN_TECH'!$F$36/'ENG_OPS'!$L$15,1E+15),IFERROR('IN_TECH'!$G$36/'ENG_OPS'!$L$16,1E+15),IFERROR('IN_TECH'!$H$36/'ENG_OPS'!$L$17,1E+15),IFERROR('IN_TECH'!$I$36/'ENG_OPS'!$L$18,1E+15)) | M19: =MIN(IFERROR('IN_TECH'!$D$36/'ENG_OPS'!$M$13,1E+15),IFERROR('IN_TECH'!$E$36/'ENG_OPS'!$M$14,1E+15),IFERROR('IN_TECH'!$F$36/'ENG_OPS'!$M$15,1E+15),IFERROR('IN_TECH'!$G$36/'ENG_OPS'!$M$16,1E+15),IFERROR('IN_TECH'!$H$36/'ENG_OPS'!$M$17,1E+15),IFERROR('IN_TECH'!$I$36/'ENG_OPS'!$M$18,1E+15)) | N19: =MIN(IFERROR('IN_TECH'!$D$36/'ENG_OPS'!$N$13,1E+15),IFERROR('IN_TECH'!$E$36/'ENG_OPS'!$N$14,1E+15),IFERROR('IN_TECH'!$F$36/'ENG_OPS'!$N$15,1E+15),IFERROR('IN_TECH'!$G$36/'ENG_OPS'!$N$16,1E+15),IFERROR('IN_TECH'!$H$36/'ENG_OPS'!$N$17,1E+15),IFERROR('IN_TECH'!$I$36/'ENG_OPS'!$N$18,1E+15)) | O19: =MIN(IFERROR('IN_TECH'!$D$36/'ENG_OPS'!$O$13,1E+15),IFERROR('IN_TECH'!$E$36/'ENG_OPS'!$O$14,1E+15),IFERROR('IN_TECH'!$F$36/'ENG_OPS'!$O$15,1E+15),IFERROR('IN_TECH'!$G$36/'ENG_OPS'!$O$16,1E+15),IFERROR('IN_TECH'!$H$36/'ENG_OPS'!$O$17,1E+15),IFERROR('IN_TECH'!$I$36/'ENG_OPS'!$O$18,1E+15)) | P19: =MIN(IFERROR('IN_TECH'!$D$36/'ENG_OPS'!$P$13,1E+15),IFERROR('IN_TECH'!$E$36/'ENG_OPS'!$P$14,1E+15),IFERROR('IN_TECH'!$F$36/'ENG_OPS'!$P$15,1E+15),IFERROR('IN_TECH'!$G$36/'ENG_OPS'!$P$16,1E+15),IFERROR('IN_TECH'!$H$36/'ENG_OPS'!$P$17,1E+15),IFERROR('IN_TECH'!$I$36/'ENG_OPS'!$P$18,1E+15))
A20: ورودی واقعی باتری ضایعاتی | B20: OPS.intake | C20: تن | D20: =MIN('IN_TECH'!$D$8*'ENG_OPS'!$D$12,'ENG_OPS'!$D$19) | E20: =MIN('IN_TECH'!$D$8*'ENG_OPS'!$E$12,'ENG_OPS'!$E$19) | F20: =MIN('IN_TECH'!$D$8*'ENG_OPS'!$F$12,'ENG_OPS'!$F$19) | G20: =MIN('IN_TECH'!$D$8*'ENG_OPS'!$G$12,'ENG_OPS'!$G$19) | H20: =MIN('IN_TECH'!$D$8*'ENG_OPS'!$H$12,'ENG_OPS'!$H$19) | I20: =MIN('IN_TECH'!$D$8*'ENG_OPS'!$I$12,'ENG_OPS'!$I$19) | J20: =MIN('IN_TECH'!$D$8*'ENG_OPS'!$J$12,'ENG_OPS'!$J$19) | K20: =MIN('IN_TECH'!$D$8*'ENG_OPS'!$K$12,'ENG_OPS'!$K$19) | L20: =MIN('IN_TECH'!$D$8*'ENG_OPS'!$L$12,'ENG_OPS'!$L$19) | M20: =MIN('IN_TECH'!$D$8*'ENG_OPS'!$M$12,'ENG_OPS'!$M$19) | N20: =MIN('IN_TECH'!$D$8*'ENG_OPS'!$N$12,'ENG_OPS'!$N$19) | O20: =MIN('IN_TECH'!$D$8*'ENG_OPS'!$O$12,'ENG_OPS'!$O$19) | P20: =MIN('IN_TECH'!$D$8*'ENG_OPS'!$P$12,'ENG_OPS'!$P$19)
A21: ساعات اسمی کارکرد در سال | B21: OPS.hours_nom | C21: ساعت | D21: ='IN_TECH'!$D$9*'IN_TECH'!$D$10*'IN_TECH'!$D$11 | E21: ='IN_TECH'!$D$9*'IN_TECH'!$D$10*'IN_TECH'!$D$11 | F21: ='IN_TECH'!$D$9*'IN_TECH'!$D$10*'IN_TECH'!$D$11 | G21: ='IN_TECH'!$D$9*'IN_TECH'!$D$10*'IN_TECH'!$D$11 | H21: ='IN_TECH'!$D$9*'IN_TECH'!$D$10*'IN_TECH'!$D$11 | I21: ='IN_TECH'!$D$9*'IN_TECH'!$D$10*'IN_TECH'!$D$11 | J21: ='IN_TECH'!$D$9*'IN_TECH'!$D$10*'IN_TECH'!$D$11 | K21: ='IN_TECH'!$D$9*'IN_TECH'!$D$10*'IN_TECH'!$D$11 | ... P21: ='IN_TECH'!$D$9*'IN_TECH'!$D$10*'IN_TECH'!$D$11
A22: ساعات مؤثر کارکرد | B22: OPS.hours | C22: ساعت | D22: =MAX(0,('ENG_OPS'!$D$21-'IN_TECH'!$D$12-'IN_TECH'!$D$13))*'ENG_OPS'!$D$12 | E22: =MAX(0,('ENG_OPS'!$E$21-'IN_TECH'!$D$12-'IN_TECH'!$D$13))*'ENG_OPS'!$E$12 | F22: =MAX(0,('ENG_OPS'!$F$21-'IN_TECH'!$D$12-'IN_TECH'!$D$13))*'ENG_OPS'!$F$12 | G22: =MAX(0,('ENG_OPS'!$G$21-'IN_TECH'!$D$12-'IN_TECH'!$D$13))*'ENG_OPS'!$G$12 | H22: =MAX(0,('ENG_OPS'!$H$21-'IN_TECH'!$D$12-'IN_TECH'!$D$13))*'ENG_OPS'!$H$12 | I22: =MAX(0,('ENG_OPS'!$I$21-'IN_TECH'!$D$12-'IN_TECH'!$D$13))*'ENG_OPS'!$I$12 | J22: =MAX(0,('ENG_OPS'!$J$21-'IN_TECH'!$D$12-'IN_TECH'!$D$13))*'ENG_OPS'!$J$12 | K22: =MAX(0,('ENG_OPS'!$K$21-'IN_TECH'!$D$12-'IN_TECH'!$D$13))*'ENG_OPS'!$K$12 | L22: =MAX(0,('ENG_OPS'!$L$21-'IN_TECH'!$D$12-'IN_TECH'!$D$13))*'ENG_OPS'!$L$12 | M22: =MAX(0,('ENG_OPS'!$M$21-'IN_TECH'!$D$12-'IN_TECH'!$D$13))*'ENG_OPS'!$M$12 | N22: =MAX(0,('ENG_OPS'!$N$21-'IN_TECH'!$D$12-'IN_TECH'!$D$13))*'ENG_OPS'!$N$12 | O22: =MAX(0,('ENG_OPS'!$O$21-'IN_TECH'!$D$12-'IN_TECH'!$D$13))*'ENG_OPS'!$O$12 | P22: =MAX(0,('ENG_OPS'!$P$21-'IN_TECH'!$D$12-'IN_TECH'!$D$13))*'ENG_OPS'!$P$12
A23: نرخ استفاده از ظرفیت اسمی | B23: OPS.caputil | C23: درصد | D23: =IFERROR('ENG_OPS'!$D$20/'IN_TECH'!$D$8,0) | E23: =IFERROR('ENG_OPS'!$E$20/'IN_TECH'!$D$8,0) | F23: =IFERROR('ENG_OPS'!$F$20/'IN_TECH'!$D$8,0) | G23: =IFERROR('ENG_OPS'!$G$20/'IN_TECH'!$D$8,0) | H23: =IFERROR('ENG_OPS'!$H$20/'IN_TECH'!$D$8,0) | I23: =IFERROR('ENG_OPS'!$I$20/'IN_TECH'!$D$8,0) | J23: =IFERROR('ENG_OPS'!$J$20/'IN_TECH'!$D$8,0) | K23: =IFERROR('ENG_OPS'!$K$20/'IN_TECH'!$D$8,0) | L23: =IFERROR('ENG_OPS'!$L$20/'IN_TECH'!$D$8,0) | M23: =IFERROR('ENG_OPS'!$M$20/'IN_TECH'!$D$8,0) | N23: =IFERROR('ENG_OPS'!$N$20/'IN_TECH'!$D$8,0) | O23: =IFERROR('ENG_OPS'!$O$20/'IN_TECH'!$D$8,0) | P23: =IFERROR('ENG_OPS'!$P$20/'IN_TECH'!$D$8,0)
A25: ب) جریان مواد و تراز جرم
A26: خروجی ایستگاه ۱ (پس از تخلیه) | B26: OPS.s1out | C26: تن | D26: ='ENG_OPS'!$D$20*(1-'IN_TECH'!$D$40) | E26: ='ENG_OPS'!$E$20*(1-'IN_TECH'!$D$40) | F26: ='ENG_OPS'!$F$20*(1-'IN_TECH'!$D$40) | G26: ='ENG_OPS'!$G$20*(1-'IN_TECH'!$D$40) | H26: ='ENG_OPS'!$H$20*(1-'IN_TECH'!$D$40) | I26: ='ENG_OPS'!$I$20*(1-'IN_TECH'!$D$40) | J26: ='ENG_OPS'!$J$20*(1-'IN_TECH'!$D$40) | K26: ='ENG_OPS'!$K$20*(1-'IN_TECH'!$D$40) | L26: ='ENG_OPS'!$L$20*(1-'IN_TECH'!$D$40) | M26: ='ENG_OPS'!$M$20*(1-'IN_TECH'!$D$40) | N26: ='ENG_OPS'!$N$20*(1-'IN_TECH'!$D$40) | O26: ='ENG_OPS'!$O$20*(1-'IN_TECH'!$D$40) | P26: ='ENG_OPS'!$P$20*(1-'IN_TECH'!$D$40)
A27: خروجی ایستگاه ۲ (پس از خردایش) | B27: OPS.s2out | C27: تن | D27: ='ENG_OPS'!$D$26*(1-'IN_TECH'!$E$40) | E27: ='ENG_OPS'!$E$26*(1-'IN_TECH'!$E$40) | F27: ='ENG_OPS'!$F$26*(1-'IN_TECH'!$E$40) | G27: ='ENG_OPS'!$G$26*(1-'IN_TECH'!$E$40) | H27: ='ENG_OPS'!$H$26*(1-'IN_TECH'!$E$40) | I27: ='ENG_OPS'!$I$26*(1-'IN_TECH'!$E$40) | J27: ='ENG_OPS'!$J$26*(1-'IN_TECH'!$E$40) | K27: ='ENG_OPS'!$K$26*(1-'IN_TECH'!$E$40) | L27: ='ENG_OPS'!$L$26*(1-'IN_TECH'!$E$40) | M27: ='ENG_OPS'!$M$26*(1-'IN_TECH'!$E$40) | N27: ='ENG_OPS'!$N$26*(1-'IN_TECH'!$E$40) | O27: ='ENG_OPS'!$O$26*(1-'IN_TECH'!$E$40) | P27: ='ENG_OPS'!$P$26*(1-'IN_TECH'!$E$40)
A28: خمیر سرب (جریان تفکیک‌شده) | B28: OPS.paste | C28: تن | D28: ='ENG_OPS'!$D$27*'IN_TECH'!$D$27 | E28: ='ENG_OPS'!$E$27*'IN_TECH'!$D$27 | F28: ='ENG_OPS'!$F$27*'IN_TECH'!$D$27 | G28: ='ENG_OPS'!$G$27*'IN_TECH'!$D$27 | H28: ='ENG_OPS'!$H$27*'IN_TECH'!$D$27 | I28: ='ENG_OPS'!$I$27*'IN_TECH'!$D$27 | J28: ='ENG_OPS'!$J$27*'IN_TECH'!$D$27 | K28: ='ENG_OPS'!$K$27*'IN_TECH'!$D$27 | L28: ='ENG_OPS'!$L$27*'IN_TECH'!$D$27 | M28: ='ENG_OPS'!$M$27*'IN_TECH'!$D$27 | N28: ='ENG_OPS'!$N$27*'IN_TECH'!$D$27 | O28: ='ENG_OPS'!$O$27*'IN_TECH'!$D$27 | P28: ='ENG_OPS'!$P$27*'IN_TECH'!$D$27
A29: قطعات فلزی سربی (جریان تفکیک‌شده) | B29: OPS.metal | C29: تن | D29: ='ENG_OPS'!$D$27*'IN_TECH'!$D$28 | E29: ='ENG_OPS'!$E$27*'IN_TECH'!$D$28 | F29: ='ENG_OPS'!$F$27*'IN_TECH'!$D$28 | G29: ='ENG_OPS'!$G$27*'IN_TECH'!$D$28 | H29: ='ENG_OPS'!$H$27*'IN_TECH'!$D$28 | I29: ='ENG_OPS'!$I$27*'IN_TECH'!$D$28 | J29: ='ENG_OPS'!$J$27*'IN_TECH'!$D$28 | K29: ='ENG_OPS'!$K$27*'IN_TECH'!$D$28 | L29: ='ENG_OPS'!$L$27*'IN_TECH'!$D$28 | M29: ='ENG_OPS'!$M$27*'IN_TECH'!$D$28 | N29: ='ENG_OPS'!$N$27*'IN_TECH'!$D$28 | O29: ='ENG_OPS'!$O$27*'IN_TECH'!$D$28 | P29: ='ENG_OPS'!$P$27*'IN_TECH'!$D$28
A30: پلی‌پروپیلن (جریان تفکیک‌شده) | B30: OPS.pp | C30: تن | D30: ='ENG_OPS'!$D$27*'IN_TECH'!$D$29 | E30: ='ENG_OPS'!$E$27*'IN_TECH'!$D$29 | F30: ='ENG_OPS'!$F$27*'IN_TECH'!$D$29 | G30: ='ENG_OPS'!$G$27*'IN_TECH'!$D$29 | H30: ='ENG_OPS'!$H$27*'IN_TECH'!$D$29 | I30: ='ENG_OPS'!$I$27*'IN_TECH'!$D$29 | J30: ='ENG_OPS'!$J$27*'IN_TECH'!$D$29 | K30: ='ENG_OPS'!$K$27*'IN_TECH'!$D$29 | L30: ='ENG_OPS'!$L$27*'IN_TECH'!$D$29 | M30: ='ENG_OPS'!$M$27*'IN_TECH'!$D$29 | N30: ='ENG_OPS'!$N$27*'IN_TECH'!$D$29 | O30: ='ENG_OPS'!$O$27*'IN_TECH'!$D$29 | P30: ='ENG_OPS'!$P$27*'IN_TECH'!$D$29
A31: جداکننده و سایر پسماند (جریان تفکیک‌شده) | B31: OPS.res | C31: تن | D31: ='ENG_OPS'!$D$27*'IN_TECH'!$D$31 | E31: ='ENG_OPS'!$E$27*'IN_TECH'!$D$31 | F31: ='ENG_OPS'!$F$27*'IN_TECH'!$D$31 | G31: ='ENG_OPS'!$G$27*'IN_TECH'!$D$31 | H31: ='ENG_OPS'!$H$27*'IN_TECH'!$D$31 | I31: ='ENG_OPS'!$I$27*'IN_TECH'!$D$31 | J31: ='ENG_OPS'!$J$27*'IN_TECH'!$D$31 | K31: ='ENG_OPS'!$K$27*'IN_TECH'!$D$31 | L31: ='ENG_OPS'!$L$27*'IN_TECH'!$D$31 | M31: ='ENG_OPS'!$M$27*'IN_TECH'!$D$31 | N31: ='ENG_OPS'!$N$27*'IN_TECH'!$D$31 | O31: ='ENG_OPS'!$O$27*'IN_TECH'!$D$31 | P31: ='ENG_OPS'!$P$27*'IN_TECH'!$D$31
A32: الکترولیت تخلیه‌شده | B32: OPS.elec | C32: تن | D32: ='ENG_OPS'!$D$20*'IN_TECH'!$D$30 | E32: ='ENG_OPS'!$E$20*'IN_TECH'!$D$30 | F32: ='ENG_OPS'!$F$20*'IN_TECH'!$D$30 | G32: ='ENG_OPS'!$G$20*'IN_TECH'!$D$30 | H32: ='ENG_OPS'!$H$20*'IN_TECH'!$D$30 | I32: ='ENG_OPS'!$I$20*'IN_TECH'!$D$30 | J32: ='ENG_OPS'!$J$20*'IN_TECH'!$D$30 | K32: ='ENG_OPS'!$K$20*'IN_TECH'!$D$30 | L32: ='ENG_OPS'!$L$20*'IN_TECH'!$D$30 | M32: ='ENG_OPS'!$M$20*'IN_TECH'!$D$30 | N32: ='ENG_OPS'!$N$20*'IN_TECH'!$D$30 | O32: ='ENG_OPS'!$O$20*'IN_TECH'!$D$30 | P32: ='ENG_OPS'!$P$20*'IN_TECH'!$D$30
A33: خمیر سولفات‌زدایی‌شده | B33: OPS.paste_ds | C33: تن | D33: ='ENG_OPS'!$D$28*'IN_TECH'!$D$18*(1-'IN_TECH'!$F$40) | E33: ='ENG_OPS'!$E$28*'IN_TECH'!$D$18*(1-'IN_TECH'!$F$40) | F33: ='ENG_OPS'!$F$28*'IN_TECH'!$D$18*(1-'IN_TECH'!$F$40) | G33: ='ENG_OPS'!$G$28*'IN_TECH'!$D$18*(1-'IN_TECH'!$F$40) | H33: ='ENG_OPS'!$H$28*'IN_TECH'!$D$18*(1-'IN_TECH'!$F$40) | I33: ='ENG_OPS'!$I$28*'IN_TECH'!$D$18*(1-'IN_TECH'!$F$40) | J33: ='ENG_OPS'!$J$28*'IN_TECH'!$D$18*(1-'IN_TECH'!$F$40) | K33: ='ENG_OPS'!$K$28*'IN_TECH'!$D$18*(1-'IN_TECH'!$F$40) | L33: ='ENG_OPS'!$L$28*'IN_TECH'!$D$18*(1-'IN_TECH'!$F$40) | M33: ='ENG_OPS'!$M$28*'IN_TECH'!$D$18*(1-'IN_TECH'!$F$40) | N33: ='ENG_OPS'!$N$28*'IN_TECH'!$D$18*(1-'IN_TECH'!$F$40) | O33: ='ENG_OPS'!$O$28*'IN_TECH'!$D$18*(1-'IN_TECH'!$F$40) | P33: ='ENG_OPS'!$P$28*'IN_TECH'!$D$18*(1-'IN_TECH'!$F$40)
A34: سرب ورودی به کوره | B34: OPS.furnace_pb | C34: تن | D34: ='ENG_OPS'!$D$33*'IN_TECH'!$D$16+'ENG_OPS'!$D$29*'IN_TECH'!$D$17 | E34: ='ENG_OPS'!$E$33*'IN_TECH'!$D$16+'ENG_OPS'!$E$29*'IN_TECH'!$D$17 | F34: ='ENG_OPS'!$F$33*'IN_TECH'!$D$16+'ENG_OPS'!$F$29*'IN_TECH'!$D$17 | G34: ='ENG_OPS'!$G$33*'IN_TECH'!$D$16+'ENG_OPS'!$G$29*'IN_TECH'!$D$17 | H34: ='ENG_OPS'!$H$33*'IN_TECH'!$D$16+'ENG_OPS'!$H$29*'IN_TECH'!$D$17 | I34: ='ENG_OPS'!$I$33*'IN_TECH'!$D$16+'ENG_OPS'!$I$29*'IN_TECH'!$D$17 | J34: ='ENG_OPS'!$J$33*'IN_TECH'!$D$16+'ENG_OPS'!$J$29*'IN_TECH'!$D$17 | K34: ='ENG_OPS'!$K$33*'IN_TECH'!$D$16+'ENG_OPS'!$K$29*'IN_TECH'!$D$17 | L34: ='ENG_OPS'!$L$33*'IN_TECH'!$D$16+'ENG_OPS'!$L$29*'IN_TECH'!$D$17 | M34: ='ENG_OPS'!$M$33*'IN_TECH'!$D$16+'ENG_OPS'!$M$29*'IN_TECH'!$D$17 | N34: ='ENG_OPS'!$N$33*'IN_TECH'!$D$16+'ENG_OPS'!$N$29*'IN_TECH'!$D$17 | O34: ='ENG_OPS'!$O$33*'IN_TECH'!$D$16+'ENG_OPS'!$O$29*'IN_TECH'!$D$17 | P34: ='ENG_OPS'!$P$33*'IN_TECH'!$D$16+'ENG_OPS'!$P$29*'IN_TECH'!$D$17
A35: سرب خام خروجی کوره | B35: OPS.crude | C35: تن | D35: ='ENG_OPS'!$D$34*'IN_TECH'!$D$19*(1-'IN_TECH'!$G$40) | E35: ='ENG_OPS'!$E$34*'IN_TECH'!$D$19*(1-'IN_TECH'!$G$40) | F35: ='ENG_OPS'!$F$34*'IN_TECH'!$D$19*(1-'IN_TECH'!$G$40) | G35: ='ENG_OPS'!$G$34*'IN_TECH'!$D$19*(1-'IN_TECH'!$G$40) | H35: ='ENG_OPS'!$H$34*'IN_TECH'!$D$19*(1-'IN_TECH'!$G$40) | I35: ='ENG_OPS'!$I$34*'IN_TECH'!$D$19*(1-'IN_TECH'!$G$40) | J35: ='ENG_OPS'!$J$34*'IN_TECH'!$D$19*(1-'IN_TECH'!$G$40) | K35: ='ENG_OPS'!$K$34*'IN_TECH'!$D$19*(1-'IN_TECH'!$G$40) | L35: ='ENG_OPS'!$L$34*'IN_TECH'!$D$19*(1-'IN_TECH'!$G$40) | M35: ='ENG_OPS'!$M$34*'IN_TECH'!$D$19*(1-'IN_TECH'!$G$40) | N35: ='ENG_OPS'!$N$34*'IN_TECH'!$D$19*(1-'IN_TECH'!$G$40) | O35: ='ENG_OPS'!$O$34*'IN_TECH'!$D$19*(1-'IN_TECH'!$G$40) | P35: ='ENG_OPS'!$P$34*'IN_TECH'!$D$19*(1-'IN_TECH'!$G$40)
A36: سرب تصفیه‌شده | B36: OPS.refined | C36: تن | D36: ='ENG_OPS'!$D$35*'IN_TECH'!$D$20*(1-'IN_TECH'!$H$40) | E36: ='ENG_OPS'!$E$35*'IN_TECH'!$D$20*(1-'IN_TECH'!$H$40) | F36: ='ENG_OPS'!$F$35*'IN_TECH'!$D$20*(1-'IN_TECH'!$H$40) | G36: ='ENG_OPS'!$G$35*'IN_TECH'!$D$20*(1-'IN_TECH'!$H$40) | H36: ='ENG_OPS'!$H$35*'IN_TECH'!$D$20*(1-'IN_TECH'!$H$40) | I36: ='ENG_OPS'!$I$35*'IN_TECH'!$D$20*(1-'IN_TECH'!$H$40) | J36: ='ENG_OPS'!$J$35*'IN_TECH'!$D$20*(1-'IN_TECH'!$H$40) | K36: ='ENG_OPS'!$K$35*'IN_TECH'!$D$20*(1-'IN_TECH'!$H$40) | L36: ='ENG_OPS'!$L$35*'IN_TECH'!$D$20*(1-'IN_TECH'!$H$40) | M36: ='ENG_OPS'!$M$35*'IN_TECH'!$D$20*(1-'IN_TECH'!$H$40) | N36: ='ENG_OPS'!$N$35*'IN_TECH'!$D$20*(1-'IN_TECH'!$H$40) | O36: ='ENG_OPS'!$O$35*'IN_TECH'!$D$20*(1-'IN_TECH'!$H$40) | P36: ='ENG_OPS'!$P$35*'IN_TECH'!$D$20*(1-'IN_TECH'!$H$40)
A38: ج) محصولات قابل فروش
A39: شمش سرب خالص (تولید) | B39: OPS.soft | C39: تن | D39: ='ENG_OPS'!$D$36*'IN_TECH'!$D$23*(1-'IN_TECH'!$I$40) | E39: ='ENG_OPS'!$E$36*'IN_TECH'!$D$23*(1-'IN_TECH'!$I$40) | F39: ='ENG_OPS'!$F$36*'IN_TECH'!$D$23*(1-'IN_TECH'!$I$40) | G39: ='ENG_OPS'!$G$36*'IN_TECH'!$D$23*(1-'IN_TECH'!$I$40) | H39: ='ENG_OPS'!$H$36*'IN_TECH'!$D$23*(1-'IN_TECH'!$I$40) | I39: ='ENG_OPS'!$I$36*'IN_TECH'!$D$23*(1-'IN_TECH'!$I$40) | J39: ='ENG_OPS'!$J$36*'IN_TECH'!$D$23*(1-'IN_TECH'!$I$40) | K39: ='ENG_OPS'!$K$36*'IN_TECH'!$D$23*(1-'IN_TECH'!$I$40) | L39: ='ENG_OPS'!$L$36*'IN_TECH'!$D$23*(1-'IN_TECH'!$I$40) | M39: ='ENG_OPS'!$M$36*'IN_TECH'!$D$23*(1-'IN_TECH'!$I$40) | N39: ='ENG_OPS'!$N$36*'IN_TECH'!$D$23*(1-'IN_TECH'!$I$40) | O39: ='ENG_OPS'!$O$36*'IN_TECH'!$D$23*(1-'IN_TECH'!$I$40) | P39: ='ENG_OPS'!$P$36*'IN_TECH'!$D$23*(1-'IN_TECH'!$I$40)
A40: شمش آلیاژ سرب (تولید) | B40: OPS.alloy | C40: تن | D40: ='ENG_OPS'!$D$36*'IN_TECH'!$D$24*(1-'IN_TECH'!$I$40) | E40: ='ENG_OPS'!$E$36*'IN_TECH'!$D$24*(1-'IN_TECH'!$I$40) | F40: ='ENG_OPS'!$F$36*'IN_TECH'!$D$24*(1-'IN_TECH'!$I$40) | G40: ='ENG_OPS'!$G$36*'IN_TECH'!$D$24*(1-'IN_TECH'!$I$40) | H40: ='ENG_OPS'!$H$36*'IN_TECH'!$D$24*(1-'IN_TECH'!$I$40) | I40: ='ENG_OPS'!$I$36*'IN_TECH'!$D$24*(1-'IN_TECH'!$I$40) | J40: ='ENG_OPS'!$J$36*'IN_TECH'!$D$24*(1-'IN_TECH'!$I$40) | K40: ='ENG_OPS'!$K$36*'IN_TECH'!$D$24*(1-'IN_TECH'!$I$40) | L40: ='ENG_OPS'!$L$36*'IN_TECH'!$D$24*(1-'IN_TECH'!$I$40) | M40: ='ENG_OPS'!$M$36*'IN_TECH'!$D$24*(1-'IN_TECH'!$I$40) | N40: ='ENG_OPS'!$N$36*'IN_TECH'!$D$24*(1-'IN_TECH'!$I$40) | O40: ='ENG_OPS'!$O$36*'IN_TECH'!$D$24*(1-'IN_TECH'!$I$40) | P40: ='ENG_OPS'!$P$36*'IN_TECH'!$D$24*(1-'IN_TECH'!$I$40)
A41: گرانول پلی‌پروپیلن (تولید) | B41: OPS.ppg | C41: تن | D41: ='ENG_OPS'!$D$30*'IN_TECH'!$D$21*(1-'IN_TECH'!$I$40) | E41: ='ENG_OPS'!$E$30*'IN_TECH'!$D$21*(1-'IN_TECH'!$I$40) | F41: ='ENG_OPS'!$F$30*'IN_TECH'!$D$21*(1-'IN_TECH'!$I$40) | G41: ='ENG_OPS'!$G$30*'IN_TECH'!$D$21*(1-'IN_TECH'!$I$40) | H41: ='ENG_OPS'!$H$30*'IN_TECH'!$D$21*(1-'IN_TECH'!$I$40) | I41: ='ENG_OPS'!$I$30*'IN_TECH'!$D$21*(1-'IN_TECH'!$I$40) | J41: ='ENG_OPS'!$J$30*'IN_TECH'!$D$21*(1-'IN_TECH'!$I$40) | K41: ='ENG_OPS'!$K$30*'IN_TECH'!$D$21*(1-'IN_TECH'!$I$40) | L41: ='ENG_OPS'!$L$30*'IN_TECH'!$D$21*(1-'IN_TECH'!$I$40) | M41: ='ENG_OPS'!$M$30*'IN_TECH'!$D$21*(1-'IN_TECH'!$I$40) | N41: ='ENG_OPS'!$N$30*'IN_TECH'!$D$21*(1-'IN_TECH'!$I$40) | O41: ='ENG_OPS'!$O$30*'IN_TECH'!$D$21*(1-'IN_TECH'!$I$40) | P41: ='ENG_OPS'!$P$30*'IN_TECH'!$D$21*(1-'IN_TECH'!$I$40)
A42: سولفات سدیم (تولید) | B42: OPS.na2so4 | C42: تن | D42: ='ENG_OPS'!$D$20*'IN_TECH'!$D$22*(1-'IN_TECH'!$I$40) | E42: ='ENG_OPS'!$E$20*'IN_TECH'!$D$22*(1-'IN_TECH'!$I$40) | F42: ='ENG_OPS'!$F$20*'IN_TECH'!$D$22*(1-'IN_TECH'!$I$40) | G42: ='ENG_OPS'!$G$20*'IN_TECH'!$D$22*(1-'IN_TECH'!$I$40) | H42: ='ENG_OPS'!$H$20*'IN_TECH'!$D$22*(1-'IN_TECH'!$I$40) | I42: ='ENG_OPS'!$I$20*'IN_TECH'!$D$22*(1-'IN_TECH'!$I$40) | J42: ='ENG_OPS'!$J$20*'IN_TECH'!$D$22*(1-'IN_TECH'!$I$40) | K42: ='ENG_OPS'!$K$20*'IN_TECH'!$D$22*(1-'IN_TECH'!$I$40) | L42: ='ENG_OPS'!$L$20*'IN_TECH'!$D$22*(1-'IN_TECH'!$I$40) | M42: ='ENG_OPS'!$M$20*'IN_TECH'!$D$22*(1-'IN_TECH'!$I$40) | N42: ='ENG_OPS'!$N$20*'IN_TECH'!$D$22*(1-'IN_TECH'!$I$40) | O42: ='ENG_OPS'!$O$20*'IN_TECH'!$D$22*(1-'IN_TECH'!$I$40) | P42: ='ENG_OPS'!$P$20*'IN_TECH'!$D$22*(1-'IN_TECH'!$I$40)
A43: جمع محصولات تولیدی | B43: OPS.prod_total | C43: تن | D43: ='ENG_OPS'!$D$39+'ENG_OPS'!$D$40+'ENG_OPS'!$D$41+'ENG_OPS'!$D$42 | E43: ='ENG_OPS'!$E$39+'ENG_OPS'!$E$40+'ENG_OPS'!$E$41+'ENG_OPS'!$E$42 | F43: ='ENG_OPS'!$F$39+'ENG_OPS'!$F$40+'ENG_OPS'!$F$41+'ENG_OPS'!$F$42 | G43: ='ENG_OPS'!$G$39+'ENG_OPS'!$G$40+'ENG_OPS'!$G$41+'ENG_OPS'!$G$42 | H43: ='ENG_OPS'!$H$39+'ENG_OPS'!$H$40+'ENG_OPS'!$H$41+'ENG_OPS'!$H$42 | I43: ='ENG_OPS'!$I$39+'ENG_OPS'!$I$40+'ENG_OPS'!$I$41+'ENG_OPS'!$I$42 | J43: ='ENG_OPS'!$J$39+'ENG_OPS'!$J$40+'ENG_OPS'!$J$41+'ENG_OPS'!$J$42 | K43: ='ENG_OPS'!$K$39+'ENG_OPS'!$K$40+'ENG_OPS'!$K$41+'ENG_OPS'!$K$42 | L43: ='ENG_OPS'!$L$39+'ENG_OPS'!$L$40+'ENG_OPS'!$L$41+'ENG_OPS'!$L$42 | M43: ='ENG_OPS'!$M$39+'ENG_OPS'!$M$40+'ENG_OPS'!$M$41+'ENG_OPS'!$M$42 | N43: ='ENG_OPS'!$N$39+'ENG_OPS'!$N$40+'ENG_OPS'!$N$41+'ENG_OPS'!$N$42 | O43: ='ENG_OPS'!$O$39+'ENG_OPS'!$O$40+'ENG_OPS'!$O$41+'ENG_OPS'!$O$42 | P43: ='ENG_OPS'!$P$39+'ENG_OPS'!$P$40+'ENG_OPS'!$P$41+'ENG_OPS'!$P$42
A44: ضایعات و پسماند (کنترل تراز) | B44: OPS.waste | C44: تن | D44: ='ENG_OPS'!$D$20-'ENG_OPS'!$D$43 | E44: ='ENG_OPS'!$E$20-'ENG_OPS'!$E$43 | F44: ='ENG_OPS'!$F$20-'ENG_OPS'!$F$43 | G44: ='ENG_OPS'!$G$20-'ENG_OPS'!$G$43 | H44: ='ENG_OPS'!$H$20-'ENG_OPS'!$H$43 | I44: ='ENG_OPS'!$I$20-'ENG_OPS'!$I$43 | J44: ='ENG_OPS'!$J$20-'ENG_OPS'!$J$43 | K44: ='ENG_OPS'!$K$20-'ENG_OPS'!$K$43 | L44: ='ENG_OPS'!$L$20-'ENG_OPS'!$L$43 | M44: ='ENG_OPS'!$M$20-'ENG_OPS'!$M$43 | N44: ='ENG_OPS'!$N$20-'ENG_OPS'!$N$43 | O44: ='ENG_OPS'!$O$20-'ENG_OPS'!$O$43 | P44: ='ENG_OPS'!$P$20-'ENG_OPS'!$P$43
A46: د) ورودی و بارگذاری ایستگاه‌ها
A47: ورودی ایستگاه 1 | B47: OPS.feed.0 | C47: تن | D47: ='ENG_OPS'!$D$20 | E47: ='ENG_OPS'!$E$20 | F47: ='ENG_OPS'!$F$20 | G47: ='ENG_OPS'!$G$20 | H47: ='ENG_OPS'!$H$20 | I47: ='ENG_OPS'!$I$20 | J47: ='ENG_OPS'!$J$20 | K47: ='ENG_OPS'!$K$20 | L47: ='ENG_OPS'!$L$20 | M47: ='ENG_OPS'!$M$20 | N47: ='ENG_OPS'!$N$20 | O47: ='ENG_OPS'!$O$20 | P47: ='ENG_OPS'!$P$20
A48: ورودی ایستگاه 2 | B48: OPS.feed.1 | C48: تن | D48: ='ENG_OPS'!$D$26 | E48: ='ENG_OPS'!$E$26 | F48: ='ENG_OPS'!$F$26 | G48: ='ENG_OPS'!$G$26 | H48: ='ENG_OPS'!$H$26 | I48: ='ENG_OPS'!$I$26 | J48: ='ENG_OPS'!$J$26 | K48: ='ENG_OPS'!$K$26 | L48: ='ENG_OPS'!$L$26 | M48: ='ENG_OPS'!$M$26 | N48: ='ENG_OPS'!$N$26 | O48: ='ENG_OPS'!$O$26 | P48: ='ENG_OPS'!$P$26
A49: ورودی ایستگاه 3 | B49: OPS.feed.2 | C49: تن | D49: ='ENG_OPS'!$D$28 | E49: ='ENG_OPS'!$E$28 | F49: ='ENG_OPS'!$F$28 | G49: ='ENG_OPS'!$G$28 | H49: ='ENG_OPS'!$H$28 | I49: ='ENG_OPS'!$I$28 | J49: ='ENG_OPS'!$J$28 | K49: ='ENG_OPS'!$K$28 | L49: ='ENG_OPS'!$L$28 | M49: ='ENG_OPS'!$M$28 | N49: ='ENG_OPS'!$N$28 | O49: ='ENG_OPS'!$O$28 | P49: ='ENG_OPS'!$P$28
A50: ورودی ایستگاه 4 | B50: OPS.feed.3 | C50: تن | D50: ='ENG_OPS'!$D$33+'ENG_OPS'!$D$29 | E50: ='ENG_OPS'!$E$33+'ENG_OPS'!$E$29 | F50: ='ENG_OPS'!$F$33+'ENG_OPS'!$F$29 | G50: ='ENG_OPS'!$G$33+'ENG_OPS'!$G$29 | H50: ='ENG_OPS'!$H$33+'ENG_OPS'!$H$29 | I50: ='ENG_OPS'!$I$33+'ENG_OPS'!$I$29 | J50: ='ENG_OPS'!$J$33+'ENG_OPS'!$J$29 | K50: ='ENG_OPS'!$K$33+'ENG_OPS'!$K$29 | L50: ='ENG_OPS'!$L$33+'ENG_OPS'!$L$29 | M50: ='ENG_OPS'!$M$33+'ENG_OPS'!$M$29 | N50: ='ENG_OPS'!$N$33+'ENG_OPS'!$N$29 | O50: ='ENG_OPS'!$O$33+'ENG_OPS'!$O$29 | P50: ='ENG_OPS'!$P$33+'ENG_OPS'!$P$29
A51: ورودی ایستگاه 5 | B51: OPS.feed.4 | C51: تن | D51: ='ENG_OPS'!$D$35 | E51: ='ENG_OPS'!$E$35 | F51: ='ENG_OPS'!$F$35 | G51: ='ENG_OPS'!$G$35 | H51: ='ENG_OPS'!$H$35 | I51: ='ENG_OPS'!$I$35 | J51: ='ENG_OPS'!$J$35 | K51: ='ENG_OPS'!$K$35 | L51: ='ENG_OPS'!$L$35 | M51: ='ENG_OPS'!$M$35 | N51: ='ENG_OPS'!$N$35 | O51: ='ENG_OPS'!$O$35 | P51: ='ENG_OPS'!$P$35
A52: ورودی ایستگاه 6 | B52: OPS.feed.5 | C52: تن | D52: ='ENG_OPS'!$D$36+'ENG_OPS'!$D$41/(1-'IN_TECH'!$I$40)+'ENG_OPS'!$D$42/(1-'IN_TECH'!$I$40) | E52: ='ENG_OPS'!$E$36+'ENG_OPS'!$E$41/(1-'IN_TECH'!$I$40)+'ENG_OPS'!$E$42/(1-'IN_TECH'!$I$40) | F52: ='ENG_OPS'!$F$36+'ENG_OPS'!$F$41/(1-'IN_TECH'!$I$40)+'ENG_OPS'!$F$42/(1-'IN_TECH'!$I$40) | G52: ='ENG_OPS'!$G$36+'ENG_OPS'!$G$41/(1-'IN_TECH'!$I$40)+'ENG_OPS'!$G$42/(1-'IN_TECH'!$I$40) | H52: ='ENG_OPS'!$H$36+'ENG_OPS'!$H$41/(1-'IN_TECH'!$I$40)+'ENG_OPS'!$H$42/(1-'IN_TECH'!$I$40) | I52: ='ENG_OPS'!$I$36+'ENG_OPS'!$I$41/(1-'IN_TECH'!$I$40)+'ENG_OPS'!$I$42/(1-'IN_TECH'!$I$40) | J52: ='ENG_OPS'!$J$36+'ENG_OPS'!$J$41/(1-'IN_TECH'!$I$40)+'ENG_OPS'!$J$42/(1-'IN_TECH'!$I$40) | K52: ='ENG_OPS'!$K$36+'ENG_OPS'!$K$41/(1-'IN_TECH'!$I$40)+'ENG_OPS'!$K$42/(1-'IN_TECH'!$I$40) | L52: ='ENG_OPS'!$L$36+'ENG_OPS'!$L$41/(1-'IN_TECH'!$I$40)+'ENG_OPS'!$L$42/(1-'IN_TECH'!$I$40) | M52: ='ENG_OPS'!$M$36+'ENG_OPS'!$M$41/(1-'IN_TECH'!$I$40)+'ENG_OPS'!$M$42/(1-'IN_TECH'!$I$40) | N52: ='ENG_OPS'!$N$36+'ENG_OPS'!$N$41/(1-'IN_TECH'!$I$40)+'ENG_OPS'!$N$42/(1-'IN_TECH'!$I$40) | O52: ='ENG_OPS'!$O$36+'ENG_OPS'!$O$41/(1-'IN_TECH'!$I$40)+'ENG_OPS'!$O$42/(1-'IN_TECH'!$I$40) | P52: ='ENG_OPS'!$P$36+'ENG_OPS'!$P$41/(1-'IN_TECH'!$I$40)+'ENG_OPS'!$P$42/(1-'IN_TECH'!$I$40)
A53: بارگذاری ایستگاه 1 | B53: S1 | C53: درصد | D53: =IFERROR('ENG_OPS'!$D$47/'IN_TECH'!$D$36,0) | E53: =IFERROR('ENG_OPS'!$E$47/'IN_TECH'!$D$36,0) | F53: =IFERROR('ENG_OPS'!$F$47/'IN_TECH'!$D$36,0) | G53: =IFERROR('ENG_OPS'!$G$47/'IN_TECH'!$D$36,0) | H53: =IFERROR('ENG_OPS'!$H$47/'IN_TECH'!$D$36,0) | I53: =IFERROR('ENG_OPS'!$I$47/'IN_TECH'!$D$36,0) | J53: =IFERROR('ENG_OPS'!$J$47/'IN_TECH'!$D$36,0) | K53: =IFERROR('ENG_OPS'!$K$47/'IN_TECH'!$D$36,0) | L53: =IFERROR('ENG_OPS'!$L$47/'IN_TECH'!$D$36,0) | M53: =IFERROR('ENG_OPS'!$M$47/'IN_TECH'!$D$36,0) | N53: =IFERROR('ENG_OPS'!$N$47/'IN_TECH'!$D$36,0) | O53: =IFERROR('ENG_OPS'!$O$47/'IN_TECH'!$D$36,0) | P53: =IFERROR('ENG_OPS'!$P$47/'IN_TECH'!$D$36,0)
A54: بارگذاری ایستگاه 2 | B54: S2 | C54: درصد | D54: =IFERROR('ENG_OPS'!$D$48/'IN_TECH'!$E$36,0) | E54: =IFERROR('ENG_OPS'!$E$48/'IN_TECH'!$E$36,0) | F54: =IFERROR('ENG_OPS'!$F$48/'IN_TECH'!$E$36,0) | G54: =IFERROR('ENG_OPS'!$G$48/'IN_TECH'!$E$36,0) | H54: =IFERROR('ENG_OPS'!$H$48/'IN_TECH'!$E$36,0) | I54: =IFERROR('ENG_OPS'!$I$48/'IN_TECH'!$E$36,0) | J54: =IFERROR('ENG_OPS'!$J$48/'IN_TECH'!$E$36,0) | K54: =IFERROR('ENG_OPS'!$K$48/'IN_TECH'!$E$36,0) | L54: =IFERROR('ENG_OPS'!$L$48/'IN_TECH'!$E$36,0) | M54: =IFERROR('ENG_OPS'!$M$48/'IN_TECH'!$E$36,0) | N54: =IFERROR('ENG_OPS'!$N$48/'IN_TECH'!$E$36,0) | O54: =IFERROR('ENG_OPS'!$O$48/'IN_TECH'!$E$36,0) | P54: =IFERROR('ENG_OPS'!$P$48/'IN_TECH'!$E$36,0)
A55: بارگذاری ایستگاه 3 | B55: S3 | C55: درصد | D55: =IFERROR('ENG_OPS'!$D$49/'IN_TECH'!$F$36,0) | E55: =IFERROR('ENG_OPS'!$E$49/'IN_TECH'!$F$36,0) | F55: =IFERROR('ENG_OPS'!$F$49/'IN_TECH'!$F$36,0) | G55: =IFERROR('ENG_OPS'!$G$49/'IN_TECH'!$F$36,0) | H55: =IFERROR('ENG_OPS'!$H$49/'IN_TECH'!$F$36,0) | I55: =IFERROR('ENG_OPS'!$I$49/'IN_TECH'!$F$36,0) | J55: =IFERROR('ENG_OPS'!$J$49/'IN_TECH'!$F$36,0) | K55: =IFERROR('ENG_OPS'!$K$49/'IN_TECH'!$F$36,0) | L55: =IFERROR('ENG_OPS'!$L$49/'IN_TECH'!$F$36,0) | M55: =IFERROR('ENG_OPS'!$M$49/'IN_TECH'!$F$36,0) | N55: =IFERROR('ENG_OPS'!$N$49/'IN_TECH'!$F$36,0) | O55: =IFERROR('ENG_OPS'!$O$49/'IN_TECH'!$F$36,0) | P55: =IFERROR('ENG_OPS'!$P$49/'IN_TECH'!$F$36,0)
A56: بارگذاری ایستگاه 4 | B56: S4 | C56: درصد | D56: =IFERROR('ENG_OPS'!$D$50/'IN_TECH'!$G$36,0) | E56: =IFERROR('ENG_OPS'!$E$50/'IN_TECH'!$G$36,0) | F56: =IFERROR('ENG_OPS'!$F$50/'IN_TECH'!$G$36,0) | G56: =IFERROR('ENG_OPS'!$G$50/'IN_TECH'!$G$36,0) | H56: =IFERROR('ENG_OPS'!$H$50/'IN_TECH'!$G$36,0) | I56: =IFERROR('ENG_OPS'!$I$50/'IN_TECH'!$G$36,0) | J56: =IFERROR('ENG_OPS'!$J$50/'IN_TECH'!$G$36,0) | K56: =IFERROR('ENG_OPS'!$K$50/'IN_TECH'!$G$36,0) | L56: =IFERROR('ENG_OPS'!$L$50/'IN_TECH'!$G$36,0) | M56: =IFERROR('ENG_OPS'!$M$50/'IN_TECH'!$G$36,0) | N56: =IFERROR('ENG_OPS'!$N$50/'IN_TECH'!$G$36,0) | O56: =IFERROR('ENG_OPS'!$O$50/'IN_TECH'!$G$36,0) | P56: =IFERROR('ENG_OPS'!$P$50/'IN_TECH'!$G$36,0)
A57: بارگذاری ایستگاه 5 | B57: S5 | C57: درصد | D57: =IFERROR('ENG_OPS'!$D$51/'IN_TECH'!$H$36,0) | E57: =IFERROR('ENG_OPS'!$E$51/'IN_TECH'!$H$36,0) | F57: =IFERROR('ENG_OPS'!$F$51/'IN_TECH'!$H$36,0) | G57: =IFERROR('ENG_OPS'!$G$51/'IN_TECH'!$H$36,0) | H57: =IFERROR('ENG_OPS'!$H$51/'IN_TECH'!$H$36,0) | I57: =IFERROR('ENG_OPS'!$I$51/'IN_TECH'!$H$36,0) | J57: =IFERROR('ENG_OPS'!$J$51/'IN_TECH'!$H$36,0) | K57: =IFERROR('ENG_OPS'!$K$51/'IN_TECH'!$H$36,0) | L57: =IFERROR('ENG_OPS'!$L$51/'IN_TECH'!$H$36,0) | M57: =IFERROR('ENG_OPS'!$M$51/'IN_TECH'!$H$36,0) | N57: =IFERROR('ENG_OPS'!$N$51/'IN_TECH'!$H$36,0) | O57: =IFERROR('ENG_OPS'!$O$51/'IN_TECH'!$H$36,0) | P57: =IFERROR('ENG_OPS'!$P$51/'IN_TECH'!$H$36,0)
A58: بارگذاری ایستگاه 6 | B58: S6 | C58: درصد | D58: =IFERROR('ENG_OPS'!$D$52/'IN_TECH'!$I$36,0) | E58: =IFERROR('ENG_OPS'!$E$52/'IN_TECH'!$I$36,0) | F58: =IFERROR('ENG_OPS'!$F$52/'IN_TECH'!$I$36,0) | G58: =IFERROR('ENG_OPS'!$G$52/'IN_TECH'!$I$36,0) | H58: =IFERROR('ENG_OPS'!$H$52/'IN_TECH'!$I$36,0) | I58: =IFERROR('ENG_OPS'!$I$52/'IN_TECH'!$I$36,0) | J58: =IFERROR('ENG_OPS'!$J$52/'IN_TECH'!$I$36,0) | K58: =IFERROR('ENG_OPS'!$K$52/'IN_TECH'!$I$36,0) | L58: =IFERROR('ENG_OPS'!$L$52/'IN_TECH'!$I$36,0) | M58: =IFERROR('ENG_OPS'!$M$52/'IN_TECH'!$I$36,0) | N58: =IFERROR('ENG_OPS'!$N$52/'IN_TECH'!$I$36,0) | O58: =IFERROR('ENG_OPS'!$O$52/'IN_TECH'!$I$36,0) | P58: =IFERROR('ENG_OPS'!$P$52/'IN_TECH'!$I$36,0)
A59: بیشترین بارگذاری (گلوگاه) | B59: OPS.bottleneck | C59: درصد | D59: =MAX('ENG_OPS'!$D$53,'ENG_OPS'!$D$54,'ENG_OPS'!$D$55,'ENG_OPS'!$D$56,'ENG_OPS'!$D$57,'ENG_OPS'!$D$58) | E59: =MAX('ENG_OPS'!$E$53,'ENG_OPS'!$E$54,'ENG_OPS'!$E$55,'ENG_OPS'!$E$56,'ENG_OPS'!$E$57,'ENG_OPS'!$E$58) | F59: =MAX('ENG_OPS'!$F$53,'ENG_OPS'!$F$54,'ENG_OPS'!$F$55,'ENG_OPS'!$F$56,'ENG_OPS'!$F$57,'ENG_OPS'!$F$58) | G59: =MAX('ENG_OPS'!$G$53,'ENG_OPS'!$G$54,'ENG_OPS'!$G$55,'ENG_OPS'!$G$56,'ENG_OPS'!$G$57,'ENG_OPS'!$G$58) | H59: =MAX('ENG_OPS'!$H$53,'ENG_OPS'!$H$54,'ENG_OPS'!$H$55,'ENG_OPS'!$H$56,'ENG_OPS'!$H$57,'ENG_OPS'!$H$58) | I59: =MAX('ENG_OPS'!$I$53,'ENG_OPS'!$I$54,'ENG_OPS'!$I$55,'ENG_OPS'!$I$56,'ENG_OPS'!$I$57,'ENG_OPS'!$I$58) | J59: =MAX('ENG_OPS'!$J$53,'ENG_OPS'!$J$54,'ENG_OPS'!$J$55,'ENG_OPS'!$J$56,'ENG_OPS'!$J$57,'ENG_OPS'!$J$58) | K59: =MAX('ENG_OPS'!$K$53,'ENG_OPS'!$K$54,'ENG_OPS'!$K$55,'ENG_OPS'!$K$56,'ENG_OPS'!$K$57,'ENG_OPS'!$K$58) | L59: =MAX('ENG_OPS'!$L$53,'ENG_OPS'!$L$54,'ENG_OPS'!$L$55,'ENG_OPS'!$L$56,'ENG_OPS'!$L$57,'ENG_OPS'!$L$58) | M59: =MAX('ENG_OPS'!$M$53,'ENG_OPS'!$M$54,'ENG_OPS'!$M$55,'ENG_OPS'!$M$56,'ENG_OPS'!$M$57,'ENG_OPS'!$M$58) | N59: =MAX('ENG_OPS'!$N$53,'ENG_OPS'!$N$54,'ENG_OPS'!$N$55,'ENG_OPS'!$N$56,'ENG_OPS'!$N$57,'ENG_OPS'!$N$58) | O59: =MAX('ENG_OPS'!$O$53,'ENG_OPS'!$O$54,'ENG_OPS'!$O$55,'ENG_OPS'!$O$56,'ENG_OPS'!$O$57,'ENG_OPS'!$O$58) | P59: =MAX('ENG_OPS'!$P$53,'ENG_OPS'!$P$54,'ENG_OPS'!$P$55,'ENG_OPS'!$P$56,'ENG_OPS'!$P$57,'ENG_OPS'!$P$58)
A60: شماره ایستگاه گلوگاه | B60: OPS.bottleneck_st | C60: شماره | D60: =IFERROR(INDEX('ENG_OPS'!$B$53:$B$58,MATCH('ENG_OPS'!$D$59,INDEX('ENG_OPS'!$D$53:$P$58,1,0),0),1),0) | E60: =IFERROR(INDEX('ENG_OPS'!$B$53:$B$58,MATCH('ENG_OPS'!$E$59,INDEX('ENG_OPS'!$D$53:$P$58,2,0),0),1),0) | F60: =IFERROR(INDEX('ENG_OPS'!$B$53:$B$58,MATCH('ENG_OPS'!$F$59,INDEX('ENG_OPS'!$D$53:$P$58,3,0),0),1),0) | G60: =IFERROR(INDEX('ENG_OPS'!$B$53:$B$58,MATCH('ENG_OPS'!$G$59,INDEX('ENG_OPS'!$D$53:$P$58,4,0),0),1),0) | H60: =IFERROR(INDEX('ENG_OPS'!$B$53:$B$58,MATCH('ENG_OPS'!$H$59,INDEX('ENG_OPS'!$D$53:$P$58,5,0),0),1),0) | I60: =IFERROR(INDEX('ENG_OPS'!$B$53:$B$58,MATCH('ENG_OPS'!$I$59,INDEX('ENG_OPS'!$D$53:$P$58,6,0),0),1),0) | J60: =IFERROR(INDEX('ENG_OPS'!$B$53:$B$58,MATCH('ENG_OPS'!$J$59,INDEX('ENG_OPS'!$D$53:$P$58,7,0),0),1),0) | K60: =IFERROR(INDEX('ENG_OPS'!$B$53:$B$58,MATCH('ENG_OPS'!$K$59,INDEX('ENG_OPS'!$D$53:$P$58,8,0),0),1),0) | L60: =IFERROR(INDEX('ENG_OPS'!$B$53:$B$58,MATCH('ENG_OPS'!$L$59,INDEX('ENG_OPS'!$D$53:$P$58,9,0),0),1),0) | M60: =IFERROR(INDEX('ENG_OPS'!$B$53:$B$58,MATCH('ENG_OPS'!$M$59,INDEX('ENG_OPS'!$D$53:$P$58,10,0),0),1),0) | N60: =IFERROR(INDEX('ENG_OPS'!$B$53:$B$58,MATCH('ENG_OPS'!$N$59,INDEX('ENG_OPS'!$D$53:$P$58,11,0),0),1),0) | O60: =IFERROR(INDEX('ENG_OPS'!$B$53:$B$58,MATCH('ENG_OPS'!$O$59,INDEX('ENG_OPS'!$D$53:$P$58,12,0),0),1),0) | P60: =IFERROR(INDEX('ENG_OPS'!$B$53:$B$58,MATCH('ENG_OPS'!$P$59,INDEX('ENG_OPS'!$D$53:$P$58,13,0),0),1),0)
A62: ه‍) مصارف انرژی و آب
A63: برق مصرفی کل | B63: OPS.kwh | C63: kWh | D63: =('ENG_OPS'!$D$47*'IN_TECH'!$D$41)+('ENG_OPS'!$D$48*'IN_TECH'!$E$41)+('ENG_OPS'!$D$49*'IN_TECH'!$F$41)+('ENG_OPS'!$D$50*'IN_TECH'!$G$41)+('ENG_OPS'!$D$51*'IN_TECH'!$H$41)+('ENG_OPS'!$D$52*'IN_TECH'!$I$41) | E63: =('ENG_OPS'!$E$47*'IN_TECH'!$D$41)+('ENG_OPS'!$E$48*'IN_TECH'!$E$41)+('ENG_OPS'!$E$49*'IN_TECH'!$F$41)+('ENG_OPS'!$E$50*'IN_TECH'!$G$41)+('ENG_OPS'!$E$51*'IN_TECH'!$H$41)+('ENG_OPS'!$E$52*'IN_TECH'!$I$41) | F63: =('ENG_OPS'!$F$47*'IN_TECH'!$D$41)+('ENG_OPS'!$F$48*'IN_TECH'!$E$41)+('ENG_OPS'!$F$49*'IN_TECH'!$F$41)+('ENG_OPS'!$F$50*'IN_TECH'!$G$41)+('ENG_OPS'!$F$51*'IN_TECH'!$H$41)+('ENG_OPS'!$F$52*'IN_TECH'!$I$41) | G63: =('ENG_OPS'!$G$47*'IN_TECH'!$D$41)+('ENG_OPS'!$G$48*'IN_TECH'!$E$41)+('ENG_OPS'!$G$49*'IN_TECH'!$F$41)+('ENG_OPS'!$G$50*'IN_TECH'!$G$41)+('ENG_OPS'!$G$51*'IN_TECH'!$H$41)+('ENG_OPS'!$G$52*'IN_TECH'!$I$41) | H63: =('ENG_OPS'!$H$47*'IN_TECH'!$D$41)+('ENG_OPS'!$H$48*'IN_TECH'!$E$41)+('ENG_OPS'!$H$49*'IN_TECH'!$F$41)+('ENG_OPS'!$H$50*'IN_TECH'!$G$41)+('ENG_OPS'!$H$51*'IN_TECH'!$H$41)+('ENG_OPS'!$H$52*'IN_TECH'!$I$41) | I63: =('ENG_OPS'!$I$47*'IN_TECH'!$D$41)+('ENG_OPS'!$I$48*'IN_TECH'!$E$41)+('ENG_OPS'!$I$49*'IN_TECH'!$F$41)+('ENG_OPS'!$I$50*'IN_TECH'!$G$41)+('ENG_OPS'!$I$51*'IN_TECH'!$H$41)+('ENG_OPS'!$I$52*'IN_TECH'!$I$41) | J63: =('ENG_OPS'!$J$47*'IN_TECH'!$D$41)+('ENG_OPS'!$J$48*'IN_TECH'!$E$41)+('ENG_OPS'!$J$49*'IN_TECH'!$F$41)+('ENG_OPS'!$J$50*'IN_TECH'!$G$41)+('ENG_OPS'!$J$51*'IN_TECH'!$H$41)+('ENG_OPS'!$J$52*'IN_TECH'!$I$41) | K63: =('ENG_OPS'!$K$47*'IN_TECH'!$D$41)+('ENG_OPS'!$K$48*'IN_TECH'!$E$41)+('ENG_OPS'!$K$49*'IN_TECH'!$F$41)+('ENG_OPS'!$K$50*'IN_TECH'!$G$41)+('ENG_OPS'!$K$51*'IN_TECH'!$H$41)+('ENG_OPS'!$K$52*'IN_TECH'!$I$41) | L63: =('ENG_OPS'!$L$47*'IN_TECH'!$D$41)+('ENG_OPS'!$L$48*'IN_TECH'!$E$41)+('ENG_OPS'!$L$49*'IN_TECH'!$F$41)+('ENG_OPS'!$L$50*'IN_TECH'!$G$41)+('ENG_OPS'!$L$51*'IN_TECH'!$H$41)+('ENG_OPS'!$L$52*'IN_TECH'!$I$41) | M63: =('ENG_OPS'!$M$47*'IN_TECH'!$D$41)+('ENG_OPS'!$M$48*'IN_TECH'!$E$41)+('ENG_OPS'!$M$49*'IN_TECH'!$F$41)+('ENG_OPS'!$M$50*'IN_TECH'!$G$41)+('ENG_OPS'!$M$51*'IN_TECH'!$H$41)+('ENG_OPS'!$M$52*'IN_TECH'!$I$41) | N63: =('ENG_OPS'!$N$47*'IN_TECH'!$D$41)+('ENG_OPS'!$N$48*'IN_TECH'!$E$41)+('ENG_OPS'!$N$49*'IN_TECH'!$F$41)+('ENG_OPS'!$N$50*'IN_TECH'!$G$41)+('ENG_OPS'!$N$51*'IN_TECH'!$H$41)+('ENG_OPS'!$N$52*'IN_TECH'!$I$41) | O63: =('ENG_OPS'!$O$47*'IN_TECH'!$D$41)+('ENG_OPS'!$O$48*'IN_TECH'!$E$41)+('ENG_OPS'!$O$49*'IN_TECH'!$F$41)+('ENG_OPS'!$O$50*'IN_TECH'!$G$41)+('ENG_OPS'!$O$51*'IN_TECH'!$H$41)+('ENG_OPS'!$O$52*'IN_TECH'!$I$41) | P63: =('ENG_OPS'!$P$47*'IN_TECH'!$D$41)+('ENG_OPS'!$P$48*'IN_TECH'!$E$41)+('ENG_OPS'!$P$49*'IN_TECH'!$F$41)+('ENG_OPS'!$P$50*'IN_TECH'!$G$41)+('ENG_OPS'!$P$51*'IN_TECH'!$H$41)+('ENG_OPS'!$P$52*'IN_TECH'!$I$41)
A64: آب مصرفی کل | B64: OPS.water | C64: m3 | D64: =('ENG_OPS'!$D$47*'IN_TECH'!$D$42)+('ENG_OPS'!$D$48*'IN_TECH'!$E$42)+('ENG_OPS'!$D$49*'IN_TECH'!$F$42)+('ENG_OPS'!$D$50*'IN_TECH'!$G$42)+('ENG_OPS'!$D$51*'IN_TECH'!$H$42)+('ENG_OPS'!$D$52*'IN_TECH'!$I$42) | E64: =('ENG_OPS'!$E$47*'IN_TECH'!$D$42)+('ENG_OPS'!$E$48*'IN_TECH'!$E$42)+('ENG_OPS'!$E$49*'IN_TECH'!$F$42)+('ENG_OPS'!$E$50*'IN_TECH'!$G$42)+('ENG_OPS'!$E$51*'IN_TECH'!$H$42)+('ENG_OPS'!$E$52*'IN_TECH'!$I$42) | F64: =('ENG_OPS'!$F$47*'IN_TECH'!$D$42)+('ENG_OPS'!$F$48*'IN_TECH'!$E$42)+('ENG_OPS'!$F$49*'IN_TECH'!$F$42)+('ENG_OPS'!$F$50*'IN_TECH'!$G$42)+('ENG_OPS'!$F$51*'IN_TECH'!$H$42)+('ENG_OPS'!$F$52*'IN_TECH'!$I$42) | G64: =('ENG_OPS'!$G$47*'IN_TECH'!$D$42)+('ENG_OPS'!$G$48*'IN_TECH'!$E$42)+('ENG_OPS'!$G$49*'IN_TECH'!$F$42)+('ENG_OPS'!$G$50*'IN_TECH'!$G$42)+('ENG_OPS'!$G$51*'IN_TECH'!$H$42)+('ENG_OPS'!$G$52*'IN_TECH'!$I$42) | H64: =('ENG_OPS'!$H$47*'IN_TECH'!$D$42)+('ENG_OPS'!$H$48*'IN_TECH'!$E$42)+('ENG_OPS'!$H$49*'IN_TECH'!$F$42)+('ENG_OPS'!$H$50*'IN_TECH'!$G$42)+('ENG_OPS'!$H$51*'IN_TECH'!$H$42)+('ENG_OPS'!$H$52*'IN_TECH'!$I$42) | I64: =('ENG_OPS'!$I$47*'IN_TECH'!$D$42)+('ENG_OPS'!$I$48*'IN_TECH'!$E$42)+('ENG_OPS'!$I$49*'IN_TECH'!$F$42)+('ENG_OPS'!$I$50*'IN_TECH'!$G$42)+('ENG_OPS'!$I$51*'IN_TECH'!$H$42)+('ENG_OPS'!$I$52*'IN_TECH'!$I$42) | J64: =('ENG_OPS'!$J$47*'IN_TECH'!$D$42)+('ENG_OPS'!$J$48*'IN_TECH'!$E$42)+('ENG_OPS'!$J$49*'IN_TECH'!$F$42)+('ENG_OPS'!$J$50*'IN_TECH'!$G$42)+('ENG_OPS'!$J$51*'IN_TECH'!$H$42)+('ENG_OPS'!$J$52*'IN_TECH'!$I$42) | K64: =('ENG_OPS'!$K$47*'IN_TECH'!$D$42)+('ENG_OPS'!$K$48*'IN_TECH'!$E$42)+('ENG_OPS'!$K$49*'IN_TECH'!$F$42)+('ENG_OPS'!$K$50*'IN_TECH'!$G$42)+('ENG_OPS'!$K$51*'IN_TECH'!$H$42)+('ENG_OPS'!$K$52*'IN_TECH'!$I$42) | L64: =('ENG_OPS'!$L$47*'IN_TECH'!$D$42)+('ENG_OPS'!$L$48*'IN_TECH'!$E$42)+('ENG_OPS'!$L$49*'IN_TECH'!$F$42)+('ENG_OPS'!$L$50*'IN_TECH'!$G$42)+('ENG_OPS'!$L$51*'IN_TECH'!$H$42)+('ENG_OPS'!$L$52*'IN_TECH'!$I$42) | M64: =('ENG_OPS'!$M$47*'IN_TECH'!$D$42)+('ENG_OPS'!$M$48*'IN_TECH'!$E$42)+('ENG_OPS'!$M$49*'IN_TECH'!$F$42)+('ENG_OPS'!$M$50*'IN_TECH'!$G$42)+('ENG_OPS'!$M$51*'IN_TECH'!$H$42)+('ENG_OPS'!$M$52*'IN_TECH'!$I$42) | N64: =('ENG_OPS'!$N$47*'IN_TECH'!$D$42)+('ENG_OPS'!$N$48*'IN_TECH'!$E$42)+('ENG_OPS'!$N$49*'IN_TECH'!$F$42)+('ENG_OPS'!$N$50*'IN_TECH'!$G$42)+('ENG_OPS'!$N$51*'IN_TECH'!$H$42)+('ENG_OPS'!$N$52*'IN_TECH'!$I$42) | O64: =('ENG_OPS'!$O$47*'IN_TECH'!$D$42)+('ENG_OPS'!$O$48*'IN_TECH'!$E$42)+('ENG_OPS'!$O$49*'IN_TECH'!$F$42)+('ENG_OPS'!$O$50*'IN_TECH'!$G$42)+('ENG_OPS'!$O$51*'IN_TECH'!$H$42)+('ENG_OPS'!$O$52*'IN_TECH'!$I$42) | P64: =('ENG_OPS'!$P$47*'IN_TECH'!$D$42)+('ENG_OPS'!$P$48*'IN_TECH'!$E$42)+('ENG_OPS'!$P$49*'IN_TECH'!$F$42)+('ENG_OPS'!$P$50*'IN_TECH'!$G$42)+('ENG_OPS'!$P$51*'IN_TECH'!$H$42)+('ENG_OPS'!$P$52*'IN_TECH'!$I$42)
A66: و) قیمت‌گذاری و درآمد
A67: قیمت فروش محصول 1 | B67: OPS.price | C67: میلیون ریال/تن | D67: =IF('IN_SALES'!$D$11=1,'ENG_SCEN'!$D$28*'ENG_SCEN'!$D$29/1000000*'IN_SALES'!$D$12,'IN_SALES'!$D$10*POWER(1+'IN_SALES'!$D$13,'IN_MACRO'!$D$23)*(1+'IN_SALES'!$D$14*('ENG_SCEN'!$D$29/'ENG_SCEN'!$D$29-1)))*'ENG_SCEN'!$G$12 | E67: =IF('IN_SALES'!$D$11=1,'ENG_SCEN'!$E$28*'ENG_SCEN'!$E$29/1000000*'IN_SALES'!$D$12,'IN_SALES'!$D$10*POWER(1+'IN_SALES'!$D$13,'IN_MACRO'!$E$23)*(1+'IN_SALES'!$D$14*('ENG_SCEN'!$E$29/'ENG_SCEN'!$D$29-1)))*'ENG_SCEN'!$G$12 | F67: =IF('IN_SALES'!$D$11=1,'ENG_SCEN'!$F$28*'ENG_SCEN'!$F$29/1000000*'IN_SALES'!$D$12,'IN_SALES'!$D$10*POWER(1+'IN_SALES'!$D$13,'IN_MACRO'!$F$23)*(1+'IN_SALES'!$D$14*('ENG_SCEN'!$F$29/'ENG_SCEN'!$D$29-1)))*'ENG_SCEN'!$G$12 | G67: =IF('IN_SALES'!$D$11=1,'ENG_SCEN'!$G$28*'ENG_SCEN'!$G$29/1000000*'IN_SALES'!$D$12,'IN_SALES'!$D$10*POWER(1+'IN_SALES'!$D$13,'IN_MACRO'!$G$23)*(1+'IN_SALES'!$D$14*('ENG_SCEN'!$G$29/'ENG_SCEN'!$D$29-1)))*'ENG_SCEN'!$G$12 | H67: =IF('IN_SALES'!$D$11=1,'ENG_SCEN'!$H$28*'ENG_SCEN'!$H$29/1000000*'IN_SALES'!$D$12,'IN_SALES'!$D$10*POWER(1+'IN_SALES'!$D$13,'IN_MACRO'!$H$23)*(1+'IN_SALES'!$D$14*('ENG_SCEN'!$H$29/'ENG_SCEN'!$D$29-1)))*'ENG_SCEN'!$G$12 | I67: =IF('IN_SALES'!$D$11=1,'ENG_SCEN'!$I$28*'ENG_SCEN'!$I$29/1000000*'IN_SALES'!$D$12,'IN_SALES'!$D$10*POWER(1+'IN_SALES'!$D$13,'IN_MACRO'!$I$23)*(1+'IN_SALES'!$D$14*('ENG_SCEN'!$I$29/'ENG_SCEN'!$D$29-1)))*'ENG_SCEN'!$G$12 | J67: =IF('IN_SALES'!$D$11=1,'ENG_SCEN'!$J$28*'ENG_SCEN'!$J$29/1000000*'IN_SALES'!$D$12,'IN_SALES'!$D$10*POWER(1+'IN_SALES'!$D$13,'IN_MACRO'!$J$23)*(1+'IN_SALES'!$D$14*('ENG_SCEN'!$J$29/'ENG_SCEN'!$D$29-1)))*'ENG_SCEN'!$G$12 | K67: =IF('IN_SALES'!$D$11=1,'ENG_SCEN'!$K$28*'ENG_SCEN'!$K$29/1000000*'IN_SALES'!$D$12,'IN_SALES'!$D$10*POWER(1+'IN_SALES'!$D$13,'IN_MACRO'!$K$23)*(1+'IN_SALES'!$D$14*('ENG_SCEN'!$K$29/'ENG_SCEN'!$D$29-1)))*'ENG_SCEN'!$G$12 | L67: =IF('IN_SALES'!$D$11=1,'ENG_SCEN'!$L$28*'ENG_SCEN'!$L$29/1000000*'IN_SALES'!$D$12,'IN_SALES'!$D$10*POWER(1+'IN_SALES'!$D$13,'IN_MACRO'!$L$23)*(1+'IN_SALES'!$D$14*('ENG_SCEN'!$L$29/'ENG_SCEN'!$D$29-1)))*'ENG_SCEN'!$G$12 | M67: =IF('IN_SALES'!$D$11=1,'ENG_SCEN'!$M$28*'ENG_SCEN'!$M$29/1000000*'IN_SALES'!$D$12,'IN_SALES'!$D$10*POWER(1+'IN_SALES'!$D$13,'IN_MACRO'!$M$23)*(1+'IN_SALES'!$D$14*('ENG_SCEN'!$M$29/'ENG_SCEN'!$D$29-1)))*'ENG_SCEN'!$G$12 | N67: =IF('IN_SALES'!$D$11=1,'ENG_SCEN'!$N$28*'ENG_SCEN'!$N$29/1000000*'IN_SALES'!$D$12,'IN_SALES'!$D$10*POWER(1+'IN_SALES'!$D$13,'IN_MACRO'!$N$23)*(1+'IN_SALES'!$D$14*('ENG_SCEN'!$N$29/'ENG_SCEN'!$D$29-1)))*'ENG_SCEN'!$G$12 | O67: =IF('IN_SALES'!$D$11=1,'ENG_SCEN'!$O$28*'ENG_SCEN'!$O$29/1000000*'IN_SALES'!$D$12,'IN_SALES'!$D$10*POWER(1+'IN_SALES'!$D$13,'IN_MACRO'!$O$23)*(1+'IN_SALES'!$D$14*('ENG_SCEN'!$O$29/'ENG_SCEN'!$D$29-1)))*'ENG_SCEN'!$G$12 | P67: =IF('IN_SALES'!$D$11=1,'ENG_SCEN'!$P$28*'ENG_SCEN'!$P$29/1000000*'IN_SALES'!$D$12,'IN_SALES'!$D$10*POWER(1+'IN_SALES'!$D$13,'IN_MACRO'!$P$23)*(1+'IN_SALES'!$D$14*('ENG_SCEN'!$P$29/'ENG_SCEN'!$D$29-1)))*'ENG_SCEN'!$G$12
A68: قیمت فروش محصول 2 | C68: میلیون ریال/تن | D68: =IF('IN_SALES'!$E$11=1,'ENG_SCEN'!$D$28*'ENG_SCEN'!$D$29/1000000*'IN_SALES'!$E$12,'IN_SALES'!$E$10*POWER(1+'IN_SALES'!$E$13,'IN_MACRO'!$D$23)*(1+'IN_SALES'!$E$14*('ENG_SCEN'!$D$29/'ENG_SCEN'!$D$29-1)))*'ENG_SCEN'!$G$12 | E68: =IF('IN_SALES'!$E$11=1,'ENG_SCEN'!$E$28*'ENG_SCEN'!$E$29/1000000*'IN_SALES'!$E$12,'IN_SALES'!$E$10*POWER(1+'IN_SALES'!$E$13,'IN_MACRO'!$E$23)*(1+'IN_SALES'!$E$14*('ENG_SCEN'!$E$29/'ENG_SCEN'!$D$29-1)))*'ENG_SCEN'!$G$12 | F68: =IF('IN_SALES'!$E$11=1,'ENG_SCEN'!$F$28*'ENG_SCEN'!$F$29/1000000*'IN_SALES'!$E$12,'IN_SALES'!$E$10*POWER(1+'IN_SALES'!$E$13,'IN_MACRO'!$F$23)*(1+'IN_SALES'!$E$14*('ENG_SCEN'!$F$29/'ENG_SCEN'!$D$29-1)))*'ENG_SCEN'!$G$12 | G68: =IF('IN_SALES'!$E$11=1,'ENG_SCEN'!$G$28*'ENG_SCEN'!$G$29/1000000*'IN_SALES'!$E$12,'IN_SALES'!$E$10*POWER(1+'IN_SALES'!$E$13,'IN_MACRO'!$G$23)*(1+'IN_SALES'!$E$14*('ENG_SCEN'!$G$29/'ENG_SCEN'!$D$29-1)))*'ENG_SCEN'!$G$12 | H68: =IF('IN_SALES'!$E$11=1,'ENG_SCEN'!$H$28*'ENG_SCEN'!$H$29/1000000*'IN_SALES'!$E$12,'IN_SALES'!$E$10*POWER(1+'IN_SALES'!$E$13,'IN_MACRO'!$H$23)*(1+'IN_SALES'!$E$14*('ENG_SCEN'!$H$29/'ENG_SCEN'!$D$29-1)))*'ENG_SCEN'!$G$12 | I68: =IF('IN_SALES'!$E$11=1,'ENG_SCEN'!$I$28*'ENG_SCEN'!$I$29/1000000*'IN_SALES'!$E$12,'IN_SALES'!$E$10*POWER(1+'IN_SALES'!$E$13,'IN_MACRO'!$I$23)*(1+'IN_SALES'!$E$14*('ENG_SCEN'!$I$29/'ENG_SCEN'!$D$29-1)))*'ENG_SCEN'!$G$12 | J68: =IF('IN_SALES'!$E$11=1,'ENG_SCEN'!$J$28*'ENG_SCEN'!$J$29/1000000*'IN_SALES'!$E$12,'IN_SALES'!$E$10*POWER(1+'IN_SALES'!$E$13,'IN_MACRO'!$J$23)*(1+'IN_SALES'!$E$14*('ENG_SCEN'!$J$29/'ENG_SCEN'!$D$29-1)))*'ENG_SCEN'!$G$12 | K68: =IF('IN_SALES'!$E$11=1,'ENG_SCEN'!$K$28*'ENG_SCEN'!$K$29/1000000*'IN_SALES'!$E$12,'IN_SALES'!$E$10*POWER(1+'IN_SALES'!$E$13,'IN_MACRO'!$K$23)*(1+'IN_SALES'!$E$14*('ENG_SCEN'!$K$29/'ENG_SCEN'!$D$29-1)))*'ENG_SCEN'!$G$12 | L68: =IF('IN_SALES'!$E$11=1,'ENG_SCEN'!$L$28*'ENG_SCEN'!$L$29/1000000*'IN_SALES'!$E$12,'IN_SALES'!$E$10*POWER(1+'IN_SALES'!$E$13,'IN_MACRO'!$L$23)*(1+'IN_SALES'!$E$14*('ENG_SCEN'!$L$29/'ENG_SCEN'!$D$29-1)))*'ENG_SCEN'!$G$12 | M68: =IF('IN_SALES'!$E$11=1,'ENG_SCEN'!$M$28*'ENG_SCEN'!$M$29/1000000*'IN_SALES'!$E$12,'IN_SALES'!$E$10*POWER(1+'IN_SALES'!$E$13,'IN_MACRO'!$M$23)*(1+'IN_SALES'!$E$14*('ENG_SCEN'!$M$29/'ENG_SCEN'!$D$29-1)))*'ENG_SCEN'!$G$12 | N68: =IF('IN_SALES'!$E$11=1,'ENG_SCEN'!$N$28*'ENG_SCEN'!$N$29/1000000*'IN_SALES'!$E$12,'IN_SALES'!$E$10*POWER(1+'IN_SALES'!$E$13,'IN_MACRO'!$N$23)*(1+'IN_SALES'!$E$14*('ENG_SCEN'!$N$29/'ENG_SCEN'!$D$29-1)))*'ENG_SCEN'!$G$12 | O68: =IF('IN_SALES'!$E$11=1,'ENG_SCEN'!$O$28*'ENG_SCEN'!$O$29/1000000*'IN_SALES'!$E$12,'IN_SALES'!$E$10*POWER(1+'IN_SALES'!$E$13,'IN_MACRO'!$O$23)*(1+'IN_SALES'!$E$14*('ENG_SCEN'!$O$29/'ENG_SCEN'!$D$29-1)))*'ENG_SCEN'!$G$12 | P68: =IF('IN_SALES'!$E$11=1,'ENG_SCEN'!$P$28*'ENG_SCEN'!$P$29/1000000*'IN_SALES'!$E$12,'IN_SALES'!$E$10*POWER(1+'IN_SALES'!$E$13,'IN_MACRO'!$P$23)*(1+'IN_SALES'!$E$14*('ENG_SCEN'!$P$29/'ENG_SCEN'!$D$29-1)))*'ENG_SCEN'!$G$12
A69: قیمت فروش محصول 3 | C69: میلیون ریال/تن | D69: =IF('IN_SALES'!$F$11=1,'ENG_SCEN'!$D$28*'ENG_SCEN'!$D$29/1000000*'IN_SALES'!$F$12,'IN_SALES'!$F$10*POWER(1+'IN_SALES'!$F$13,'IN_MACRO'!$D$23)*(1+'IN_SALES'!$F$14*('ENG_SCEN'!$D$29/'ENG_SCEN'!$D$29-1)))*'ENG_SCEN'!$G$12 | E69: =IF('IN_SALES'!$F$11=1,'ENG_SCEN'!$E$28*'ENG_SCEN'!$E$29/1000000*'IN_SALES'!$F$12,'IN_SALES'!$F$10*POWER(1+'IN_SALES'!$F$13,'IN_MACRO'!$E$23)*(1+'IN_SALES'!$F$14*('ENG_SCEN'!$E$29/'ENG_SCEN'!$D$29-1)))*'ENG_SCEN'!$G$12 | F69: =IF('IN_SALES'!$F$11=1,'ENG_SCEN'!$F$28*'ENG_SCEN'!$F$29/1000000*'IN_SALES'!$F$12,'IN_SALES'!$F$10*POWER(1+'IN_SALES'!$F$13,'IN_MACRO'!$F$23)*(1+'IN_SALES'!$F$14*('ENG_SCEN'!$F$29/'ENG_SCEN'!$D$29-1)))*'ENG_SCEN'!$G$12 | G69: =IF('IN_SALES'!$F$11=1,'ENG_SCEN'!$G$28*'ENG_SCEN'!$G$29/1000000*'IN_SALES'!$F$12,'IN_SALES'!$F$10*POWER(1+'IN_SALES'!$F$13,'IN_MACRO'!$G$23)*(1+'IN_SALES'!$F$14*('ENG_SCEN'!$G$29/'ENG_SCEN'!$D$29-1)))*'ENG_SCEN'!$G$12 | H69: =IF('IN_SALES'!$F$11=1,'ENG_SCEN'!$H$28*'ENG_SCEN'!$H$29/1000000*'IN_SALES'!$F$12,'IN_SALES'!$F$10*POWER(1+'IN_SALES'!$F$13,'IN_MACRO'!$H$23)*(1+'IN_SALES'!$F$14*('ENG_SCEN'!$H$29/'ENG_SCEN'!$D$29-1)))*'ENG_SCEN'!$G$12 | I69: =IF('IN_SALES'!$F$11=1,'ENG_SCEN'!$I$28*'ENG_SCEN'!$I$29/1000000*'IN_SALES'!$F$12,'IN_SALES'!$F$10*POWER(1+'IN_SALES'!$F$13,'IN_MACRO'!$I$23)*(1+'IN_SALES'!$F$14*('ENG_SCEN'!$I$29/'ENG_SCEN'!$D$29-1)))*'ENG_SCEN'!$G$12 | J69: =IF('IN_SALES'!$F$11=1,'ENG_SCEN'!$J$28*'ENG_SCEN'!$J$29/1000000*'IN_SALES'!$F$12,'IN_SALES'!$F$10*POWER(1+'IN_SALES'!$F$13,'IN_MACRO'!$J$23)*(1+'IN_SALES'!$F$14*('ENG_SCEN'!$J$29/'ENG_SCEN'!$D$29-1)))*'ENG_SCEN'!$G$12 | K69: =IF('IN_SALES'!$F$11=1,'ENG_SCEN'!$K$28*'ENG_SCEN'!$K$29/1000000*'IN_SALES'!$F$12,'IN_SALES'!$F$10*POWER(1+'IN_SALES'!$F$13,'IN_MACRO'!$K$23)*(1+'IN_SALES'!$F$14*('ENG_SCEN'!$K$29/'ENG_SCEN'!$D$29-1)))*'ENG_SCEN'!$G$12 | L69: =IF('IN_SALES'!$F$11=1,'ENG_SCEN'!$L$28*'ENG_SCEN'!$L$29/1000000*'IN_SALES'!$F$12,'IN_SALES'!$F$10*POWER(1+'IN_SALES'!$F$13,'IN_MACRO'!$L$23)*(1+'IN_SALES'!$F$14*('ENG_SCEN'!$L$29/'ENG_SCEN'!$D$29-1)))*'ENG_SCEN'!$G$12 | M69: =IF('IN_SALES'!$F$11=1,'ENG_SCEN'!$M$28*'ENG_SCEN'!$M$29/1000000*'IN_SALES'!$F$12,'IN_SALES'!$F$10*POWER(1+'IN_SALES'!$F$13,'IN_MACRO'!$M$23)*(1+'IN_SALES'!$F$14*('ENG_SCEN'!$M$29/'ENG_SCEN'!$D$29-1)))*'ENG_SCEN'!$G$12 | N69: =IF('IN_SALES'!$F$11=1,'ENG_SCEN'!$N$28*'ENG_SCEN'!$N$29/1000000*'IN_SALES'!$F$12,'IN_SALES'!$F$10*POWER(1+'IN_SALES'!$F$13,'IN_MACRO'!$N$23)*(1+'IN_SALES'!$F$14*('ENG_SCEN'!$N$29/'ENG_SCEN'!$D$29-1)))*'ENG_SCEN'!$G$12 | O69: =IF('IN_SALES'!$F$11=1,'ENG_SCEN'!$O$28*'ENG_SCEN'!$O$29/1000000*'IN_SALES'!$F$12,'IN_SALES'!$F$10*POWER(1+'IN_SALES'!$F$13,'IN_MACRO'!$O$23)*(1+'IN_SALES'!$F$14*('ENG_SCEN'!$O$29/'ENG_SCEN'!$D$29-1)))*'ENG_SCEN'!$G$12 | P69: =IF('IN_SALES'!$F$11=1,'ENG_SCEN'!$P$28*'ENG_SCEN'!$P$29/1000000*'IN_SALES'!$F$12,'IN_SALES'!$F$10*POWER(1+'IN_SALES'!$F$13,'IN_MACRO'!$P$23)*(1+'IN_SALES'!$F$14*('ENG_SCEN'!$P$29/'ENG_SCEN'!$D$29-1)))*'ENG_SCEN'!$G$12
A70: قیمت فروش محصول 4 | C70: میلیون ریال/تن | D70: =IF('IN_SALES'!$G$11=1,'ENG_SCEN'!$D$28*'ENG_SCEN'!$D$29/1000000*'IN_SALES'!$G$12,'IN_SALES'!$G$10*POWER(1+'IN_SALES'!$G$13,'IN_MACRO'!$D$23)*(1+'IN_SALES'!$G$14*('ENG_SCEN'!$D$29/'ENG_SCEN'!$D$29-1)))*'ENG_SCEN'!$G$12 | E70: =IF('IN_SALES'!$G$11=1,'ENG_SCEN'!$E$28*'ENG_SCEN'!$E$29/1000000*'IN_SALES'!$G$12,'IN_SALES'!$G$10*POWER(1+'IN_SALES'!$G$13,'IN_MACRO'!$E$23)*(1+'IN_SALES'!$G$14*('ENG_SCEN'!$E$29/'ENG_SCEN'!$D$29-1)))*'ENG_SCEN'!$G$12 | F70: =IF('IN_SALES'!$G$11=1,'ENG_SCEN'!$F$28*'ENG_SCEN'!$F$29/1000000*'IN_SALES'!$G$12,'IN_SALES'!$G$10*POWER(1+'IN_SALES'!$G$13,'IN_MACRO'!$F$23)*(1+'IN_SALES'!$G$14*('ENG_SCEN'!$F$29/'ENG_SCEN'!$D$29-1)))*'ENG_SCEN'!$G$12 | G70: =IF('IN_SALES'!$G$11=1,'ENG_SCEN'!$G$28*'ENG_SCEN'!$G$29/1000000*'IN_SALES'!$G$12,'IN_SALES'!$G$10*POWER(1+'IN_SALES'!$G$13,'IN_MACRO'!$G$23)*(1+'IN_SALES'!$G$14*('ENG_SCEN'!$G$29/'ENG_SCEN'!$D$29-1)))*'ENG_SCEN'!$G$12 | H70: =IF('IN_SALES'!$G$11=1,'ENG_SCEN'!$H$28*'ENG_SCEN'!$H$29/1000000*'IN_SALES'!$G$12,'IN_SALES'!$G$10*POWER(1+'IN_SALES'!$G$13,'IN_MACRO'!$H$23)*(1+'IN_SALES'!$G$14*('ENG_SCEN'!$H$29/'ENG_SCEN'!$D$29-1)))*'ENG_SCEN'!$G$12 | I70: =IF('IN_SALES'!$G$11=1,'ENG_SCEN'!$I$28*'ENG_SCEN'!$I$29/1000000*'IN_SALES'!$G$12,'IN_SALES'!$G$10*POWER(1+'IN_SALES'!$G$13,'IN_MACRO'!$I$23)*(1+'IN_SALES'!$G$14*('ENG_SCEN'!$I$29/'ENG_SCEN'!$D$29-1)))*'ENG_SCEN'!$G$12 | J70: =IF('IN_SALES'!$G$11=1,'ENG_SCEN'!$J$28*'ENG_SCEN'!$J$29/1000000*'IN_SALES'!$G$12,'IN_SALES'!$G$10*POWER(1+'IN_SALES'!$G$13,'IN_MACRO'!$J$23)*(1+'IN_SALES'!$G$14*('ENG_SCEN'!$J$29/'ENG_SCEN'!$D$29-1)))*'ENG_SCEN'!$G$12 | K70: =IF('IN_SALES'!$G$11=1,'ENG_SCEN'!$K$28*'ENG_SCEN'!$K$29/1000000*'IN_SALES'!$G$12,'IN_SALES'!$G$10*POWER(1+'IN_SALES'!$G$13,'IN_MACRO'!$K$23)*(1+'IN_SALES'!$G$14*('ENG_SCEN'!$K$29/'ENG_SCEN'!$D$29-1)))*'ENG_SCEN'!$G$12 | L70: =IF('IN_SALES'!$G$11=1,'ENG_SCEN'!$L$28*'ENG_SCEN'!$L$29/1000000*'IN_SALES'!$G$12,'IN_SALES'!$G$10*POWER(1+'IN_SALES'!$G$13,'IN_MACRO'!$L$23)*(1+'IN_SALES'!$G$14*('ENG_SCEN'!$L$29/'ENG_SCEN'!$D$29-1)))*'ENG_SCEN'!$G$12 | M70: =IF('IN_SALES'!$G$11=1,'ENG_SCEN'!$M$28*'ENG_SCEN'!$M$29/1000000*'IN_SALES'!$G$12,'IN_SALES'!$G$10*POWER(1+'IN_SALES'!$G$13,'IN_MACRO'!$M$23)*(1+'IN_SALES'!$G$14*('ENG_SCEN'!$M$29/'ENG_SCEN'!$D$29-1)))*'ENG_SCEN'!$G$12 | N70: =IF('IN_SALES'!$G$11=1,'ENG_SCEN'!$N$28*'ENG_SCEN'!$N$29/1000000*'IN_SALES'!$G$12,'IN_SALES'!$G$10*POWER(1+'IN_SALES'!$G$13,'IN_MACRO'!$N$23)*(1+'IN_SALES'!$G$14*('ENG_SCEN'!$N$29/'ENG_SCEN'!$D$29-1)))*'ENG_SCEN'!$G$12 | O70: =IF('IN_SALES'!$G$11=1,'ENG_SCEN'!$O$28*'ENG_SCEN'!$O$29/1000000*'IN_SALES'!$G$12,'IN_SALES'!$G$10*POWER(1+'IN_SALES'!$G$13,'IN_MACRO'!$O$23)*(1+'IN_SALES'!$G$14*('ENG_SCEN'!$O$29/'ENG_SCEN'!$D$29-1)))*'ENG_SCEN'!$G$12 | P70: =IF('IN_SALES'!$G$11=1,'ENG_SCEN'!$P$28*'ENG_SCEN'!$P$29/1000000*'IN_SALES'!$G$12,'IN_SALES'!$G$10*POWER(1+'IN_SALES'!$G$13,'IN_MACRO'!$P$23)*(1+'IN_SALES'!$G$14*('ENG_SCEN'!$P$29/'ENG_SCEN'!$D$29-1)))*'ENG_SCEN'!$G$12
A71: مقدار فروش محصول 1 | B71: OPS.vol | C71: تن | D71: ='ENG_OPS'!$D$39*'IN_SALES'!$D$16 | E71: ='ENG_OPS'!$E$39*'IN_SALES'!$D$16 | F71: ='ENG_OPS'!$F$39*'IN_SALES'!$D$16 | G71: ='ENG_OPS'!$G$39*'IN_SALES'!$D$16 | H71: ='ENG_OPS'!$H$39*'IN_SALES'!$D$16 | I71: ='ENG_OPS'!$I$39*'IN_SALES'!$D$16 | J71: ='ENG_OPS'!$J$39*'IN_SALES'!$D$16 | K71: ='ENG_OPS'!$K$39*'IN_SALES'!$D$16 | L71: ='ENG_OPS'!$L$39*'IN_SALES'!$D$16 | M71: ='ENG_OPS'!$M$39*'IN_SALES'!$D$16 | N71: ='ENG_OPS'!$N$39*'IN_SALES'!$D$16 | O71: ='ENG_OPS'!$O$39*'IN_SALES'!$D$16 | P71: ='ENG_OPS'!$P$39*'IN_SALES'!$D$16
A72: مقدار فروش محصول 2 | C72: تن | D72: ='ENG_OPS'!$D$40*'IN_SALES'!$E$16 | E72: ='ENG_OPS'!$E$40*'IN_SALES'!$E$16 | F72: ='ENG_OPS'!$F$40*'IN_SALES'!$E$16 | G72: ='ENG_OPS'!$G$40*'IN_SALES'!$E$16 | H72: ='ENG_OPS'!$H$40*'IN_SALES'!$E$16 | I72: ='ENG_OPS'!$I$40*'IN_SALES'!$E$16 | J72: ='ENG_OPS'!$J$40*'IN_SALES'!$E$16 | K72: ='ENG_OPS'!$K$40*'IN_SALES'!$E$16 | L72: ='ENG_OPS'!$L$40*'IN_SALES'!$E$16 | M72: ='ENG_OPS'!$M$40*'IN_SALES'!$E$16 | N72: ='ENG_OPS'!$N$40*'IN_SALES'!$E$16 | O72: ='ENG_OPS'!$O$40*'IN_SALES'!$E$16 | P72: ='ENG_OPS'!$P$40*'IN_SALES'!$E$16
A73: مقدار فروش محصول 3 | C73: تن | D73: ='ENG_OPS'!$D$41*'IN_SALES'!$F$16 | E73: ='ENG_OPS'!$E$41*'IN_SALES'!$F$16 | F73: ='ENG_OPS'!$F$41*'IN_SALES'!$F$16 | G73: ='ENG_OPS'!$G$41*'IN_SALES'!$F$16 | H73: ='ENG_OPS'!$H$41*'IN_SALES'!$F$16 | I73: ='ENG_OPS'!$I$41*'IN_SALES'!$F$16 | J73: ='ENG_OPS'!$J$41*'IN_SALES'!$F$16 | K73: ='ENG_OPS'!$K$41*'IN_SALES'!$F$16 | L73: ='ENG_OPS'!$L$41*'IN_SALES'!$F$16 | M73: ='ENG_OPS'!$M$41*'IN_SALES'!$F$16 | N73: ='ENG_OPS'!$N$41*'IN_SALES'!$F$16 | O73: ='ENG_OPS'!$O$41*'IN_SALES'!$F$16 | P73: ='ENG_OPS'!$P$41*'IN_SALES'!$F$16
A74: مقدار فروش محصول 4 | C74: تن | D74: ='ENG_OPS'!$D$42*'IN_SALES'!$G$16 | E74: ='ENG_OPS'!$E$42*'IN_SALES'!$G$16 | F74: ='ENG_OPS'!$F$42*'IN_SALES'!$G$16 | G74: ='ENG_OPS'!$G$42*'IN_SALES'!$G$16 | H74: ='ENG_OPS'!$H$42*'IN_SALES'!$G$16 | I74: ='ENG_OPS'!$I$42*'IN_SALES'!$G$16 | J74: ='ENG_OPS'!$J$42*'IN_SALES'!$G$16 | K74: ='ENG_OPS'!$K$42*'IN_SALES'!$G$16 | L74: ='ENG_OPS'!$L$42*'IN_SALES'!$G$16 | M74: ='ENG_OPS'!$M$42*'IN_SALES'!$G$16 | N74: ='ENG_OPS'!$N$42*'IN_SALES'!$G$16 | O74: ='ENG_OPS'!$O$42*'IN_SALES'!$G$16 | P74: ='ENG_OPS'!$P$42*'IN_SALES'!$G$16
A75: درآمد ناخالص محصول 1 | B75: OPS.grev | C75: میلیون ریال | D75: ='ENG_OPS'!$D$71*'ENG_OPS'!$D$67 | E75: ='ENG_OPS'!$E$71*'ENG_OPS'!$E$67 | F75: ='ENG_OPS'!$F$71*'ENG_OPS'!$F$67 | G75: ='ENG_OPS'!$G$71*'ENG_OPS'!$G$67 | H75: ='ENG_OPS'!$H$71*'ENG_OPS'!$H$67 | I75: ='ENG_OPS'!$I$71*'ENG_OPS'!$I$67 | J75: ='ENG_OPS'!$J$71*'ENG_OPS'!$J$67 | K75: ='ENG_OPS'!$K$71*'ENG_OPS'!$K$67 | L75: ='ENG_OPS'!$L$71*'ENG_OPS'!$L$67 | M75: ='ENG_OPS'!$M$71*'ENG_OPS'!$M$67 | N75: ='ENG_OPS'!$N$71*'ENG_OPS'!$N$67 | O75: ='ENG_OPS'!$O$71*'ENG_OPS'!$O$67 | P75: ='ENG_OPS'!$P$71*'ENG_OPS'!$P$67
A76: درآمد ناخالص محصول 2 | C76: میلیون ریال | D76: ='ENG_OPS'!$D$72*'ENG_OPS'!$D$68 | E76: ='ENG_OPS'!$E$72*'ENG_OPS'!$E$68 | F76: ='ENG_OPS'!$F$72*'ENG_OPS'!$F$68 | G76: ='ENG_OPS'!$G$72*'ENG_OPS'!$G$68 | H76: ='ENG_OPS'!$H$72*'ENG_OPS'!$H$68 | I76: ='ENG_OPS'!$I$72*'ENG_OPS'!$I$68 | J76: ='ENG_OPS'!$J$72*'ENG_OPS'!$J$68 | K76: ='ENG_OPS'!$K$72*'ENG_OPS'!$K$68 | L76: ='ENG_OPS'!$L$72*'ENG_OPS'!$L$68 | M76: ='ENG_OPS'!$M$72*'ENG_OPS'!$M$68 | N76: ='ENG_OPS'!$N$72*'ENG_OPS'!$N$68 | O76: ='ENG_OPS'!$O$72*'ENG_OPS'!$O$68 | P76: ='ENG_OPS'!$P$72*'ENG_OPS'!$P$68
A77: درآمد ناخالص محصول 3 | C77: میلیون ریال | D77: ='ENG_OPS'!$D$73*'ENG_OPS'!$D$69 | E77: ='ENG_OPS'!$E$73*'ENG_OPS'!$E$69 | F77: ='ENG_OPS'!$F$73*'ENG_OPS'!$F$69 | G77: ='ENG_OPS'!$G$73*'ENG_OPS'!$G$69 | H77: ='ENG_OPS'!$H$73*'ENG_OPS'!$H$69 | I77: ='ENG_OPS'!$I$73*'ENG_OPS'!$I$69 | J77: ='ENG_OPS'!$J$73*'ENG_OPS'!$J$69 | K77: ='ENG_OPS'!$K$73*'ENG_OPS'!$K$69 | L77: ='ENG_OPS'!$L$73*'ENG_OPS'!$L$69 | M77: ='ENG_OPS'!$M$73*'ENG_OPS'!$M$69 | N77: ='ENG_OPS'!$N$73*'ENG_OPS'!$N$69 | O77: ='ENG_OPS'!$O$73*'ENG_OPS'!$O$69 | P77: ='ENG_OPS'!$P$73*'ENG_OPS'!$P$69
A78: درآمد ناخالص محصول 4 | C78: میلیون ریال | D78: ='ENG_OPS'!$D$74*'ENG_OPS'!$D$70 | E78: ='ENG_OPS'!$E$74*'ENG_OPS'!$E$70 | F78: ='ENG_OPS'!$F$74*'ENG_OPS'!$F$70 | G78: ='ENG_OPS'!$G$74*'ENG_OPS'!$G$70 | H78: ='ENG_OPS'!$H$74*'ENG_OPS'!$H$70 | I78: ='ENG_OPS'!$I$74*'ENG_OPS'!$I$70 | J78: ='ENG_OPS'!$J$74*'ENG_OPS'!$J$70 | K78: ='ENG_OPS'!$K$74*'ENG_OPS'!$K$70 | L78: ='ENG_OPS'!$L$74*'ENG_OPS'!$L$70 | M78: ='ENG_OPS'!$M$74*'ENG_OPS'!$M$70 | N78: ='ENG_OPS'!$N$74*'ENG_OPS'!$N$70 | O78: ='ENG_OPS'!$O$74*'ENG_OPS'!$O$70 | P78: ='ENG_OPS'!$P$74*'ENG_OPS'!$P$70
A79: جمع درآمد ناخالص | B79: OPS.grev_t | C79: میلیون ریال | D79: ='ENG_OPS'!$D$75+'ENG_OPS'!$D$76+'ENG_OPS'!$D$77+'ENG_OPS'!$D$78 | E79: ='ENG_OPS'!$E$75+'ENG_OPS'!$E$76+'ENG_OPS'!$E$77+'ENG_OPS'!$E$78 | F79: ='ENG_OPS'!$F$75+'ENG_OPS'!$F$76+'ENG_OPS'!$F$77+'ENG_OPS'!$F$78 | G79: ='ENG_OPS'!$G$75+'ENG_OPS'!$G$76+'ENG_OPS'!$G$77+'ENG_OPS'!$G$78 | H79: ='ENG_OPS'!$H$75+'ENG_OPS'!$H$76+'ENG_OPS'!$H$77+'ENG_OPS'!$H$78 | I79: ='ENG_OPS'!$I$75+'ENG_OPS'!$I$76+'ENG_OPS'!$I$77+'ENG_OPS'!$I$78 | J79: ='ENG_OPS'!$J$75+'ENG_OPS'!$J$76+'ENG_OPS'!$J$77+'ENG_OPS'!$J$78 | K79: ='ENG_OPS'!$K$75+'ENG_OPS'!$K$76+'ENG_OPS'!$K$77+'ENG_OPS'!$K$78 | L79: ='ENG_OPS'!$L$75+'ENG_OPS'!$L$76+'ENG_OPS'!$L$77+'ENG_OPS'!$L$78 | M79: ='ENG_OPS'!$M$75+'ENG_OPS'!$M$76+'ENG_OPS'!$M$77+'ENG_OPS'!$M$78 | N79: ='ENG_OPS'!$N$75+'ENG_OPS'!$N$76+'ENG_OPS'!$N$77+'ENG_OPS'!$N$78 | O79: ='ENG_OPS'!$O$75+'ENG_OPS'!$O$76+'ENG_OPS'!$O$77+'ENG_OPS'!$O$78 | P79: ='ENG_OPS'!$P$75+'ENG_OPS'!$P$76+'ENG_OPS'!$P$77+'ENG_OPS'!$P$78
A80: تخفیفات و برگشت از فروش | B80: OPS.disc | C80: میلیون ریال | D80: =('ENG_OPS'!$D$75*'IN_SALES'!$D$15)+('ENG_OPS'!$D$76*'IN_SALES'!$E$15)+('ENG_OPS'!$D$77*'IN_SALES'!$F$15)+('ENG_OPS'!$D$78*'IN_SALES'!$G$15) | E80: =('ENG_OPS'!$E$75*'IN_SALES'!$D$15)+('ENG_OPS'!$E$76*'IN_SALES'!$E$15)+('ENG_OPS'!$E$77*'IN_SALES'!$F$15)+('ENG_OPS'!$E$78*'IN_SALES'!$G$15) | F80: =('ENG_OPS'!$F$75*'IN_SALES'!$D$15)+('ENG_OPS'!$F$76*'IN_SALES'!$E$15)+('ENG_OPS'!$F$77*'IN_SALES'!$F$15)+('ENG_OPS'!$F$78*'IN_SALES'!$G$15) | G80: =('ENG_OPS'!$G$75*'IN_SALES'!$D$15)+('ENG_OPS'!$G$76*'IN_SALES'!$E$15)+('ENG_OPS'!$G$77*'IN_SALES'!$F$15)+('ENG_OPS'!$G$78*'IN_SALES'!$G$15) | H80: =('ENG_OPS'!$H$75*'IN_SALES'!$D$15)+('ENG_OPS'!$H$76*'IN_SALES'!$E$15)+('ENG_OPS'!$H$77*'IN_SALES'!$F$15)+('ENG_OPS'!$H$78*'IN_SALES'!$G$15) | I80: =('ENG_OPS'!$I$75*'IN_SALES'!$D$15)+('ENG_OPS'!$I$76*'IN_SALES'!$E$15)+('ENG_OPS'!$I$77*'IN_SALES'!$F$15)+('ENG_OPS'!$I$78*'IN_SALES'!$G$15) | J80: =('ENG_OPS'!$J$75*'IN_SALES'!$D$15)+('ENG_OPS'!$J$76*'IN_SALES'!$E$15)+('ENG_OPS'!$J$77*'IN_SALES'!$F$15)+('ENG_OPS'!$J$78*'IN_SALES'!$G$15) | K80: =('ENG_OPS'!$K$75*'IN_SALES'!$D$15)+('ENG_OPS'!$K$76*'IN_SALES'!$E$15)+('ENG_OPS'!$K$77*'IN_SALES'!$F$15)+('ENG_OPS'!$K$78*'IN_SALES'!$G$15) | L80: =('ENG_OPS'!$L$75*'IN_SALES'!$D$15)+('ENG_OPS'!$L$76*'IN_SALES'!$E$15)+('ENG_OPS'!$L$77*'IN_SALES'!$F$15)+('ENG_OPS'!$L$78*'IN_SALES'!$G$15) | M80: =('ENG_OPS'!$M$75*'IN_SALES'!$D$15)+('ENG_OPS'!$M$76*'IN_SALES'!$E$15)+('ENG_OPS'!$M$77*'IN_SALES'!$F$15)+('ENG_OPS'!$M$78*'IN_SALES'!$G$15) | N80: =('ENG_OPS'!$N$75*'IN_SALES'!$D$15)+('ENG_OPS'!$N$76*'IN_SALES'!$E$15)+('ENG_OPS'!$N$77*'IN_SALES'!$F$15)+('ENG_OPS'!$N$78*'IN_SALES'!$G$15) | O80: =('ENG_OPS'!$O$75*'IN_SALES'!$D$15)+('ENG_OPS'!$O$76*'IN_SALES'!$E$15)+('ENG_OPS'!$O$77*'IN_SALES'!$F$15)+('ENG_OPS'!$O$78*'IN_SALES'!$G$15) | P80: =('ENG_OPS'!$P$75*'IN_SALES'!$D$15)+('ENG_OPS'!$P$76*'IN_SALES'!$E$15)+('ENG_OPS'!$P$77*'IN_SALES'!$F$15)+('ENG_OPS'!$P$78*'IN_SALES'!$G$15)
A81: درآمد خالص | B81: OPS.rev | C81: میلیون ریال | D81: ='ENG_OPS'!$D$79-'ENG_OPS'!$D$80 | E81: ='ENG_OPS'!$E$79-'ENG_OPS'!$E$80 | F81: ='ENG_OPS'!$F$79-'ENG_OPS'!$F$80 | G81: ='ENG_OPS'!$G$79-'ENG_OPS'!$G$80 | H81: ='ENG_OPS'!$H$79-'ENG_OPS'!$H$80 | I81: ='ENG_OPS'!$I$79-'ENG_OPS'!$I$80 | J81: ='ENG_OPS'!$J$79-'ENG_OPS'!$J$80 | K81: ='ENG_OPS'!$K$79-'ENG_OPS'!$K$80 | L81: ='ENG_OPS'!$L$79-'ENG_OPS'!$L$80 | M81: ='ENG_OPS'!$M$79-'ENG_OPS'!$M$80 | N81: ='ENG_OPS'!$N$79-'ENG_OPS'!$N$80 | O81: ='ENG_OPS'!$O$79-'ENG_OPS'!$O$80 | P81: ='ENG_OPS'!$P$79-'ENG_OPS'!$P$80
A82: جمع تن فروخته‌شده | B82: OPS.sold_tons | C82: تن | D82: ='ENG_OPS'!$D$71+'ENG_OPS'!$D$72+'ENG_OPS'!$D$73+'ENG_OPS'!$D$74 | E82: ='ENG_OPS'!$E$71+'ENG_OPS'!$E$72+'ENG_OPS'!$E$73+'ENG_OPS'!$E$74 | F82: ='ENG_OPS'!$F$71+'ENG_OPS'!$F$72+'ENG_OPS'!$F$73+'ENG_OPS'!$F$74 | G82: ='ENG_OPS'!$G$71+'ENG_OPS'!$G$72+'ENG_OPS'!$G$73+'ENG_OPS'!$G$74 | H82: ='ENG_OPS'!$H$71+'ENG_OPS'!$H$72+'ENG_OPS'!$H$73+'ENG_OPS'!$H$74 | I82: ='ENG_OPS'!$I$71+'ENG_OPS'!$I$72+'ENG_OPS'!$I$73+'ENG_OPS'!$I$74 | J82: ='ENG_OPS'!$J$71+'ENG_OPS'!$J$72+'ENG_OPS'!$J$73+'ENG_OPS'!$J$74 | K82: ='ENG_OPS'!$K$71+'ENG_OPS'!$K$72+'ENG_OPS'!$K$73+'ENG_OPS'!$K$74 | L82: ='ENG_OPS'!$L$71+'ENG_OPS'!$L$72+'ENG_OPS'!$L$73+'ENG_OPS'!$L$74 | M82: ='ENG_OPS'!$M$71+'ENG_OPS'!$M$72+'ENG_OPS'!$M$73+'ENG_OPS'!$M$74 | N82: ='ENG_OPS'!$N$71+'ENG_OPS'!$N$72+'ENG_OPS'!$N$73+'ENG_OPS'!$N$74 | O82: ='ENG_OPS'!$O$71+'ENG_OPS'!$O$72+'ENG_OPS'!$O$73+'ENG_OPS'!$O$74 | P82: ='ENG_OPS'!$P$71+'ENG_OPS'!$P$72+'ENG_OPS'!$P$73+'ENG_OPS'!$P$74
A83: درآمد خالص هر تن محصول | B83: OPS.rev_per_ton | C83: میلیون ریال/تن | D83: =IFERROR('ENG_OPS'!$D$81/'ENG_OPS'!$D$82,0) | E83: =IFERROR('ENG_OPS'!$E$81/'ENG_OPS'!$E$82,0) | F83: =IFERROR('ENG_OPS'!$F$81/'ENG_OPS'!$F$82,0) | G83: =IFERROR('ENG_OPS'!$G$81/'ENG_OPS'!$G$82,0) | H83: =IFERROR('ENG_OPS'!$H$81/'ENG_OPS'!$H$82,0) | I83: =IFERROR('ENG_OPS'!$I$81/'ENG_OPS'!$I$82,0) | J83: =IFERROR('ENG_OPS'!$J$81/'ENG_OPS'!$J$82,0) | K83: =IFERROR('ENG_OPS'!$K$81/'ENG_OPS'!$K$82,0) | L83: =IFERROR('ENG_OPS'!$L$81/'ENG_OPS'!$L$82,0) | M83: =IFERROR('ENG_OPS'!$M$81/'ENG_OPS'!$M$82,0) | N83: =IFERROR('ENG_OPS'!$N$81/'ENG_OPS'!$N$82,0) | O83: =IFERROR('ENG_OPS'!$O$81/'ENG_OPS'!$O$82,0) | P83: =IFERROR('ENG_OPS'!$P$81/'ENG_OPS'!$P$82,0)
A84: سهم ارزی درآمد (وزنی) | B84: OPS.fxsh_rev | C84: درصد | D84: =IFERROR((('ENG_OPS'!$D$75*'IN_SALES'!$D$14)+('ENG_OPS'!$D$76*'IN_SALES'!$E$14)+('ENG_OPS'!$D$77*'IN_SALES'!$F$14)+('ENG_OPS'!$D$78*'IN_SALES'!$G$14))/('ENG_OPS'!$D$79),0) | E84: =IFERROR((('ENG_OPS'!$E$75*'IN_SALES'!$D$14)+('ENG_OPS'!$E$76*'IN_SALES'!$E$14)+('ENG_OPS'!$E$77*'IN_SALES'!$F$14)+('ENG_OPS'!$E$78*'IN_SALES'!$G$14))/('ENG_OPS'!$E$79),0) | F84: =IFERROR((('ENG_OPS'!$F$75*'IN_SALES'!$D$14)+('ENG_OPS'!$F$76*'IN_SALES'!$E$14)+('ENG_OPS'!$F$77*'IN_SALES'!$F$14)+('ENG_OPS'!$F$78*'IN_SALES'!$G$14))/('ENG_OPS'!$F$79),0) | G84: =IFERROR((('ENG_OPS'!$G$75*'IN_SALES'!$D$14)+('ENG_OPS'!$G$76*'IN_SALES'!$E$14)+('ENG_OPS'!$G$77*'IN_SALES'!$F$14)+('ENG_OPS'!$G$78*'IN_SALES'!$G$14))/('ENG_OPS'!$G$79),0) | H84: =IFERROR((('ENG_OPS'!$H$75*'IN_SALES'!$D$14)+('ENG_OPS'!$H$76*'IN_SALES'!$E$14)+('ENG_OPS'!$H$77*'IN_SALES'!$F$14)+('ENG_OPS'!$H$78*'IN_SALES'!$G$14))/('ENG_OPS'!$H$79),0) | I84: =IFERROR((('ENG_OPS'!$I$75*'IN_SALES'!$D$14)+('ENG_OPS'!$I$76*'IN_SALES'!$E$14)+('ENG_OPS'!$I$77*'IN_SALES'!$F$14)+('ENG_OPS'!$I$78*'IN_SALES'!$G$14))/('ENG_OPS'!$I$79),0) | J84: =IFERROR((('ENG_OPS'!$J$75*'IN_SALES'!$D$14)+('ENG_OPS'!$J$76*'IN_SALES'!$E$14)+('ENG_OPS'!$J$77*'IN_SALES'!$F$14)+('ENG_OPS'!$J$78*'IN_SALES'!$G$14))/('ENG_OPS'!$J$79),0) | K84: =IFERROR((('ENG_OPS'!$K$75*'IN_SALES'!$D$14)+('ENG_OPS'!$K$76*'IN_SALES'!$E$14)+('ENG_OPS'!$K$77*'IN_SALES'!$F$14)+('ENG_OPS'!$K$78*'IN_SALES'!$G$14))/('ENG_OPS'!$K$79),0) | L84: =IFERROR((('ENG_OPS'!$L$75*'IN_SALES'!$D$14)+('ENG_OPS'!$L$76*'IN_SALES'!$E$14)+('ENG_OPS'!$L$77*'IN_SALES'!$F$14)+('ENG_OPS'!$L$78*'IN_SALES'!$G$14))/('ENG_OPS'!$L$79),0) | M84: =IFERROR((('ENG_OPS'!$M$75*'IN_SALES'!$D$14)+('ENG_OPS'!$M$76*'IN_SALES'!$E$14)+('ENG_OPS'!$M$77*'IN_SALES'!$F$14)+('ENG_OPS'!$M$78*'IN_SALES'!$G$14))/('ENG_OPS'!$M$79),0) | N84: =IFERROR((('ENG_OPS'!$N$75*'IN_SALES'!$D$14)+('ENG_OPS'!$N$76*'IN_SALES'!$E$14)+('ENG_OPS'!$N$77*'IN_SALES'!$F$14)+('ENG_OPS'!$N$78*'IN_SALES'!$G$14))/('ENG_OPS'!$N$79),0) | O84: =IFERROR((('ENG_OPS'!$O$75*'IN_SALES'!$D$14)+('ENG_OPS'!$O$76*'IN_SALES'!$E$14)+('ENG_OPS'!$O$77*'IN_SALES'!$F$14)+('ENG_OPS'!$O$78*'IN_SALES'!$G$14))/('ENG_OPS'!$O$79),0) | P84: =IFERROR((('ENG_OPS'!$P$75*'IN_SALES'!$D$14)+('ENG_OPS'!$P$76*'IN_SALES'!$E$14)+('ENG_OPS'!$P$77*'IN_SALES'!$F$14)+('ENG_OPS'!$P$78*'IN_SALES'!$G$14))/('ENG_OPS'!$P$79),0)

Sheet ENG_CAPEX
A1: چرخهٔ عمر دارایی‌ها و CAPEX | B1: موتور محاسبات
A2: برنامه تزریق سرمایه‌گذاری، جایگزینی تجهیزات، استهلاک و ارزش دفتری دارایی‌ها.
A7: دوره (t) | D7: 0 | E7: 1 | F7: 2 | G7: 3 | H7: 4 | I7: 5 | J7: 6 | K7: 7 | L7: 8 | M7: 9 | N7: 10 | O7: 11 | P7: 12
A8: سال تقویمی | D8: 2026 | E8: 2027 | F8: 2028 | G8: 2029 | H8: 2030 | I8: 2031 | J8: 2032 | K8: 2033 | L8: 2034 | M8: 2035 | N8: 2036 | O8: 2037 | P8: 2038
A9: الف) برنامه تزریق سرمایه‌گذاری ثابت
A10: سرمایه‌گذاری زمین | B10: CAPEX.cap.0 | C10: میلیون ریال | D10: ='IN_FIN'!$D$9*((1-'IN_FIN'!$E$9)*'ENG_SCEN'!$D$32+'IN_FIN'!$E$9*'ENG_SCEN'!$D$36)*(IF('IN_MACRO'!$D$23=0,'IN_FIN'!$J$9,IF('IN_MACRO'!$D$23=1,'IN_FIN'!$K$9,IF('IN_MACRO'!$D$23=2,'IN_FIN'!$L$9,0))))*'ENG_SCEN'!$G$16 | E10: ='IN_FIN'!$D$9*((1-'IN_FIN'!$E$9)*'ENG_SCEN'!$E$32+'IN_FIN'!$E$9*'ENG_SCEN'!$E$36)*(IF('IN_MACRO'!$E$23=0,'IN_FIN'!$J$9,IF('IN_MACRO'!$E$23=1,'IN_FIN'!$K$9,IF('IN_MACRO'!$E$23=2,'IN_FIN'!$L$9,0))))*'ENG_SCEN'!$G$16 | F10: ='IN_FIN'!$D$9*((1-'IN_FIN'!$E$9)*'ENG_SCEN'!$F$32+'IN_FIN'!$E$9*'ENG_SCEN'!$F$36)*(IF('IN_MACRO'!$F$23=0,'IN_FIN'!$J$9,IF('IN_MACRO'!$F$23=1,'IN_FIN'!$K$9,IF('IN_MACRO'!$F$23=2,'IN_FIN'!$L$9,0))))*'ENG_SCEN'!$G$16 | G10: ='IN_FIN'!$D$9*((1-'IN_FIN'!$E$9)*'ENG_SCEN'!$G$32+'IN_FIN'!$E$9*'ENG_SCEN'!$G$36)*(IF('IN_MACRO'!$G$23=0,'IN_FIN'!$J$9,IF('IN_MACRO'!$G$23=1,'IN_FIN'!$K$9,IF('IN_MACRO'!$G$23=2,'IN_FIN'!$L$9,0))))*'ENG_SCEN'!$G$16 | H10: ='IN_FIN'!$D$9*((1-'IN_FIN'!$E$9)*'ENG_SCEN'!$H$32+'IN_FIN'!$E$9*'ENG_SCEN'!$H$36)*(IF('IN_MACRO'!$H$23=0,'IN_FIN'!$J$9,IF('IN_MACRO'!$H$23=1,'IN_FIN'!$K$9,IF('IN_MACRO'!$H$23=2,'IN_FIN'!$L$9,0))))*'ENG_SCEN'!$G$16 | I10: ='IN_FIN'!$D$9*((1-'IN_FIN'!$E$9)*'ENG_SCEN'!$I$32+'IN_FIN'!$E$9*'ENG_SCEN'!$I$36)*(IF('IN_MACRO'!$I$23=0,'IN_FIN'!$J$9,IF('IN_MACRO'!$I$23=1,'IN_FIN'!$K$9,IF('IN_MACRO'!$I$23=2,'IN_FIN'!$L$9,0))))*'ENG_SCEN'!$G$16 | J10: ='IN_FIN'!$D$9*((1-'IN_FIN'!$E$9)*'ENG_SCEN'!$J$32+'IN_FIN'!$E$9*'ENG_SCEN'!$J$36)*(IF('IN_MACRO'!$J$23=0,'IN_FIN'!$J$9,IF('IN_MACRO'!$J$23=1,'IN_FIN'!$K$9,IF('IN_MACRO'!$J$23=2,'IN_FIN'!$L$9,0))))*'ENG_SCEN'!$G$16 | K10: ='IN_FIN'!$D$9*((1-'IN_FIN'!$E$9)*'ENG_SCEN'!$K$32+'IN_FIN'!$E$9*'ENG_SCEN'!$K$36)*(IF('IN_MACRO'!$K$23=0,'IN_FIN'!$J$9,IF('IN_MACRO'!$K$23=1,'IN_FIN'!$K$9,IF('IN_MACRO'!$K$23=2,'IN_FIN'!$L$9,0))))*'ENG_SCEN'!$G$16 | L10: ='IN_FIN'!$D$9*((1-'IN_FIN'!$E$9)*'ENG_SCEN'!$L$32+'IN_FIN'!$E$9*'ENG_SCEN'!$L$36)*(IF('IN_MACRO'!$L$23=0,'IN_FIN'!$J$9,IF('IN_MACRO'!$L$23=1,'IN_FIN'!$K$9,IF('IN_MACRO'!$L$23=2,'IN_FIN'!$L$9,0))))*'ENG_SCEN'!$G$16 | M10: ='IN_FIN'!$D$9*((1-'IN_FIN'!$E$9)*'ENG_SCEN'!$M$32+'IN_FIN'!$E$9*'ENG_SCEN'!$M$36)*(IF('IN_MACRO'!$M$23=0,'IN_FIN'!$J$9,IF('IN_MACRO'!$M$23=1,'IN_FIN'!$K$9,IF('IN_MACRO'!$M$23=2,'IN_FIN'!$L$9,0))))*'ENG_SCEN'!$G$16 | N10: ='IN_FIN'!$D$9*((1-'IN_FIN'!$E$9)*'ENG_SCEN'!$N$32+'IN_FIN'!$E$9*'ENG_SCEN'!$N$36)*(IF('IN_MACRO'!$N$23=0,'IN_FIN'!$J$9,IF('IN_MACRO'!$N$23=1,'IN_FIN'!$K$9,IF('IN_MACRO'!$N$23=2,'IN_FIN'!$L$9,0))))*'ENG_SCEN'!$G$16 | O10: ='IN_FIN'!$D$9*((1-'IN_FIN'!$E$9)*'ENG_SCEN'!$O$32+'IN_FIN'!$E$9*'ENG_SCEN'!$O$36)*(IF('IN_MACRO'!$O$23=0,'IN_FIN'!$J$9,IF('IN_MACRO'!$O$23=1,'IN_FIN'!$K$9,IF('IN_MACRO'!$O$23=2,'IN_FIN'!$L$9,0))))*'ENG_SCEN'!$G$16 | P10: ='IN_FIN'!$D$9*((1-'IN_FIN'!$E$9)*'ENG_SCEN'!$P$32+'IN_FIN'!$E$9*'ENG_SCEN'!$P$36)*(IF('IN_MACRO'!$P$23=0,'IN_FIN'!$J$9,IF('IN_MACRO'!$P$23=1,'IN_FIN'!$K$9,IF('IN_MACRO'!$P$23=2,'IN_FIN'!$L$9,0))))*'ENG_SCEN'!$G$16
A11: سرمایه‌گذاری محوطه‌سازی و ساختمان | B11: CAPEX.cap.1 | C11: میلیون ریال | D11: ='IN_FIN'!$D$10*((1-'IN_FIN'!$E$10)*'ENG_SCEN'!$D$32+'IN_FIN'!$E$10*'ENG_SCEN'!$D$36)*(IF('IN_MACRO'!$D$23=0,'IN_FIN'!$J$10,IF('IN_MACRO'!$D$23=1,'IN_FIN'!$K$10,IF('IN_MACRO'!$D$23=2,'IN_FIN'!$L$10,0))))*'ENG_SCEN'!$G$16 | E11: ='IN_FIN'!$D$10*((1-'IN_FIN'!$E$10)*'ENG_SCEN'!$E$32+'IN_FIN'!$E$10*'ENG_SCEN'!$E$36)*(IF('IN_MACRO'!$E$23=0,'IN_FIN'!$J$10,IF('IN_MACRO'!$E$23=1,'IN_FIN'!$K$10,IF('IN_MACRO'!$E$23=2,'IN_FIN'!$L$10,0))))*'ENG_SCEN'!$G$16 | F11: ='IN_FIN'!$D$10*((1-'IN_FIN'!$E$10)*'ENG_SCEN'!$F$32+'IN_FIN'!$E$10*'ENG_SCEN'!$F$36)*(IF('IN_MACRO'!$F$23=0,'IN_FIN'!$J$10,IF('IN_MACRO'!$F$23=1,'IN_FIN'!$K$10,IF('IN_MACRO'!$F$23=2,'IN_FIN'!$L$10,0))))*'ENG_SCEN'!$G$16 | G11: ='IN_FIN'!$D$10*((1-'IN_FIN'!$E$10)*'ENG_SCEN'!$G$32+'IN_FIN'!$E$10*'ENG_SCEN'!$G$36)*(IF('IN_MACRO'!$G$23=0,'IN_FIN'!$J$10,IF('IN_MACRO'!$G$23=1,'IN_FIN'!$K$10,IF('IN_MACRO'!$G$23=2,'IN_FIN'!$L$10,0))))*'ENG_SCEN'!$G$16 | H11: ='IN_FIN'!$D$10*((1-'IN_FIN'!$E$10)*'ENG_SCEN'!$H$32+'IN_FIN'!$E$10*'ENG_SCEN'!$H$36)*(IF('IN_MACRO'!$H$23=0,'IN_FIN'!$J$10,IF('IN_MACRO'!$H$23=1,'IN_FIN'!$K$10,IF('IN_MACRO'!$H$23=2,'IN_FIN'!$L$10,0))))*'ENG_SCEN'!$G$16 | I11: ='IN_FIN'!$D$10*((1-'IN_FIN'!$E$10)*'ENG_SCEN'!$I$32+'IN_FIN'!$E$10*'ENG_SCEN'!$I$36)*(IF('IN_MACRO'!$I$23=0,'IN_FIN'!$J$10,IF('IN_MACRO'!$I$23=1,'IN_FIN'!$K$10,IF('IN_MACRO'!$I$23=2,'IN_FIN'!$L$10,0))))*'ENG_SCEN'!$G$16 | J11: ='IN_FIN'!$D$10*((1-'IN_FIN'!$E$10)*'ENG_SCEN'!$J$32+'IN_FIN'!$E$10*'ENG_SCEN'!$J$36)*(IF('IN_MACRO'!$J$23=0,'IN_FIN'!$J$10,IF('IN_MACRO'!$J$23=1,'IN_FIN'!$K$10,IF('IN_MACRO'!$J$23=2,'IN_FIN'!$L$10,0))))*'ENG_SCEN'!$G$16 | K11: ='IN_FIN'!$D$10*((1-'IN_FIN'!$E$10)*'ENG_SCEN'!$K$32+'IN_FIN'!$E$10*'ENG_SCEN'!$K$36)*(IF('IN_MACRO'!$K$23=0,'IN_FIN'!$J$10,IF('IN_MACRO'!$K$23=1,'IN_FIN'!$K$10,IF('IN_MACRO'!$K$23=2,'IN_FIN'!$L$10,0))))*'ENG_SCEN'!$G$16 | L11: ='IN_FIN'!$D$10*((1-'IN_FIN'!$E$10)*'ENG_SCEN'!$L$32+'IN_FIN'!$E$10*'ENG_SCEN'!$L$36)*(IF('IN_MACRO'!$L$23=0,'IN_FIN'!$J$10,IF('IN_MACRO'!$L$23=1,'IN_FIN'!$K$10,IF('IN_MACRO'!$L$23=2,'IN_FIN'!$L$10,0))))*'ENG_SCEN'!$G$16 | M11: ='IN_FIN'!$D$10*((1-'IN_FIN'!$E$10)*'ENG_SCEN'!$M$32+'IN_FIN'!$E$10*'ENG_SCEN'!$M$36)*(IF('IN_MACRO'!$M$23=0,'IN_FIN'!$J$10,IF('IN_MACRO'!$M$23=1,'IN_FIN'!$K$10,IF('IN_MACRO'!$M$23=2,'IN_FIN'!$L$10,0))))*'ENG_SCEN'!$G$16 | N11: ='IN_FIN'!$D$10*((1-'IN_FIN'!$E$10)*'ENG_SCEN'!$N$32+'IN_FIN'!$E$10*'ENG_SCEN'!$N$36)*(IF('IN_MACRO'!$N$23=0,'IN_FIN'!$J$10,IF('IN_MACRO'!$N$23=1,'IN_FIN'!$K$10,IF('IN_MACRO'!$N$23=2,'IN_FIN'!$L$10,0))))*'ENG_SCEN'!$G$16 | O11: ='IN_FIN'!$D$10*((1-'IN_FIN'!$E$10)*'ENG_SCEN'!$O$32+'IN_FIN'!$E$10*'ENG_SCEN'!$O$36)*(IF('IN_MACRO'!$O$23=0,'IN_FIN'!$J$10,IF('IN_MACRO'!$O$23=1,'IN_FIN'!$K$10,IF('IN_MACRO'!$O$23=2,'IN_FIN'!$L$10,0))))*'ENG_SCEN'!$G$16 | P11: ='IN_FIN'!$D$10*((1-'IN_FIN'!$E$10)*'ENG_SCEN'!$P$32+'IN_FIN'!$E$10*'ENG_SCEN'!$P$36)*(IF('IN_MACRO'!$P$23=0,'IN_FIN'!$J$10,IF('IN_MACRO'!$P$23=1,'IN_FIN'!$K$10,IF('IN_MACRO'!$P$23=2,'IN_FIN'!$L$10,0))))*'ENG_SCEN'!$G$16
A12: سرمایه‌گذاری ماشین‌آلات وارداتی | B12: CAPEX.cap.2 | C12: میلیون ریال | D12: ='IN_FIN'!$D$11*((1-'IN_FIN'!$E$11)*'ENG_SCEN'!$D$32+'IN_FIN'!$E$11*'ENG_SCEN'!$D$36)*(IF('IN_MACRO'!$D$23=0,'IN_FIN'!$J$11,IF('IN_MACRO'!$D$23=1,'IN_FIN'!$K$11,IF('IN_MACRO'!$D$23=2,'IN_FIN'!$L$11,0))))*'ENG_SCEN'!$G$16 | E12: ='IN_FIN'!$D$11*((1-'IN_FIN'!$E$11)*'ENG_SCEN'!$E$32+'IN_FIN'!$E$11*'ENG_SCEN'!$E$36)*(IF('IN_MACRO'!$E$23=0,'IN_FIN'!$J$11,IF('IN_MACRO'!$E$23=1,'IN_FIN'!$K$11,IF('IN_MACRO'!$E$23=2,'IN_FIN'!$L$11,0))))*'ENG_SCEN'!$G$16 | F12: ='IN_FIN'!$D$11*((1-'IN_FIN'!$E$11)*'ENG_SCEN'!$F$32+'IN_FIN'!$E$11*'ENG_SCEN'!$F$36)*(IF('IN_MACRO'!$F$23=0,'IN_FIN'!$J$11,IF('IN_MACRO'!$F$23=1,'IN_FIN'!$K$11,IF('IN_MACRO'!$F$23=2,'IN_FIN'!$L$11,0))))*'ENG_SCEN'!$G$16 | G12: ='IN_FIN'!$D$11*((1-'IN_FIN'!$E$11)*'ENG_SCEN'!$G$32+'IN_FIN'!$E$11*'ENG_SCEN'!$G$36)*(IF('IN_MACRO'!$G$23=0,'IN_FIN'!$J$11,IF('IN_MACRO'!$G$23=1,'IN_FIN'!$K$11,IF('IN_MACRO'!$G$23=2,'IN_FIN'!$L$11,0))))*'ENG_SCEN'!$G$16 | H12: ='IN_FIN'!$D$11*((1-'IN_FIN'!$E$11)*'ENG_SCEN'!$H$32+'IN_FIN'!$E$11*'ENG_SCEN'!$H$36)*(IF('IN_MACRO'!$H$23=0,'IN_FIN'!$J$11,IF('IN_MACRO'!$H$23=1,'IN_FIN'!$K$11,IF('IN_MACRO'!$H$23=2,'IN_FIN'!$L$11,0))))*'ENG_SCEN'!$G$16 | I12: ='IN_FIN'!$D$11*((1-'IN_FIN'!$E$11)*'ENG_SCEN'!$I$32+'IN_FIN'!$E$11*'ENG_SCEN'!$I$36)*(IF('IN_MACRO'!$I$23=0,'IN_FIN'!$J$11,IF('IN_MACRO'!$I$23=1,'IN_FIN'!$K$11,IF('IN_MACRO'!$I$23=2,'IN_FIN'!$L$11,0))))*'ENG_SCEN'!$G$16 | J12: ='IN_FIN'!$D$11*((1-'IN_FIN'!$E$11)*'ENG_SCEN'!$J$32+'IN_FIN'!$E$11*'ENG_SCEN'!$J$36)*(IF('IN_MACRO'!$J$23=0,'IN_FIN'!$J$11,IF('IN_MACRO'!$J$23=1,'IN_FIN'!$K$11,IF('IN_MACRO'!$J$23=2,'IN_FIN'!$L$11,0))))*'ENG_SCEN'!$G$16 | K12: ='IN_FIN'!$D$11*((1-'IN_FIN'!$E$11)*'ENG_SCEN'!$K$32+'IN_FIN'!$E$11*'ENG_SCEN'!$K$36)*(IF('IN_MACRO'!$K$23=0,'IN_FIN'!$J$11,IF('IN_MACRO'!$K$23=1,'IN_FIN'!$K$11,IF('IN_MACRO'!$K$23=2,'IN_FIN'!$L$11,0))))*'ENG_SCEN'!$G$16 | L12: ='IN_FIN'!$D$11*((1-'IN_FIN'!$E$11)*'ENG_SCEN'!$L$32+'IN_FIN'!$E$11*'ENG_SCEN'!$L$36)*(IF('IN_MACRO'!$L$23=0,'IN_FIN'!$J$11,IF('IN_MACRO'!$L$23=1,'IN_FIN'!$K$11,IF('IN_MACRO'!$L$23=2,'IN_FIN'!$L$11,0))))*'ENG_SCEN'!$G$16 | M12: ='IN_FIN'!$D$11*((1-'IN_FIN'!$E$11)*'ENG_SCEN'!$M$32+'IN_FIN'!$E$11*'ENG_SCEN'!$M$36)*(IF('IN_MACRO'!$M$23=0,'IN_FIN'!$J$11,IF('IN_MACRO'!$M$23=1,'IN_FIN'!$K$11,IF('IN_MACRO'!$M$23=2,'IN_FIN'!$L$11,0))))*'ENG_SCEN'!$G$16 | N12: ='IN_FIN'!$D$11*((1-'IN_FIN'!$E$11)*'ENG_SCEN'!$N$32+'IN_FIN'!$E$11*'ENG_SCEN'!$N$36)*(IF('IN_MACRO'!$N$23=0,'IN_FIN'!$J$11,IF('IN_MACRO'!$N$23=1,'IN_FIN'!$K$11,IF('IN_MACRO'!$N$23=2,'IN_FIN'!$L$11,0))))*'ENG_SCEN'!$G$16 | O12: ='IN_FIN'!$D$11*((1-'IN_FIN'!$E$11)*'ENG_SCEN'!$O$32+'IN_FIN'!$E$11*'ENG_SCEN'!$O$36)*(IF('IN_MACRO'!$O$23=0,'IN_FIN'!$J$11,IF('IN_MACRO'!$O$23=1,'IN_FIN'!$K$11,IF('IN_MACRO'!$O$23=2,'IN_FIN'!$L$11,0))))*'ENG_SCEN'!$G$16 | P12: ='IN_FIN'!$D$11*((1-'IN_FIN'!$E$11)*'ENG_SCEN'!$P$32+'IN_FIN'!$E$11*'ENG_SCEN'!$P$36)*(IF('IN_MACRO'!$P$23=0,'IN_FIN'!$J$11,IF('IN_MACRO'!$P$23=1,'IN_FIN'!$K$11,IF('IN_MACRO'!$P$23=2,'IN_FIN'!$L$11,0))))*'ENG_SCEN'!$G$16
A13: سرمایه‌گذاری ماشین‌آلات داخلی | B13: CAPEX.cap.3 | C13: میلیون ریال | D13: ='IN_FIN'!$D$12*((1-'IN_FIN'!$E$12)*'ENG_SCEN'!$D$32+'IN_FIN'!$E$12*'ENG_SCEN'!$D$36)*(IF('IN_MACRO'!$D$23=0,'IN_FIN'!$J$12,IF('IN_MACRO'!$D$23=1,'IN_FIN'!$K$12,IF('IN_MACRO'!$D$23=2,'IN_FIN'!$L$12,0))))*'ENG_SCEN'!$G$16 | E13: ='IN_FIN'!$D$12*((1-'IN_FIN'!$E$12)*'ENG_SCEN'!$E$32+'IN_FIN'!$E$12*'ENG_SCEN'!$E$36)*(IF('IN_MACRO'!$E$23=0,'IN_FIN'!$J$12,IF('IN_MACRO'!$E$23=1,'IN_FIN'!$K$12,IF('IN_MACRO'!$E$23=2,'IN_FIN'!$L$12,0))))*'ENG_SCEN'!$G$16 | F13: ='IN_FIN'!$D$12*((1-'IN_FIN'!$E$12)*'ENG_SCEN'!$F$32+'IN_FIN'!$E$12*'ENG_SCEN'!$F$36)*(IF('IN_MACRO'!$F$23=0,'IN_FIN'!$J$12,IF('IN_MACRO'!$F$23=1,'IN_FIN'!$K$12,IF('IN_MACRO'!$F$23=2,'IN_FIN'!$L$12,0))))*'ENG_SCEN'!$G$16 | G13: ='IN_FIN'!$D$12*((1-'IN_FIN'!$E$12)*'ENG_SCEN'!$G$32+'IN_FIN'!$E$12*'ENG_SCEN'!$G$36)*(IF('IN_MACRO'!$G$23=0,'IN_FIN'!$J$12,IF('IN_MACRO'!$G$23=1,'IN_FIN'!$K$12,IF('IN_MACRO'!$G$23=2,'IN_FIN'!$L$12,0))))*'ENG_SCEN'!$G$16 | H13: ='IN_FIN'!$D$12*((1-'IN_FIN'!$E$12)*'ENG_SCEN'!$H$32+'IN_FIN'!$E$12*'ENG_SCEN'!$H$36)*(IF('IN_MACRO'!$H$23=0,'IN_FIN'!$J$12,IF('IN_MACRO'!$H$23=1,'IN_FIN'!$K$12,IF('IN_MACRO'!$H$23=2,'IN_FIN'!$L$12,0))))*'ENG_SCEN'!$G$16 | I13: ='IN_FIN'!$D$12*((1-'IN_FIN'!$E$12)*'ENG_SCEN'!$I$32+'IN_FIN'!$E$12*'ENG_SCEN'!$I$36)*(IF('IN_MACRO'!$I$23=0,'IN_FIN'!$J$12,IF('IN_MACRO'!$I$23=1,'IN_FIN'!$K$12,IF('IN_MACRO'!$I$23=2,'IN_FIN'!$L$12,0))))*'ENG_SCEN'!$G$16 | J13: ='IN_FIN'!$D$12*((1-'IN_FIN'!$E$12)*'ENG_SCEN'!$J$32+'IN_FIN'!$E$12*'ENG_SCEN'!$J$36)*(IF('IN_MACRO'!$J$23=0,'IN_FIN'!$J$12,IF('IN_MACRO'!$J$23=1,'IN_FIN'!$K$12,IF('IN_MACRO'!$J$23=2,'IN_FIN'!$L$12,0))))*'ENG_SCEN'!$G$16 | K13: ='IN_FIN'!$D$12*((1-'IN_FIN'!$E$12)*'ENG_SCEN'!$K$32+'IN_FIN'!$E$12*'ENG_SCEN'!$K$36)*(IF('IN_MACRO'!$K$23=0,'IN_FIN'!$J$12,IF('IN_MACRO'!$K$23=1,'IN_FIN'!$K$12,IF('IN_MACRO'!$K$23=2,'IN_FIN'!$L$12,0))))*'ENG_SCEN'!$G$16 | L13: ='IN_FIN'!$D$12*((1-'IN_FIN'!$E$12)*'ENG_SCEN'!$L$32+'IN_FIN'!$E$12*'ENG_SCEN'!$L$36)*(IF('IN_MACRO'!$L$23=0,'IN_FIN'!$J$12,IF('IN_MACRO'!$L$23=1,'IN_FIN'!$K$12,IF('IN_MACRO'!$L$23=2,'IN_FIN'!$L$12,0))))*'ENG_SCEN'!$G$16 | M13: ='IN_FIN'!$D$12*((1-'IN_FIN'!$E$12)*'ENG_SCEN'!$M$32+'IN_FIN'!$E$12*'ENG_SCEN'!$M$36)*(IF('IN_MACRO'!$M$23=0,'IN_FIN'!$J$12,IF('IN_MACRO'!$M$23=1,'IN_FIN'!$K$12,IF('IN_MACRO'!$M$23=2,'IN_FIN'!$L$12,0))))*'ENG_SCEN'!$G$16 | N13: ='IN_FIN'!$D$12*((1-'IN_FIN'!$E$12)*'ENG_SCEN'!$N$32+'IN_FIN'!$E$12*'ENG_SCEN'!$N$36)*(IF('IN_MACRO'!$N$23=0,'IN_FIN'!$J$12,IF('IN_MACRO'!$N$23=1,'IN_FIN'!$K$12,IF('IN_MACRO'!$N$23=2,'IN_FIN'!$L$12,0))))*'ENG_SCEN'!$G$16 | O13: ='IN_FIN'!$D$12*((1-'IN_FIN'!$E$12)*'ENG_SCEN'!$O$32+'IN_FIN'!$E$12*'ENG_SCEN'!$O$36)*(IF('IN_MACRO'!$O$23=0,'IN_FIN'!$J$12,IF('IN_MACRO'!$O$23=1,'IN_FIN'!$K$12,IF('IN_MACRO'!$O$23=2,'IN_FIN'!$L$12,0))))*'ENG_SCEN'!$G$16 | P13: ='IN_FIN'!$D$12*((1-'IN_FIN'!$E$12)*'ENG_SCEN'!$P$32+'IN_FIN'!$E$12*'ENG_SCEN'!$P$36)*(IF('IN_MACRO'!$P$23=0,'IN_FIN'!$J$12,IF('IN_MACRO'!$P$23=1,'IN_FIN'!$K$12,IF('IN_MACRO'!$P$23=2,'IN_FIN'!$L$12,0))))*'ENG_SCEN'!$G$16
A14: سرمایه‌گذاری تأسیسات و تجهیزات جانبی | B14: CAPEX.cap.4 | C14: میلیون ریال | D14: ='IN_FIN'!$D$13*((1-'IN_FIN'!$E$13)*'ENG_SCEN'!$D$32+'IN_FIN'!$E$13*'ENG_SCEN'!$D$36)*(IF('IN_MACRO'!$D$23=0,'IN_FIN'!$J$13,IF('IN_MACRO'!$D$23=1,'IN_FIN'!$K$13,IF('IN_MACRO'!$D$23=2,'IN_FIN'!$L$13,0))))*'ENG_SCEN'!$G$16 | E14: ='IN_FIN'!$D$13*((1-'IN_FIN'!$E$13)*'ENG_SCEN'!$E$32+'IN_FIN'!$E$13*'ENG_SCEN'!$E$36)*(IF('IN_MACRO'!$E$23=0,'IN_FIN'!$J$13,IF('IN_MACRO'!$E$23=1,'IN_FIN'!$K$13,IF('IN_MACRO'!$E$23=2,'IN_FIN'!$L$13,0))))*'ENG_SCEN'!$G$16 | F14: ='IN_FIN'!$D$13*((1-'IN_FIN'!$E$13)*'ENG_SCEN'!$F$32+'IN_FIN'!$E$13*'ENG_SCEN'!$F$36)*(IF('IN_MACRO'!$F$23=0,'IN_FIN'!$J$13,IF('IN_MACRO'!$F$23=1,'IN_FIN'!$K$13,IF('IN_MACRO'!$F$23=2,'IN_FIN'!$L$13,0))))*'ENG_SCEN'!$G$16 | G14: ='IN_FIN'!$D$13*((1-'IN_FIN'!$E$13)*'ENG_SCEN'!$G$32+'IN_FIN'!$E$13*'ENG_SCEN'!$G$36)*(IF('IN_MACRO'!$G$23=0,'IN_FIN'!$J$13,IF('IN_MACRO'!$G$23=1,'IN_FIN'!$K$13,IF('IN_MACRO'!$G$23=2,'IN_FIN'!$L$13,0))))*'ENG_SCEN'!$G$16 | H14: ='IN_FIN'!$D$13*((1-'IN_FIN'!$E$13)*'ENG_SCEN'!$H$32+'IN_FIN'!$E$13*'ENG_SCEN'!$H$36)*(IF('IN_MACRO'!$H$23=0,'IN_FIN'!$J$13,IF('IN_MACRO'!$H$23=1,'IN_FIN'!$K$13,IF('IN_MACRO'!$H$23=2,'IN_FIN'!$L$13,0))))*'ENG_SCEN'!$G$16 | I14: ='IN_FIN'!$D$13*((1-'IN_FIN'!$E$13)*'ENG_SCEN'!$I$32+'IN_FIN'!$E$13*'ENG_SCEN'!$I$36)*(IF('IN_MACRO'!$I$23=0,'IN_FIN'!$J$13,IF('IN_MACRO'!$I$23=1,'IN_FIN'!$K$13,IF('IN_MACRO'!$I$23=2,'IN_FIN'!$L$13,0))))*'ENG_SCEN'!$G$16 | J14: ='IN_FIN'!$D$13*((1-'IN_FIN'!$E$13)*'ENG_SCEN'!$J$32+'IN_FIN'!$E$13*'ENG_SCEN'!$J$36)*(IF('IN_MACRO'!$J$23=0,'IN_FIN'!$J$13,IF('IN_MACRO'!$J$23=1,'IN_FIN'!$K$13,IF('IN_MACRO'!$J$23=2,'IN_FIN'!$L$13,0))))*'ENG_SCEN'!$G$16 | K14: ='IN_FIN'!$D$13*((1-'IN_FIN'!$E$13)*'ENG_SCEN'!$K$32+'IN_FIN'!$E$13*'ENG_SCEN'!$K$36)*(IF('IN_MACRO'!$K$23=0,'IN_FIN'!$J$13,IF('IN_MACRO'!$K$23=1,'IN_FIN'!$K$13,IF('IN_MACRO'!$K$23=2,'IN_FIN'!$L$13,0))))*'ENG_SCEN'!$G$16 | L14: ='IN_FIN'!$D$13*((1-'IN_FIN'!$E$13)*'ENG_SCEN'!$L$32+'IN_FIN'!$E$13*'ENG_SCEN'!$L$36)*(IF('IN_MACRO'!$L$23=0,'IN_FIN'!$J$13,IF('IN_MACRO'!$L$23=1,'IN_FIN'!$K$13,IF('IN_MACRO'!$L$23=2,'IN_FIN'!$L$13,0))))*'ENG_SCEN'!$G$16 | M14: ='IN_FIN'!$D$13*((1-'IN_FIN'!$E$13)*'ENG_SCEN'!$M$32+'IN_FIN'!$E$13*'ENG_SCEN'!$M$36)*(IF('IN_MACRO'!$M$23=0,'IN_FIN'!$J$13,IF('IN_MACRO'!$M$23=1,'IN_FIN'!$K$13,IF('IN_MACRO'!$M$23=2,'IN_FIN'!$L$13,0))))*'ENG_SCEN'!$G$16 | N14: ='IN_FIN'!$D$13*((1-'IN_FIN'!$E$13)*'ENG_SCEN'!$N$32+'IN_FIN'!$E$13*'ENG_SCEN'!$N$36)*(IF('IN_MACRO'!$N$23=0,'IN_FIN'!$J$13,IF('IN_MACRO'!$N$23=1,'IN_FIN'!$K$13,IF('IN_MACRO'!$N$23=2,'IN_FIN'!$L$13,0))))*'ENG_SCEN'!$G$16 | O14: ='IN_FIN'!$D$13*((1-'IN_FIN'!$E$13)*'ENG_SCEN'!$O$32+'IN_FIN'!$E$13*'ENG_SCEN'!$O$36)*(IF('IN_MACRO'!$O$23=0,'IN_FIN'!$J$13,IF('IN_MACRO'!$O$23=1,'IN_FIN'!$K$13,IF('IN_MACRO'!$O$23=2,'IN_FIN'!$L$13,0))))*'ENG_SCEN'!$G$16 | P14: ='IN_FIN'!$D$13*((1-'IN_FIN'!$E$13)*'ENG_SCEN'!$P$32+'IN_FIN'!$E$13*'ENG_SCEN'!$P$36)*(IF('IN_MACRO'!$P$23=0,'IN_FIN'!$J$13,IF('IN_MACRO'!$P$23=1,'IN_FIN'!$K$13,IF('IN_MACRO'!$P$23=2,'IN_FIN'!$L$13,0))))*'ENG_SCEN'!$G$16
A15: سرمایه‌گذاری تصفیه‌خانه و تجهیزات زیست‌محیطی | B15: CAPEX.cap.5 | C15: میلیون ریال | D15: ='IN_FIN'!$D$14*((1-'IN_FIN'!$E$14)*'ENG_SCEN'!$D$32+'IN_FIN'!$E$14*'ENG_SCEN'!$D$36)*(IF('IN_MACRO'!$D$23=0,'IN_FIN'!$J$14,IF('IN_MACRO'!$D$23=1,'IN_FIN'!$K$14,IF('IN_MACRO'!$D$23=2,'IN_FIN'!$L$14,0))))*'ENG_SCEN'!$G$16 | E15: ='IN_FIN'!$D$14*((1-'IN_FIN'!$E$14)*'ENG_SCEN'!$E$32+'IN_FIN'!$E$14*'ENG_SCEN'!$E$36)*(IF('IN_MACRO'!$E$23=0,'IN_FIN'!$J$14,IF('IN_MACRO'!$E$23=1,'IN_FIN'!$K$14,IF('IN_MACRO'!$E$23=2,'IN_FIN'!$L$14,0))))*'ENG_SCEN'!$G$16 | F15: ='IN_FIN'!$D$14*((1-'IN_FIN'!$E$14)*'ENG_SCEN'!$F$32+'IN_FIN'!$E$14*'ENG_SCEN'!$F$36)*(IF('IN_MACRO'!$F$23=0,'IN_FIN'!$J$14,IF('IN_MACRO'!$F$23=1,'IN_FIN'!$K$14,IF('IN_MACRO'!$F$23=2,'IN_FIN'!$L$14,0))))*'ENG_SCEN'!$G$16 | G15: ='IN_FIN'!$D$14*((1-'IN_FIN'!$E$14)*'ENG_SCEN'!$G$32+'IN_FIN'!$E$14*'ENG_SCEN'!$G$36)*(IF('IN_MACRO'!$G$23=0,'IN_FIN'!$J$14,IF('IN_MACRO'!$G$23=1,'IN_FIN'!$K$14,IF('IN_MACRO'!$G$23=2,'IN_FIN'!$L$14,0))))*'ENG_SCEN'!$G$16 | H15: ='IN_FIN'!$D$14*((1-'IN_FIN'!$E$14)*'ENG_SCEN'!$H$32+'IN_FIN'!$E$14*'ENG_SCEN'!$H$36)*(IF('IN_MACRO'!$H$23=0,'IN_FIN'!$J$14,IF('IN_MACRO'!$H$23=1,'IN_FIN'!$K$14,IF('IN_MACRO'!$H$23=2,'IN_FIN'!$L$14,0))))*'ENG_SCEN'!$G$16 | I15: ='IN_FIN'!$D$14*((1-'IN_FIN'!$E$14)*'ENG_SCEN'!$I$32+'IN_FIN'!$E$14*'ENG_SCEN'!$I$36)*(IF('IN_MACRO'!$I$23=0,'IN_FIN'!$J$14,IF('IN_MACRO'!$I$23=1,'IN_FIN'!$K$14,IF('IN_MACRO'!$I$23=2,'IN_FIN'!$L$14,0))))*'ENG_SCEN'!$G$16 | J15: ='IN_FIN'!$D$14*((1-'IN_FIN'!$E$14)*'ENG_SCEN'!$J$32+'IN_FIN'!$E$14*'ENG_SCEN'!$J$36)*(IF('IN_MACRO'!$J$23=0,'IN_FIN'!$J$14,IF('IN_MACRO'!$J$23=1,'IN_FIN'!$K$14,IF('IN_MACRO'!$J$23=2,'IN_FIN'!$L$14,0))))*'ENG_SCEN'!$G$16 | K15: ='IN_FIN'!$D$14*((1-'IN_FIN'!$E$14)*'ENG_SCEN'!$K$32+'IN_FIN'!$E$14*'ENG_SCEN'!$K$36)*(IF('IN_MACRO'!$K$23=0,'IN_FIN'!$J$14,IF('IN_MACRO'!$K$23=1,'IN_FIN'!$K$14,IF('IN_MACRO'!$K$23=2,'IN_FIN'!$L$14,0))))*'ENG_SCEN'!$G$16 | L15: ='IN_FIN'!$D$14*((1-'IN_FIN'!$E$14)*'ENG_SCEN'!$L$32+'IN_FIN'!$E$14*'ENG_SCEN'!$L$36)*(IF('IN_MACRO'!$L$23=0,'IN_FIN'!$J$14,IF('IN_MACRO'!$L$23=1,'IN_FIN'!$K$14,IF('IN_MACRO'!$L$23=2,'IN_FIN'!$L$14,0))))*'ENG_SCEN'!$G$16 | M15: ='IN_FIN'!$D$14*((1-'IN_FIN'!$E$14)*'ENG_SCEN'!$M$32+'IN_FIN'!$E$14*'ENG_SCEN'!$M$36)*(IF('IN_MACRO'!$M$23=0,'IN_FIN'!$J$14,IF('IN_MACRO'!$M$23=1,'IN_FIN'!$K$14,IF('IN_MACRO'!$M$23=2,'IN_FIN'!$L$14,0))))*'ENG_SCEN'!$G$16 | N15: ='IN_FIN'!$D$14*((1-'IN_FIN'!$E$14)*'ENG_SCEN'!$N$32+'IN_FIN'!$E$14*'ENG_SCEN'!$N$36)*(IF('IN_MACRO'!$N$23=0,'IN_FIN'!$J$14,IF('IN_MACRO'!$N$23=1,'IN_FIN'!$K$14,IF('IN_MACRO'!$N$23=2,'IN_FIN'!$L$14,0))))*'ENG_SCEN'!$G$16 | O15: ='IN_FIN'!$D$14*((1-'IN_FIN'!$E$14)*'ENG_SCEN'!$O$32+'IN_FIN'!$E$14*'ENG_SCEN'!$O$36)*(IF('IN_MACRO'!$O$23=0,'IN_FIN'!$J$14,IF('IN_MACRO'!$O$23=1,'IN_FIN'!$K$14,IF('IN_MACRO'!$O$23=2,'IN_FIN'!$L$14,0))))*'ENG_SCEN'!$G$16 | P15: ='IN_FIN'!$D$14*((1-'IN_FIN'!$E$14)*'ENG_SCEN'!$P$32+'IN_FIN'!$E$14*'ENG_SCEN'!$P$36)*(IF('IN_MACRO'!$P$23=0,'IN_FIN'!$J$14,IF('IN_MACRO'!$P$23=1,'IN_FIN'!$K$14,IF('IN_MACRO'!$P$23=2,'IN_FIN'!$L$14,0))))*'ENG_SCEN'!$G$16
A16: سرمایه‌گذاری تجهیزات حمل‌ونقل داخلی | B16: CAPEX.cap.6 | C16: میلیون ریال | D16: ='IN_FIN'!$D$15*((1-'IN_FIN'!$E$15)*'ENG_SCEN'!$D$32+'IN_FIN'!$E$15*'ENG_SCEN'!$D$36)*(IF('IN_MACRO'!$D$23=0,'IN_FIN'!$J$15,IF('IN_MACRO'!$D$23=1,'IN_FIN'!$K$15,IF('IN_MACRO'!$D$23=2,'IN_FIN'!$L$15,0))))*'ENG_SCEN'!$G$16 | E16: ='IN_FIN'!$D$15*((1-'IN_FIN'!$E$15)*'ENG_SCEN'!$E$32+'IN_FIN'!$E$15*'ENG_SCEN'!$E$36)*(IF('IN_MACRO'!$E$23=0,'IN_FIN'!$J$15,IF('IN_MACRO'!$E$23=1,'IN_FIN'!$K$15,IF('IN_MACRO'!$E$23=2,'IN_FIN'!$L$15,0))))*'ENG_SCEN'!$G$16 | F16: ='IN_FIN'!$D$15*((1-'IN_FIN'!$E$15)*'ENG_SCEN'!$F$32+'IN_FIN'!$E$15*'ENG_SCEN'!$F$36)*(IF('IN_MACRO'!$F$23=0,'IN_FIN'!$J$15,IF('IN_MACRO'!$F$23=1,'IN_FIN'!$K$15,IF('IN_MACRO'!$F$23=2,'IN_FIN'!$L$15,0))))*'ENG_SCEN'!$G$16 | G16: ='IN_FIN'!$D$15*((1-'IN_FIN'!$E$15)*'ENG_SCEN'!$G$32+'IN_FIN'!$E$15*'ENG_SCEN'!$G$36)*(IF('IN_MACRO'!$G$23=0,'IN_FIN'!$J$15,IF('IN_MACRO'!$G$23=1,'IN_FIN'!$K$15,IF('IN_MACRO'!$G$23=2,'IN_FIN'!$L$15,0))))*'ENG_SCEN'!$G$16 | H16: ='IN_FIN'!$D$15*((1-'IN_FIN'!$E$15)*'ENG_SCEN'!$H$32+'IN_FIN'!$E$15*'ENG_SCEN'!$H$36)*(IF('IN_MACRO'!$H$23=0,'IN_FIN'!$J$15,IF('IN_MACRO'!$H$23=1,'IN_FIN'!$K$15,IF('IN_MACRO'!$H$23=2,'IN_FIN'!$L$15,0))))*'ENG_SCEN'!$G$16 | I16: ='IN_FIN'!$D$15*((1-'IN_FIN'!$E$15)*'ENG_SCEN'!$I$32+'IN_FIN'!$E$15*'ENG_SCEN'!$I$36)*(IF('IN_MACRO'!$I$23=0,'IN_FIN'!$J$15,IF('IN_MACRO'!$I$23=1,'IN_FIN'!$K$15,IF('IN_MACRO'!$I$23=2,'IN_FIN'!$L$15,0))))*'ENG_SCEN'!$G$16 | J16: ='IN_FIN'!$D$15*((1-'IN_FIN'!$E$15)*'ENG_SCEN'!$J$32+'IN_FIN'!$E$15*'ENG_SCEN'!$J$36)*(IF('IN_MACRO'!$J$23=0,'IN_FIN'!$J$15,IF('IN_MACRO'!$J$23=1,'IN_FIN'!$K$15,IF('IN_MACRO'!$J$23=2,'IN_FIN'!$L$15,0))))*'ENG_SCEN'!$G$16 | K16: ='IN_FIN'!$D$15*((1-'IN_FIN'!$E$15)*'ENG_SCEN'!$K$32+'IN_FIN'!$E$15*'ENG_SCEN'!$K$36)*(IF('IN_MACRO'!$K$23=0,'IN_FIN'!$J$15,IF('IN_MACRO'!$K$23=1,'IN_FIN'!$K$15,IF('IN_MACRO'!$K$23=2,'IN_FIN'!$L$15,0))))*'ENG_SCEN'!$G$16 | L16: ='IN_FIN'!$D$15*((1-'IN_FIN'!$E$15)*'ENG_SCEN'!$L$32+'IN_FIN'!$E$15*'ENG_SCEN'!$L$36)*(IF('IN_MACRO'!$L$23=0,'IN_FIN'!$J$15,IF('IN_MACRO'!$L$23=1,'IN_FIN'!$K$15,IF('IN_MACRO'!$L$23=2,'IN_FIN'!$L$15,0))))*'ENG_SCEN'!$G$16 | M16: ='IN_FIN'!$D$15*((1-'IN_FIN'!$E$15)*'ENG_SCEN'!$M$32+'IN_FIN'!$E$15*'ENG_SCEN'!$M$36)*(IF('IN_MACRO'!$M$23=0,'IN_FIN'!$J$15,IF('IN_MACRO'!$M$23=1,'IN_FIN'!$K$15,IF('IN_MACRO'!$M$23=2,'IN_FIN'!$L$15,0))))*'ENG_SCEN'!$G$16 | N16: ='IN_FIN'!$D$15*((1-'IN_FIN'!$E$15)*'ENG_SCEN'!$N$32+'IN_FIN'!$E$15*'ENG_SCEN'!$N$36)*(IF('IN_MACRO'!$N$23=0,'IN_FIN'!$J$15,IF('IN_MACRO'!$N$23=1,'IN_FIN'!$K$15,IF('IN_MACRO'!$N$23=2,'IN_FIN'!$L$15,0))))*'ENG_SCEN'!$G$16 | O16: ='IN_FIN'!$D$15*((1-'IN_FIN'!$E$15)*'ENG_SCEN'!$O$32+'IN_FIN'!$E$15*'ENG_SCEN'!$O$36)*(IF('IN_MACRO'!$O$23=0,'IN_FIN'!$J$15,IF('IN_MACRO'!$O$23=1,'IN_FIN'!$K$15,IF('IN_MACRO'!$O$23=2,'IN_FIN'!$L$15,0))))*'ENG_SCEN'!$G$16 | P16: ='IN_FIN'!$D$15*((1-'IN_FIN'!$E$15)*'ENG_SCEN'!$P$32+'IN_FIN'!$E$15*'ENG_SCEN'!$P$36)*(IF('IN_MACRO'!$P$23=0,'IN_FIN'!$J$15,IF('IN_MACRO'!$P$23=1,'IN_FIN'!$K$15,IF('IN_MACRO'!$P$23=2,'IN_FIN'!$L$15,0))))*'ENG_SCEN'!$G$16
A17: سرمایه‌گذاری آزمایشگاه و ابزار دقیق | B17: CAPEX.cap.7 | C17: میلیون ریال | D17: ='IN_FIN'!$D$16*((1-'IN_FIN'!$E$16)*'ENG_SCEN'!$D$32+'IN_FIN'!$E$16*'ENG_SCEN'!$D$36)*(IF('IN_MACRO'!$D$23=0,'IN_FIN'!$J$16,IF('IN_MACRO'!$D$23=1,'IN_FIN'!$K$16,IF('IN_MACRO'!$D$23=2,'IN_FIN'!$L$16,0))))*'ENG_SCEN'!$G$16 | E17: ='IN_FIN'!$D$16*((1-'IN_FIN'!$E$16)*'ENG_SCEN'!$E$32+'IN_FIN'!$E$16*'ENG_SCEN'!$E$36)*(IF('IN_MACRO'!$E$23=0,'IN_FIN'!$J$16,IF('IN_MACRO'!$E$23=1,'IN_FIN'!$K$16,IF('IN_MACRO'!$E$23=2,'IN_FIN'!$L$16,0))))*'ENG_SCEN'!$G$16 | F17: ='IN_FIN'!$D$16*((1-'IN_FIN'!$E$16)*'ENG_SCEN'!$F$32+'IN_FIN'!$E$16*'ENG_SCEN'!$F$36)*(IF('IN_MACRO'!$F$23=0,'IN_FIN'!$J$16,IF('IN_MACRO'!$F$23=1,'IN_FIN'!$K$16,IF('IN_MACRO'!$F$23=2,'IN_FIN'!$L$16,0))))*'ENG_SCEN'!$G$16 | G17: ='IN_FIN'!$D$16*((1-'IN_FIN'!$E$16)*'ENG_SCEN'!$G$32+'IN_FIN'!$E$16*'ENG_SCEN'!$G$36)*(IF('IN_MACRO'!$G$23=0,'IN_FIN'!$J$16,IF('IN_MACRO'!$G$23=1,'IN_FIN'!$K$16,IF('IN_MACRO'!$G$23=2,'IN_FIN'!$L$16,0))))*'ENG_SCEN'!$G$16 | H17: ='IN_FIN'!$D$16*((1-'IN_FIN'!$E$16)*'ENG_SCEN'!$H$32+'IN_FIN'!$E$16*'ENG_SCEN'!$H$36)*(IF('IN_MACRO'!$H$23=0,'IN_FIN'!$J$16,IF('IN_MACRO'!$H$23=1,'IN_FIN'!$K$16,IF('IN_MACRO'!$H$23=2,'IN_FIN'!$L$16,0))))*'ENG_SCEN'!$G$16 | I17: ='IN_FIN'!$D$16*((1-'IN_FIN'!$E$16)*'ENG_SCEN'!$I$32+'IN_FIN'!$E$16*'ENG_SCEN'!$I$36)*(IF('IN_MACRO'!$I$23=0,'IN_FIN'!$J$16,IF('IN_MACRO'!$I$23=1,'IN_FIN'!$K$16,IF('IN_MACRO'!$I$23=2,'IN_FIN'!$L$16,0))))*'ENG_SCEN'!$G$16 | J17: ='IN_FIN'!$D$16*((1-'IN_FIN'!$E$16)*'ENG_SCEN'!$J$32+'IN_FIN'!$E$16*'ENG_SCEN'!$J$36)*(IF('IN_MACRO'!$J$23=0,'IN_FIN'!$J$16,IF('IN_MACRO'!$J$23=1,'IN_FIN'!$K$16,IF('IN_MACRO'!$J$23=2,'IN_FIN'!$L$16,0))))*'ENG_SCEN'!$G$16 | K17: ='IN_FIN'!$D$16*((1-'IN_FIN'!$E$16)*'ENG_SCEN'!$K$32+'IN_FIN'!$E$16*'ENG_SCEN'!$K$36)*(IF('IN_MACRO'!$K$23=0,'IN_FIN'!$J$16,IF('IN_MACRO'!$K$23=1,'IN_FIN'!$K$16,IF('IN_MACRO'!$K$23=2,'IN_FIN'!$L$16,0))))*'ENG_SCEN'!$G$16 | L17: ='IN_FIN'!$D$16*((1-'IN_FIN'!$E$16)*'ENG_SCEN'!$L$32+'IN_FIN'!$E$16*'ENG_SCEN'!$L$36)*(IF('IN_MACRO'!$L$23=0,'IN_FIN'!$J$16,IF('IN_MACRO'!$L$23=1,'IN_FIN'!$K$16,IF('IN_MACRO'!$L$23=2,'IN_FIN'!$L$16,0))))*'ENG_SCEN'!$G$16 | M17: ='IN_FIN'!$D$16*((1-'IN_FIN'!$E$16)*'ENG_SCEN'!$M$32+'IN_FIN'!$E$16*'ENG_SCEN'!$M$36)*(IF('IN_MACRO'!$M$23=0,'IN_FIN'!$J$16,IF('IN_MACRO'!$M$23=1,'IN_FIN'!$K$16,IF('IN_MACRO'!$M$23=2,'IN_FIN'!$L$16,0))))*'ENG_SCEN'!$G$16 | N17: ='IN_FIN'!$D$16*((1-'IN_FIN'!$E$16)*'ENG_SCEN'!$N$32+'IN_FIN'!$E$16*'ENG_SCEN'!$N$36)*(IF('IN_MACRO'!$N$23=0,'IN_FIN'!$J$16,IF('IN_MACRO'!$N$23=1,'IN_FIN'!$K$16,IF('IN_MACRO'!$N$23=2,'IN_FIN'!$L$16,0))))*'ENG_SCEN'!$G$16 | O17: ='IN_FIN'!$D$16*((1-'IN_FIN'!$E$16)*'ENG_SCEN'!$O$32+'IN_FIN'!$E$16*'ENG_SCEN'!$O$36)*(IF('IN_MACRO'!$O$23=0,'IN_FIN'!$J$16,IF('IN_MACRO'!$O$23=1,'IN_FIN'!$K$16,IF('IN_MACRO'!$O$23=2,'IN_FIN'!$L$16,0))))*'ENG_SCEN'!$G$16 | P17: ='IN_FIN'!$D$16*((1-'IN_FIN'!$E$16)*'ENG_SCEN'!$P$32+'IN_FIN'!$E$16*'ENG_SCEN'!$P$36)*(IF('IN_MACRO'!$P$23=0,'IN_FIN'!$J$16,IF('IN_MACRO'!$P$23=1,'IN_FIN'!$K$16,IF('IN_MACRO'!$P$23=2,'IN_FIN'!$L$16,0))))*'ENG_SCEN'!$G$16
A18: سرمایه‌گذاری مهندسی، نصب و راه‌اندازی | B18: CAPEX.cap.8 | C18: میلیون ریال | D18: ='IN_FIN'!$D$17*((1-'IN_FIN'!$E$17)*'ENG_SCEN'!$D$32+'IN_FIN'!$E$17*'ENG_SCEN'!$D$36)*(IF('IN_MACRO'!$D$23=0,'IN_FIN'!$J$17,IF('IN_MACRO'!$D$23=1,'IN_FIN'!$K$17,IF('IN_MACRO'!$D$23=2,'IN_FIN'!$L$17,0))))*'ENG_SCEN'!$G$16 | E18: ='IN_FIN'!$D$17*((1-'IN_FIN'!$E$17)*'ENG_SCEN'!$E$32+'IN_FIN'!$E$17*'ENG_SCEN'!$E$36)*(IF('IN_MACRO'!$E$23=0,'IN_FIN'!$J$17,IF('IN_MACRO'!$E$23=1,'IN_FIN'!$K$17,IF('IN_MACRO'!$E$23=2,'IN_FIN'!$L$17,0))))*'ENG_SCEN'!$G$16 | F18: ='IN_FIN'!$D$17*((1-'IN_FIN'!$E$17)*'ENG_SCEN'!$F$32+'IN_FIN'!$E$17*'ENG_SCEN'!$F$36)*(IF('IN_MACRO'!$F$23=0,'IN_FIN'!$J$17,IF('IN_MACRO'!$F$23=1,'IN_FIN'!$K$17,IF('IN_MACRO'!$F$23=2,'IN_FIN'!$L$17,0))))*'ENG_SCEN'!$G$16 | G18: ='IN_FIN'!$D$17*((1-'IN_FIN'!$E$17)*'ENG_SCEN'!$G$32+'IN_FIN'!$E$17*'ENG_SCEN'!$G$36)*(IF('IN_MACRO'!$G$23=0,'IN_FIN'!$J$17,IF('IN_MACRO'!$G$23=1,'IN_FIN'!$K$17,IF('IN_MACRO'!$G$23=2,'IN_FIN'!$L$17,0))))*'ENG_SCEN'!$G$16 | H18: ='IN_FIN'!$D$17*((1-'IN_FIN'!$E$17)*'ENG_SCEN'!$H$32+'IN_FIN'!$E$17*'ENG_SCEN'!$H$36)*(IF('IN_MACRO'!$H$23=0,'IN_FIN'!$J$17,IF('IN_MACRO'!$H$23=1,'IN_FIN'!$K$17,IF('IN_MACRO'!$H$23=2,'IN_FIN'!$L$17,0))))*'ENG_SCEN'!$G$16 | I18: ='IN_FIN'!$D$17*((1-'IN_FIN'!$E$17)*'ENG_SCEN'!$I$32+'IN_FIN'!$E$17*'ENG_SCEN'!$I$36)*(IF('IN_MACRO'!$I$23=0,'IN_FIN'!$J$17,IF('IN_MACRO'!$I$23=1,'IN_FIN'!$K$17,IF('IN_MACRO'!$I$23=2,'IN_FIN'!$L$17,0))))*'ENG_SCEN'!$G$16 | J18: ='IN_FIN'!$D$17*((1-'IN_FIN'!$E$17)*'ENG_SCEN'!$J$32+'IN_FIN'!$E$17*'ENG_SCEN'!$J$36)*(IF('IN_MACRO'!$J$23=0,'IN_FIN'!$J$17,IF('IN_MACRO'!$J$23=1,'IN_FIN'!$K$17,IF('IN_MACRO'!$J$23=2,'IN_FIN'!$L$17,0))))*'ENG_SCEN'!$G$16 | K18: ='IN_FIN'!$D$17*((1-'IN_FIN'!$E$17)*'ENG_SCEN'!$K$32+'IN_FIN'!$E$17*'ENG_SCEN'!$K$36)*(IF('IN_MACRO'!$K$23=0,'IN_FIN'!$J$17,IF('IN_MACRO'!$K$23=1,'IN_FIN'!$K$17,IF('IN_MACRO'!$K$23=2,'IN_FIN'!$L$17,0))))*'ENG_SCEN'!$G$16 | L18: ='IN_FIN'!$D$17*((1-'IN_FIN'!$E$17)*'ENG_SCEN'!$L$32+'IN_FIN'!$E$17*'ENG_SCEN'!$L$36)*(IF('IN_MACRO'!$L$23=0,'IN_FIN'!$J$17,IF('IN_MACRO'!$L$23=1,'IN_FIN'!$K$17,IF('IN_MACRO'!$L$23=2,'IN_FIN'!$L$17,0))))*'ENG_SCEN'!$G$16 | M18: ='IN_FIN'!$D$17*((1-'IN_FIN'!$E$17)*'ENG_SCEN'!$M$32+'IN_FIN'!$E$17*'ENG_SCEN'!$M$36)*(IF('IN_MACRO'!$M$23=0,'IN_FIN'!$J$17,IF('IN_MACRO'!$M$23=1,'IN_FIN'!$K$17,IF('IN_MACRO'!$M$23=2,'IN_FIN'!$L$17,0))))*'ENG_SCEN'!$G$16 | N18: ='IN_FIN'!$D$17*((1-'IN_FIN'!$E$17)*'ENG_SCEN'!$N$32+'IN_FIN'!$E$17*'ENG_SCEN'!$N$36)*(IF('IN_MACRO'!$N$23=0,'IN_FIN'!$J$17,IF('IN_MACRO'!$N$23=1,'IN_FIN'!$K$17,IF('IN_MACRO'!$N$23=2,'IN_FIN'!$L$17,0))))*'ENG_SCEN'!$G$16 | O18: ='IN_FIN'!$D$17*((1-'IN_FIN'!$E$17)*'ENG_SCEN'!$O$32+'IN_FIN'!$E$17*'ENG_SCEN'!$O$36)*(IF('IN_MACRO'!$O$23=0,'IN_FIN'!$J$17,IF('IN_MACRO'!$O$23=1,'IN_FIN'!$K$17,IF('IN_MACRO'!$O$23=2,'IN_FIN'!$L$17,0))))*'ENG_SCEN'!$G$16 | P18: ='IN_FIN'!$D$17*((1-'IN_FIN'!$E$17)*'ENG_SCEN'!$P$32+'IN_FIN'!$E$17*'ENG_SCEN'!$P$36)*(IF('IN_MACRO'!$P$23=0,'IN_FIN'!$J$17,IF('IN_MACRO'!$P$23=1,'IN_FIN'!$K$17,IF('IN_MACRO'!$P$23=2,'IN_FIN'!$L$17,0))))*'ENG_SCEN'!$G$16
A19: سرمایه‌گذاری هزینه‌های پیش از بهره‌برداری | B19: CAPEX.cap.9 | C19: میلیون ریال | D19: ='IN_FIN'!$D$18*((1-'IN_FIN'!$E$18)*'ENG_SCEN'!$D$32+'IN_FIN'!$E$18*'ENG_SCEN'!$D$36)*(IF('IN_MACRO'!$D$23=0,'IN_FIN'!$J$18,IF('IN_MACRO'!$D$23=1,'IN_FIN'!$K$18,IF('IN_MACRO'!$D$23=2,'IN_FIN'!$L$18,0))))*'ENG_SCEN'!$G$16 | E19: ='IN_FIN'!$D$18*((1-'IN_FIN'!$E$18)*'ENG_SCEN'!$E$32+'IN_FIN'!$E$18*'ENG_SCEN'!$E$36)*(IF('IN_MACRO'!$E$23=0,'IN_FIN'!$J$18,IF('IN_MACRO'!$E$23=1,'IN_FIN'!$K$18,IF('IN_MACRO'!$E$23=2,'IN_FIN'!$L$18,0))))*'ENG_SCEN'!$G$16 | F19: ='IN_FIN'!$D$18*((1-'IN_FIN'!$E$18)*'ENG_SCEN'!$F$32+'IN_FIN'!$E$18*'ENG_SCEN'!$F$36)*(IF('IN_MACRO'!$F$23=0,'IN_FIN'!$J$18,IF('IN_MACRO'!$F$23=1,'IN_FIN'!$K$18,IF('IN_MACRO'!$F$23=2,'IN_FIN'!$L$18,0))))*'ENG_SCEN'!$G$16 | G19: ='IN_FIN'!$D$18*((1-'IN_FIN'!$E$18)*'ENG_SCEN'!$G$32+'IN_FIN'!$E$18*'ENG_SCEN'!$G$36)*(IF('IN_MACRO'!$G$23=0,'IN_FIN'!$J$18,IF('IN_MACRO'!$G$23=1,'IN_FIN'!$K$18,IF('IN_MACRO'!$G$23=2,'IN_FIN'!$L$18,0))))*'ENG_SCEN'!$G$16 | H19: ='IN_FIN'!$D$18*((1-'IN_FIN'!$E$18)*'ENG_SCEN'!$H$32+'IN_FIN'!$E$18*'ENG_SCEN'!$H$36)*(IF('IN_MACRO'!$H$23=0,'IN_FIN'!$J$18,IF('IN_MACRO'!$H$23=1,'IN_FIN'!$K$18,IF('IN_MACRO'!$H$23=2,'IN_FIN'!$L$18,0))))*'ENG_SCEN'!$G$16 | I19: ='IN_FIN'!$D$18*((1-'IN_FIN'!$E$18)*'ENG_SCEN'!$I$32+'IN_FIN'!$E$18*'ENG_SCEN'!$I$36)*(IF('IN_MACRO'!$I$23=0,'IN_FIN'!$J$18,IF('IN_MACRO'!$I$23=1,'IN_FIN'!$K$18,IF('IN_MACRO'!$I$23=2,'IN_FIN'!$L$18,0))))*'ENG_SCEN'!$G$16 | J19: ='IN_FIN'!$D$18*((1-'IN_FIN'!$E$18)*'ENG_SCEN'!$J$32+'IN_FIN'!$E$18*'ENG_SCEN'!$J$36)*(IF('IN_MACRO'!$J$23=0,'IN_FIN'!$J$18,IF('IN_MACRO'!$J$23=1,'IN_FIN'!$K$18,IF('IN_MACRO'!$J$23=2,'IN_FIN'!$L$18,0))))*'ENG_SCEN'!$G$16 | K19: ='IN_FIN'!$D$18*((1-'IN_FIN'!$E$18)*'ENG_SCEN'!$K$32+'IN_FIN'!$E$18*'ENG_SCEN'!$K$36)*(IF('IN_MACRO'!$K$23=0,'IN_FIN'!$J$18,IF('IN_MACRO'!$K$23=1,'IN_FIN'!$K$18,IF('IN_MACRO'!$K$23=2,'IN_FIN'!$L$18,0))))*'ENG_SCEN'!$G$16 | L19: ='IN_FIN'!$D$18*((1-'IN_FIN'!$E$18)*'ENG_SCEN'!$L$32+'IN_FIN'!$E$18*'ENG_SCEN'!$L$36)*(IF('IN_MACRO'!$L$23=0,'IN_FIN'!$J$18,IF('IN_MACRO'!$L$23=1,'IN_FIN'!$K$18,IF('IN_MACRO'!$L$23=2,'IN_FIN'!$L$18,0))))*'ENG_SCEN'!$G$16 | M19: ='IN_FIN'!$D$18*((1-'IN_FIN'!$E$18)*'ENG_SCEN'!$M$32+'IN_FIN'!$E$18*'ENG_SCEN'!$M$36)*(IF('IN_MACRO'!$M$23=0,'IN_FIN'!$J$18,IF('IN_MACRO'!$M$23=1,'IN_FIN'!$K$18,IF('IN_MACRO'!$M$23=2,'IN_FIN'!$L$18,0))))*'ENG_SCEN'!$G$16 | N19: ='IN_FIN'!$D$18*((1-'IN_FIN'!$E$18)*'ENG_SCEN'!$N$32+'IN_FIN'!$E$18*'ENG_SCEN'!$N$36)*(IF('IN_MACRO'!$N$23=0,'IN_FIN'!$J$18,IF('IN_MACRO'!$N$23=1,'IN_FIN'!$K$18,IF('IN_MACRO'!$N$23=2,'IN_FIN'!$L$18,0))))*'ENG_SCEN'!$G$16 | O19: ='IN_FIN'!$D$18*((1-'IN_FIN'!$E$18)*'ENG_SCEN'!$O$32+'IN_FIN'!$E$18*'ENG_SCEN'!$O$36)*(IF('IN_MACRO'!$O$23=0,'IN_FIN'!$J$18,IF('IN_MACRO'!$O$23=1,'IN_FIN'!$K$18,IF('IN_MACRO'!$O$23=2,'IN_FIN'!$L$18,0))))*'ENG_SCEN'!$G$16 | P19: ='IN_FIN'!$D$18*((1-'IN_FIN'!$E$18)*'ENG_SCEN'!$P$32+'IN_FIN'!$E$18*'ENG_SCEN'!$P$36)*(IF('IN_MACRO'!$P$23=0,'IN_FIN'!$J$18,IF('IN_MACRO'!$P$23=1,'IN_FIN'!$K$18,IF('IN_MACRO'!$P$23=2,'IN_FIN'!$L$18,0))))*'ENG_SCEN'!$G$16
A20: سرمایه‌گذاری ذخیره احتیاطی فیزیکی | B20: CAPEX.cap.10 | C20: میلیون ریال | D20: ='IN_FIN'!$D$19*((1-'IN_FIN'!$E$19)*'ENG_SCEN'!$D$32+'IN_FIN'!$E$19*'ENG_SCEN'!$D$36)*(IF('IN_MACRO'!$D$23=0,'IN_FIN'!$J$19,IF('IN_MACRO'!$D$23=1,'IN_FIN'!$K$19,IF('IN_MACRO'!$D$23=2,'IN_FIN'!$L$19,0))))*'ENG_SCEN'!$G$16 | E20: ='IN_FIN'!$D$19*((1-'IN_FIN'!$E$19)*'ENG_SCEN'!$E$32+'IN_FIN'!$E$19*'ENG_SCEN'!$E$36)*(IF('IN_MACRO'!$E$23=0,'IN_FIN'!$J$19,IF('IN_MACRO'!$E$23=1,'IN_FIN'!$K$19,IF('IN_MACRO'!$E$23=2,'IN_FIN'!$L$19,0))))*'ENG_SCEN'!$G$16 | F20: ='IN_FIN'!$D$19*((1-'IN_FIN'!$E$19)*'ENG_SCEN'!$F$32+'IN_FIN'!$E$19*'ENG_SCEN'!$F$36)*(IF('IN_MACRO'!$F$23=0,'IN_FIN'!$J$19,IF('IN_MACRO'!$F$23=1,'IN_FIN'!$K$19,IF('IN_MACRO'!$F$23=2,'IN_FIN'!$L$19,0))))*'ENG_SCEN'!$G$16 | G20: ='IN_FIN'!$D$19*((1-'IN_FIN'!$E$19)*'ENG_SCEN'!$G$32+'IN_FIN'!$E$19*'ENG_SCEN'!$G$36)*(IF('IN_MACRO'!$G$23=0,'IN_FIN'!$J$19,IF('IN_MACRO'!$G$23=1,'IN_FIN'!$K$19,IF('IN_MACRO'!$G$23=2,'IN_FIN'!$L$19,0))))*'ENG_SCEN'!$G$16 | H20: ='IN_FIN'!$D$19*((1-'IN_FIN'!$E$19)*'ENG_SCEN'!$H$32+'IN_FIN'!$E$19*'ENG_SCEN'!$H$36)*(IF('IN_MACRO'!$H$23=0,'IN_FIN'!$J$19,IF('IN_MACRO'!$H$23=1,'IN_FIN'!$K$19,IF('IN_MACRO'!$H$23=2,'IN_FIN'!$L$19,0))))*'ENG_SCEN'!$G$16 | I20: ='IN_FIN'!$D$19*((1-'IN_FIN'!$E$19)*'ENG_SCEN'!$I$32+'IN_FIN'!$E$19*'ENG_SCEN'!$I$36)*(IF('IN_MACRO'!$I$23=0,'IN_FIN'!$J$19,IF('IN_MACRO'!$I$23=1,'IN_FIN'!$K$19,IF('IN_MACRO'!$I$23=2,'IN_FIN'!$L$19,0))))*'ENG_SCEN'!$G$16 | J20: ='IN_FIN'!$D$19*((1-'IN_FIN'!$E$19)*'ENG_SCEN'!$J$32+'IN_FIN'!$E$19*'ENG_SCEN'!$J$36)*(IF('IN_MACRO'!$J$23=0,'IN_FIN'!$J$19,IF('IN_MACRO'!$J$23=1,'IN_FIN'!$K$19,IF('IN_MACRO'!$J$23=2,'IN_FIN'!$L$19,0))))*'ENG_SCEN'!$G$16 | K20: ='IN_FIN'!$D$19*((1-'IN_FIN'!$E$19)*'ENG_SCEN'!$K$32+'IN_FIN'!$E$19*'ENG_SCEN'!$K$36)*(IF('IN_MACRO'!$K$23=0,'IN_FIN'!$J$19,IF('IN_MACRO'!$K$23=1,'IN_FIN'!$K$19,IF('IN_MACRO'!$K$23=2,'IN_FIN'!$L$19,0))))*'ENG_SCEN'!$G$16 | L20: ='IN_FIN'!$D$19*((1-'IN_FIN'!$E$19)*'ENG_SCEN'!$L$32+'IN_FIN'!$E$19*'ENG_SCEN'!$L$36)*(IF('IN_MACRO'!$L$23=0,'IN_FIN'!$J$19,IF('IN_MACRO'!$L$23=1,'IN_FIN'!$K$19,IF('IN_MACRO'!$L$23=2,'IN_FIN'!$L$19,0))))*'ENG_SCEN'!$G$16 | M20: ='IN_FIN'!$D$19*((1-'IN_FIN'!$E$19)*'ENG_SCEN'!$M$32+'IN_FIN'!$E$19*'ENG_SCEN'!$M$36)*(IF('IN_MACRO'!$M$23=0,'IN_FIN'!$J$19,IF('IN_MACRO'!$M$23=1,'IN_FIN'!$K$19,IF('IN_MACRO'!$M$23=2,'IN_FIN'!$L$19,0))))*'ENG_SCEN'!$G$16 | N20: ='IN_FIN'!$D$19*((1-'IN_FIN'!$E$19)*'ENG_SCEN'!$N$32+'IN_FIN'!$E$19*'ENG_SCEN'!$N$36)*(IF('IN_MACRO'!$N$23=0,'IN_FIN'!$J$19,IF('IN_MACRO'!$N$23=1,'IN_FIN'!$K$19,IF('IN_MACRO'!$N$23=2,'IN_FIN'!$L$19,0))))*'ENG_SCEN'!$G$16 | O20: ='IN_FIN'!$D$19*((1-'IN_FIN'!$E$19)*'ENG_SCEN'!$O$32+'IN_FIN'!$E$19*'ENG_SCEN'!$O$36)*(IF('IN_MACRO'!$O$23=0,'IN_FIN'!$J$19,IF('IN_MACRO'!$O$23=1,'IN_FIN'!$K$19,IF('IN_MACRO'!$O$23=2,'IN_FIN'!$L$19,0))))*'ENG_SCEN'!$G$16 | P20: ='IN_FIN'!$D$19*((1-'IN_FIN'!$E$19)*'ENG_SCEN'!$P$32+'IN_FIN'!$E$19*'ENG_SCEN'!$P$36)*(IF('IN_MACRO'!$P$23=0,'IN_FIN'!$J$19,IF('IN_MACRO'!$P$23=1,'IN_FIN'!$K$19,IF('IN_MACRO'!$P$23=2,'IN_FIN'!$L$19,0))))*'ENG_SCEN'!$G$16
A21: جمع سرمایه‌گذاری ثابت | B21: CAPEX.cap_total | C21: میلیون ریال | D21: ='ENG_CAPEX'!$D$10+'ENG_CAPEX'!$D$11+'ENG_CAPEX'!$D$12+'ENG_CAPEX'!$D$13+'ENG_CAPEX'!$D$14+'ENG_CAPEX'!$D$15+'ENG_CAPEX'!$D$16+'ENG_CAPEX'!$D$17+'ENG_CAPEX'!$D$18+'ENG_CAPEX'!$D$19+'ENG_CAPEX'!$D$20 | E21: ='ENG_CAPEX'!$E$10+'ENG_CAPEX'!$E$11+'ENG_CAPEX'!$E$12+'ENG_CAPEX'!$E$13+'ENG_CAPEX'!$E$14+'ENG_CAPEX'!$E$15+'ENG_CAPEX'!$E$16+'ENG_CAPEX'!$E$17+'ENG_CAPEX'!$E$18+'ENG_CAPEX'!$E$19+'ENG_CAPEX'!$E$20 | F21: ='ENG_CAPEX'!$F$10+'ENG_CAPEX'!$F$11+'ENG_CAPEX'!$F$12+'ENG_CAPEX'!$F$13+'ENG_CAPEX'!$F$14+'ENG_CAPEX'!$F$15+'ENG_CAPEX'!$F$16+'ENG_CAPEX'!$F$17+'ENG_CAPEX'!$F$18+'ENG_CAPEX'!$F$19+'ENG_CAPEX'!$F$20 | G21: ='ENG_CAPEX'!$G$10+'ENG_CAPEX'!$G$11+'ENG_CAPEX'!$G$12+'ENG_CAPEX'!$G$13+'ENG_CAPEX'!$G$14+'ENG_CAPEX'!$G$15+'ENG_CAPEX'!$G$16+'ENG_CAPEX'!$G$17+'ENG_CAPEX'!$G$18+'ENG_CAPEX'!$G$19+'ENG_CAPEX'!$G$20 | H21: ='ENG_CAPEX'!$H$10+'ENG_CAPEX'!$H$11+'ENG_CAPEX'!$H$12+'ENG_CAPEX'!$H$13+'ENG_CAPEX'!$H$14+'ENG_CAPEX'!$H$15+'ENG_CAPEX'!$H$16+'ENG_CAPEX'!$H$17+'ENG_CAPEX'!$H$18+'ENG_CAPEX'!$H$19+'ENG_CAPEX'!$H$20 | I21: ='ENG_CAPEX'!$I$10+'ENG_CAPEX'!$I$11+'ENG_CAPEX'!$I$12+'ENG_CAPEX'!$I$13+'ENG_CAPEX'!$I$14+'ENG_CAPEX'!$I$15+'ENG_CAPEX'!$I$16+'ENG_CAPEX'!$I$17+'ENG_CAPEX'!$I$18+'ENG_CAPEX'!$I$19+'ENG_CAPEX'!$I$20 | J21: ='ENG_CAPEX'!$J$10+'ENG_CAPEX'!$J$11+'ENG_CAPEX'!$J$12+'ENG_CAPEX'!$J$13+'ENG_CAPEX'!$J$14+'ENG_CAPEX'!$J$15+'ENG_CAPEX'!$J$16+'ENG_CAPEX'!$J$17+'ENG_CAPEX'!$J$18+'ENG_CAPEX'!$J$19+'ENG_CAPEX'!$J$20 | K21: ='ENG_CAPEX'!$K$10+'ENG_CAPEX'!$K$11+'ENG_CAPEX'!$K$12+'ENG_CAPEX'!$K$13+'ENG_CAPEX'!$K$14+'ENG_CAPEX'!$K$15+'ENG_CAPEX'!$K$16+'ENG_CAPEX'!$K$17+'ENG_CAPEX'!$K$18+'ENG_CAPEX'!$K$19+'ENG_CAPEX'!$K$20 | L21: ='ENG_CAPEX'!$L$10+'ENG_CAPEX'!$L$11+'ENG_CAPEX'!$L$12+'ENG_CAPEX'!$L$13+'ENG_CAPEX'!$L$14+'ENG_CAPEX'!$L$15+'ENG_CAPEX'!$L$16+'ENG_CAPEX'!$L$17+'ENG_CAPEX'!$L$18+'ENG_CAPEX'!$L$19+'ENG_CAPEX'!$L$20 | M21: ='ENG_CAPEX'!$M$10+'ENG_CAPEX'!$M$11+'ENG_CAPEX'!$M$12+'ENG_CAPEX'!$M$13+'ENG_CAPEX'!$M$14+'ENG_CAPEX'!$M$15+'ENG_CAPEX'!$M$16+'ENG_CAPEX'!$M$17+'ENG_CAPEX'!$M$18+'ENG_CAPEX'!$M$19+'ENG_CAPEX'!$M$20 | N21: ='ENG_CAPEX'!$N$10+'ENG_CAPEX'!$N$11+'ENG_CAPEX'!$N$12+'ENG_CAPEX'!$N$13+'ENG_CAPEX'!$N$14+'ENG_CAPEX'!$N$15+'ENG_CAPEX'!$N$16+'ENG_CAPEX'!$N$17+'ENG_CAPEX'!$N$18+'ENG_CAPEX'!$N$19+'ENG_CAPEX'!$N$20 | O21: ='ENG_CAPEX'!$O$10+'ENG_CAPEX'!$O$11+'ENG_CAPEX'!$O$12+'ENG_CAPEX'!$O$13+'ENG_CAPEX'!$O$14+'ENG_CAPEX'!$O$15+'ENG_CAPEX'!$O$16+'ENG_CAPEX'!$O$17+'ENG_CAPEX'!$O$18+'ENG_CAPEX'!$O$19+'ENG_CAPEX'!$O$20 | P21: ='ENG_CAPEX'!$P$10+'ENG_CAPEX'!$P$11+'ENG_CAPEX'!$P$12+'ENG_CAPEX'!$P$13+'ENG_CAPEX'!$P$14+'ENG_CAPEX'!$P$15+'ENG_CAPEX'!$P$16+'ENG_CAPEX'!$P$17+'ENG_CAPEX'!$P$18+'ENG_CAPEX'!$P$19+'ENG_CAPEX'!$P$20
A22: مانده تجمعی تزریق سرمایه‌گذاری | B22: CAPEX.cap_cum | C22: میلیون ریال | D22: ='ENG_CAPEX'!$D$21 | E22: ='ENG_CAPEX'!$D$22+'ENG_CAPEX'!$E$21 | F22: ='ENG_CAPEX'!$E$22+'ENG_CAPEX'!$F$21 | G22: ='ENG_CAPEX'!$F$22+'ENG_CAPEX'!$G$21 | H22: ='ENG_CAPEX'!$G$22+'ENG_CAPEX'!$H$21 | I22: ='ENG_CAPEX'!$H$22+'ENG_CAPEX'!$I$21 | J22: ='ENG_CAPEX'!$I$22+'ENG_CAPEX'!$J$21 | K22: ='ENG_CAPEX'!$J$22+'ENG_CAPEX'!$K$21 | L22: ='ENG_CAPEX'!$K$22+'ENG_CAPEX'!$L$21 | M22: ='ENG_CAPEX'!$L$22+'ENG_CAPEX'!$M$21 | N22: ='ENG_CAPEX'!$M$22+'ENG_CAPEX'!$N$21 | O22: ='ENG_CAPEX'!$N$22+'ENG_CAPEX'!$O$21 | P22: ='ENG_CAPEX'!$O$22+'ENG_CAPEX'!$P$21
A23: سهم ارزیِ وزنیِ CAPEX | B23: CAPEX.fxsh | C23: درصد | D23: =IFERROR((('IN_FIN'!$D$9*'IN_FIN'!$E$9)+('IN_FIN'!$D$10*'IN_FIN'!$E$10)+('IN_FIN'!$D$11*'IN_FIN'!$E$11)+('IN_FIN'!$D$12*'IN_FIN'!$E$12)+('IN_FIN'!$D$13*'IN_FIN'!$E$13)+('IN_FIN'!$D$14*'IN_FIN'!$E$14)+('IN_FIN'!$D$15*'IN_FIN'!$E$15)+('IN_FIN'!$D$16*'IN_FIN'!$E$16)+('IN_FIN'!$D$17*'IN_FIN'!$E$17)+('IN_FIN'!$D$18*'IN_FIN'!$E$18)+('IN_FIN'!$D$19*'IN_FIN'!$E$19))/('IN_FIN'!$D$9+'IN_FIN'!$D$10+'IN_FIN'!$D$11+'IN_FIN'!$D$12+'IN_FIN'!$D$13+'IN_FIN'!$D$14+'IN_FIN'!$D$15+'IN_FIN'!$D$16+'IN_FIN'!$D$17+'IN_FIN'!$D$18+'IN_FIN'!$D$19),0) | E23: =IFERROR((('IN_FIN'!$D$9*'IN_FIN'!$E$9)+('IN_FIN'!$D$10*'IN_FIN'!$E$10)+('IN_FIN'!$D$11*'IN_FIN'!$E$11)+('IN_FIN'!$D$12*'IN_FIN'!$E$12)+('IN_FIN'!$D$13*'IN_FIN'!$E$13)+('IN_FIN'!$D$14*'IN_FIN'!$E$14)+('IN_FIN'!$D$15*'IN_FIN'!$E$15)+('IN_FIN'!$D$16*'IN_FIN'!$E$16)+('IN_FIN'!$D$17*'IN_FIN'!$E$17)+('IN_FIN'!$D$18*'IN_FIN'!$E$18)+('IN_FIN'!$D$19*'IN_FIN'!$E$19))/('IN_FIN'!$D$9+'IN_FIN'!$D$10+'IN_FIN'!$D$11+'IN_FIN'!$D$12+'IN_FIN'!$D$13+'IN_FIN'!$D$14+'IN_FIN'!$D$15+'IN_FIN'!$D$16+'IN_FIN'!$D$17+'IN_FIN'!$D$18+'IN_FIN'!$D$19),0) | F23: =IFERROR((('IN_FIN'!$D$9*'IN_FIN'!$E$9)+('IN_FIN'!$D$10*'IN_FIN'!$E$10)+('IN_FIN'!$D$11*'IN_FIN'!$E$11)+('IN_FIN'!$D$12*'IN_FIN'!$E$12)+('IN_FIN'!$D$13*'IN_FIN'!$E$13)+('IN_FIN'!$D$14*'IN_FIN'!$E$14)+('IN_FIN'!$D$15*'IN_FIN'!$E$15)+('IN_FIN'!$D$16*'IN_FIN'!$E$16)+('IN_FIN'!$D$17*'IN_FIN'!$E$17)+('IN_FIN'!$D$18*'IN_FIN'!$E$18)+('IN_FIN'!$D$19*'IN_FIN'!$E$19))/('IN_FIN'!$D$9+'IN_FIN'!$D$10+'IN_FIN'!$D$11+'IN_FIN'!$D$12+'IN_FIN'!$D$13+'IN_FIN'!$D$14+'IN_FIN'!$D$15+'IN_FIN'!$D$16+'IN_FIN'!$D$17+'IN_FIN'!$D$18+'IN_FIN'!$D$19),0) | G23: =IFERROR((('IN_FIN'!$D$9*'IN_FIN'!$E$9)+('IN_FIN'!$D$10*'IN_FIN'!$E$10)+('IN_FIN'!$D$11*'IN_FIN'!$E$11)+('IN_FIN'!$D$12*'IN_FIN'!$E$12)+('IN_FIN'!$D$13*'IN_FIN'!$E$13)+('IN_FIN'!$D$14*'IN_FIN'!$E$14)+('IN_FIN'!$D$15*'IN_FIN'!$E$15)+('IN_FIN'!$D$16*'IN_FIN'!$E$16)+('IN_FIN'!$D$17*'IN_FIN'!$E$17)+('IN_FIN'!$D$18*'IN_FIN'!$E$18)+('IN_FIN'!$D$19*'IN_FIN'!$E$19))/('IN_FIN'!$D$9+'IN_FIN'!$D$10+'IN_FIN'!$D$11+'IN_FIN'!$D$12+'IN_FIN'!$D$13+'IN_FIN'!$D$14+'IN_FIN'!$D$15+'IN_FIN'!$D$16+'IN_FIN'!$D$17+'IN_FIN'!$D$18+'IN_FIN'!$D$19),0) | H23: =IFERROR((('IN_FIN'!$D$9*'IN_FIN'!$E$9)+('IN_FIN'!$D$10*'IN_FIN'!$E$10)+('IN_FIN'!$D$11*'IN_FIN'!$E$11)+('IN_FIN'!$D$12*'IN_FIN'!$E$12)+('IN_FIN'!$D$13*'IN_FIN'!$E$13)+('IN_FIN'!$D$14*'IN_FIN'!$E$14)+('IN_FIN'!$D$15*'IN_FIN'!$E$15)+('IN_FIN'!$D$16*'IN_FIN'!$E$16)+('IN_FIN'!$D$17*'IN_FIN'!$E$17)+('IN_FIN'!$D$18*'IN_FIN'!$E$18)+('IN_FIN'!$D$19*'IN_FIN'!$E$19))/('IN_FIN'!$D$9+'IN_FIN'!$D$10+'IN_FIN'!$D$11+'IN_FIN'!$D$12+'IN_FIN'!$D$13+'IN_FIN'!$D$14+'IN_FIN'!$D$15+'IN_FIN'!$D$16+'IN_FIN'!$D$17+'IN_FIN'!$D$18+'IN_FIN'!$D$19),0) | I23: =IFERROR((('IN_FIN'!$D$9*'IN_FIN'!$E$9)+('IN_FIN'!$D$10*'IN_FIN'!$E$10)+('IN_FIN'!$D$11*'IN_FIN'!$E$11)+('IN_FIN'!$D$12*'IN_FIN'!$E$12)+('IN_FIN'!$D$13*'IN_FIN'!$E$13)+('IN_FIN'!$D$14*'IN_FIN'!$E$14)+('IN_FIN'!$D$15*'IN_FIN'!$E$15)+('IN_FIN'!$D$16*'IN_FIN'!$E$16)+('IN_FIN'!$D$17*'IN_FIN'!$E$17)+('IN_FIN'!$D$18*'IN_FIN'!$E$18)+('IN_FIN'!$D$19*'IN_FIN'!$E$19))/('IN_FIN'!$D$9+'IN_FIN'!$D$10+'IN_FIN'!$D$11+'IN_FIN'!$D$12+'IN_FIN'!$D$13+'IN_FIN'!$D$14+'IN_FIN'!$D$15+'IN_FIN'!$D$16+'IN_FIN'!$D$17+'IN_FIN'!$D$18+'IN_FIN'!$D$19),0) | J23: =IFERROR((('IN_FIN'!$D$9*'IN_FIN'!$E$9)+('IN_FIN'!$D$10*'IN_FIN'!$E$10)+('IN_FIN'!$D$11*'IN_FIN'!$E$11)+('IN_FIN'!$D$12*'IN_FIN'!$E$12)+('IN_FIN'!$D$13*'IN_FIN'!$E$13)+('IN_FIN'!$D$14*'IN_FIN'!$E$14)+('IN_FIN'!$D$15*'IN_FIN'!$E$15)+('IN_FIN'!$D$16*'IN_FIN'!$E$16)+('IN_FIN'!$D$17*'IN_FIN'!$E$17)+('IN_FIN'!$D$18*'IN_FIN'!$E$18)+('IN_FIN'!$D$19*'IN_FIN'!$E$19))/('IN_FIN'!$D$9+'IN_FIN'!$D$10+'IN_FIN'!$D$11+'IN_FIN'!$D$12+'IN_FIN'!$D$13+'IN_FIN'!$D$14+'IN_FIN'!$D$15+'IN_FIN'!$D$16+'IN_FIN'!$D$17+'IN_FIN'!$D$18+'IN_FIN'!$D$19),0) | K23: =IFERROR((('IN_FIN'!$D$9*'IN_FIN'!$E$9)+('IN_FIN'!$D$10*'IN_FIN'!$E$10)+('IN_FIN'!$D$11*'IN_FIN'!$E$11)+('IN_FIN'!$D$12*'IN_FIN'!$E$12)+('IN_FIN'!$D$13*'IN_FIN'!$E$13)+('IN_FIN'!$D$14*'IN_FIN'!$E$14)+('IN_FIN'!$D$15*'IN_FIN'!$E$15)+('IN_FIN'!$D$16*'IN_FIN'!$E$16)+('IN_FIN'!$D$17*'IN_FIN'!$E$17)+('IN_FIN'!$D$18*'IN_FIN'!$E$18)+('IN_FIN'!$D$19*'IN_FIN'!$E$19))/('IN_FIN'!$D$9+'IN_FIN'!$D$10+'IN_FIN'!$D$11+'IN_FIN'!$D$12+'IN_FIN'!$D$13+'IN_FIN'!$D$14+'IN_FIN'!$D$15+'IN_FIN'!$D$16+'IN_FIN'!$D$17+'IN_FIN'!$D$18+'IN_FIN'!$D$19),0) | ... P23: =IFERROR((('IN_FIN'!$D$9*'IN_FIN'!$E$9)+('IN_FIN'!$D$10*'IN_FIN'!$E$10)+('IN_FIN'!$D$11*'IN_FIN'!$E$11)+('IN_FIN'!$D$12*'IN_FIN'!$E$12)+('IN_FIN'!$D$13*'IN_FIN'!$E$13)+('IN_FIN'!$D$14*'IN_FIN'!$E$14)+('IN_FIN'!$D$15*'IN_FIN'!$E$15)+('IN_FIN'!$D$16*'IN_FIN'!$E$16)+('IN_FIN'!$D$17*'IN_FIN'!$E$17)+('IN_FIN'!$D$18*'IN_FIN'!$E$18)+('IN_FIN'!$D$19*'IN_FIN'!$E$19))/('IN_FIN'!$D$9+'IN_FIN'!$D$10+'IN_FIN'!$D$11+'IN_FIN'!$D$12+'IN_FIN'!$D$13+'IN_FIN'!$D$14+'IN_FIN'!$D$15+'IN_FIN'!$D$16+'IN_FIN'!$D$17+'IN_FIN'!$D$18+'IN_FIN'!$D$19),0)
A25: ب) سود سرمایه‌گذاری حین ساخت (IDC)
A26: مانده تسهیلات در ابتدای دوره (دوره ساخت) | B26: CAPEX.debt_open | C26: میلیون ریال | D26: ='IN_FIN'!$D$24*(0) | E26: ='IN_FIN'!$D$24*('ENG_CAPEX'!$D$22+'ENG_CAPEX'!$D$28) | F26: ='IN_FIN'!$D$24*('ENG_CAPEX'!$E$22+'ENG_CAPEX'!$E$28) | G26: ='IN_FIN'!$D$24*('ENG_CAPEX'!$F$22+'ENG_CAPEX'!$F$28) | H26: ='IN_FIN'!$D$24*('ENG_CAPEX'!$G$22+'ENG_CAPEX'!$G$28) | I26: ='IN_FIN'!$D$24*('ENG_CAPEX'!$H$22+'ENG_CAPEX'!$H$28) | J26: ='IN_FIN'!$D$24*('ENG_CAPEX'!$I$22+'ENG_CAPEX'!$I$28) | K26: ='IN_FIN'!$D$24*('ENG_CAPEX'!$J$22+'ENG_CAPEX'!$J$28) | L26: ='IN_FIN'!$D$24*('ENG_CAPEX'!$K$22+'ENG_CAPEX'!$K$28) | M26: ='IN_FIN'!$D$24*('ENG_CAPEX'!$L$22+'ENG_CAPEX'!$L$28) | N26: ='IN_FIN'!$D$24*('ENG_CAPEX'!$M$22+'ENG_CAPEX'!$M$28) | O26: ='IN_FIN'!$D$24*('ENG_CAPEX'!$N$22+'ENG_CAPEX'!$N$28) | P26: ='IN_FIN'!$D$24*('ENG_CAPEX'!$O$22+'ENG_CAPEX'!$O$28)
A27: IDC (سرمایه‌ای‌شده) | B27: CAPEX.idc | C27: میلیون ریال | D27: =IF('IN_MACRO'!$D$33=1,'IN_FIN'!$D$25*('ENG_CAPEX'!$D$26+'IN_FIN'!$D$24*'ENG_CAPEX'!$D$21/2),0) | E27: =IF('IN_MACRO'!$E$33=1,'IN_FIN'!$D$25*('ENG_CAPEX'!$E$26+'IN_FIN'!$D$24*'ENG_CAPEX'!$E$21/2),0) | F27: =IF('IN_MACRO'!$F$33=1,'IN_FIN'!$D$25*('ENG_CAPEX'!$F$26+'IN_FIN'!$D$24*'ENG_CAPEX'!$F$21/2),0) | G27: =IF('IN_MACRO'!$G$33=1,'IN_FIN'!$D$25*('ENG_CAPEX'!$G$26+'IN_FIN'!$D$24*'ENG_CAPEX'!$G$21/2),0) | H27: =IF('IN_MACRO'!$H$33=1,'IN_FIN'!$D$25*('ENG_CAPEX'!$H$26+'IN_FIN'!$D$24*'ENG_CAPEX'!$H$21/2),0) | I27: =IF('IN_MACRO'!$I$33=1,'IN_FIN'!$D$25*('ENG_CAPEX'!$I$26+'IN_FIN'!$D$24*'ENG_CAPEX'!$I$21/2),0) | J27: =IF('IN_MACRO'!$J$33=1,'IN_FIN'!$D$25*('ENG_CAPEX'!$J$26+'IN_FIN'!$D$24*'ENG_CAPEX'!$J$21/2),0) | K27: =IF('IN_MACRO'!$K$33=1,'IN_FIN'!$D$25*('ENG_CAPEX'!$K$26+'IN_FIN'!$D$24*'ENG_CAPEX'!$K$21/2),0) | L27: =IF('IN_MACRO'!$L$33=1,'IN_FIN'!$D$25*('ENG_CAPEX'!$L$26+'IN_FIN'!$D$24*'ENG_CAPEX'!$L$21/2),0) | M27: =IF('IN_MACRO'!$M$33=1,'IN_FIN'!$D$25*('ENG_CAPEX'!$M$26+'IN_FIN'!$D$24*'ENG_CAPEX'!$M$21/2),0) | N27: =IF('IN_MACRO'!$N$33=1,'IN_FIN'!$D$25*('ENG_CAPEX'!$N$26+'IN_FIN'!$D$24*'ENG_CAPEX'!$N$21/2),0) | O27: =IF('IN_MACRO'!$O$33=1,'IN_FIN'!$D$25*('ENG_CAPEX'!$O$26+'IN_FIN'!$D$24*'ENG_CAPEX'!$O$21/2),0) | P27: =IF('IN_MACRO'!$P$33=1,'IN_FIN'!$D$25*('ENG_CAPEX'!$P$26+'IN_FIN'!$D$24*'ENG_CAPEX'!$P$21/2),0)
A28: مانده تجمعی IDC | B28: CAPEX.idc_cum | C28: میلیون ریال | D28: ='ENG_CAPEX'!$D$27 | E28: ='ENG_CAPEX'!$D$28+'ENG_CAPEX'!$E$27 | F28: ='ENG_CAPEX'!$E$28+'ENG_CAPEX'!$F$27 | G28: ='ENG_CAPEX'!$F$28+'ENG_CAPEX'!$G$27 | H28: ='ENG_CAPEX'!$G$28+'ENG_CAPEX'!$H$27 | I28: ='ENG_CAPEX'!$H$28+'ENG_CAPEX'!$I$27 | J28: ='ENG_CAPEX'!$I$28+'ENG_CAPEX'!$J$27 | K28: ='ENG_CAPEX'!$J$28+'ENG_CAPEX'!$K$27 | L28: ='ENG_CAPEX'!$K$28+'ENG_CAPEX'!$L$27 | M28: ='ENG_CAPEX'!$L$28+'ENG_CAPEX'!$M$27 | N28: ='ENG_CAPEX'!$M$28+'ENG_CAPEX'!$N$27 | O28: ='ENG_CAPEX'!$N$28+'ENG_CAPEX'!$O$27 | P28: ='ENG_CAPEX'!$O$28+'ENG_CAPEX'!$P$27
A30: ج) جایگزینی دارایی‌ها
A31: جایگزینی زمین | B31: CAPEX.repl.0 | C31: میلیون ریال | D31: =IF(OR('IN_FIN'!$F$9<=0,'IN_FIN'!$G$9<=0,'IN_MACRO'!$D$23=0),0,IF(AND(MOD('IN_MACRO'!$D$23,'IN_FIN'!$G$9)=0,'IN_MACRO'!$D$23<='IN_MACRO'!$D$11),'IN_FIN'!$D$9*'IN_FIN'!$H$9*((1-'IN_FIN'!$E$9)*'ENG_SCEN'!$D$32+'IN_FIN'!$E$9*'ENG_SCEN'!$D$36)*'ENG_SCEN'!$G$16,0)) | E31: =IF(OR('IN_FIN'!$F$9<=0,'IN_FIN'!$G$9<=0,'IN_MACRO'!$E$23=0),0,IF(AND(MOD('IN_MACRO'!$E$23,'IN_FIN'!$G$9)=0,'IN_MACRO'!$E$23<='IN_MACRO'!$D$11),'IN_FIN'!$D$9*'IN_FIN'!$H$9*((1-'IN_FIN'!$E$9)*'ENG_SCEN'!$E$32+'IN_FIN'!$E$9*'ENG_SCEN'!$E$36)*'ENG_SCEN'!$G$16,0)) | F31: =IF(OR('IN_FIN'!$F$9<=0,'IN_FIN'!$G$9<=0,'IN_MACRO'!$F$23=0),0,IF(AND(MOD('IN_MACRO'!$F$23,'IN_FIN'!$G$9)=0,'IN_MACRO'!$F$23<='IN_MACRO'!$D$11),'IN_FIN'!$D$9*'IN_FIN'!$H$9*((1-'IN_FIN'!$E$9)*'ENG_SCEN'!$F$32+'IN_FIN'!$E$9*'ENG_SCEN'!$F$36)*'ENG_SCEN'!$G$16,0)) | G31: =IF(OR('IN_FIN'!$F$9<=0,'IN_FIN'!$G$9<=0,'IN_MACRO'!$G$23=0),0,IF(AND(MOD('IN_MACRO'!$G$23,'IN_FIN'!$G$9)=0,'IN_MACRO'!$G$23<='IN_MACRO'!$D$11),'IN_FIN'!$D$9*'IN_FIN'!$H$9*((1-'IN_FIN'!$E$9)*'ENG_SCEN'!$G$32+'IN_FIN'!$E$9*'ENG_SCEN'!$G$36)*'ENG_SCEN'!$G$16,0)) | H31: =IF(OR('IN_FIN'!$F$9<=0,'IN_FIN'!$G$9<=0,'IN_MACRO'!$H$23=0),0,IF(AND(MOD('IN_MACRO'!$H$23,'IN_FIN'!$G$9)=0,'IN_MACRO'!$H$23<='IN_MACRO'!$D$11),'IN_FIN'!$D$9*'IN_FIN'!$H$9*((1-'IN_FIN'!$E$9)*'ENG_SCEN'!$H$32+'IN_FIN'!$E$9*'ENG_SCEN'!$H$36)*'ENG_SCEN'!$G$16,0)) | I31: =IF(OR('IN_FIN'!$F$9<=0,'IN_FIN'!$G$9<=0,'IN_MACRO'!$I$23=0),0,IF(AND(MOD('IN_MACRO'!$I$23,'IN_FIN'!$G$9)=0,'IN_MACRO'!$I$23<='IN_MACRO'!$D$11),'IN_FIN'!$D$9*'IN_FIN'!$H$9*((1-'IN_FIN'!$E$9)*'ENG_SCEN'!$I$32+'IN_FIN'!$E$9*'ENG_SCEN'!$I$36)*'ENG_SCEN'!$G$16,0)) | J31: =IF(OR('IN_FIN'!$F$9<=0,'IN_FIN'!$G$9<=0,'IN_MACRO'!$J$23=0),0,IF(AND(MOD('IN_MACRO'!$J$23,'IN_FIN'!$G$9)=0,'IN_MACRO'!$J$23<='IN_MACRO'!$D$11),'IN_FIN'!$D$9*'IN_FIN'!$H$9*((1-'IN_FIN'!$E$9)*'ENG_SCEN'!$J$32+'IN_FIN'!$E$9*'ENG_SCEN'!$J$36)*'ENG_SCEN'!$G$16,0)) | K31: =IF(OR('IN_FIN'!$F$9<=0,'IN_FIN'!$G$9<=0,'IN_MACRO'!$K$23=0),0,IF(AND(MOD('IN_MACRO'!$K$23,'IN_FIN'!$G$9)=0,'IN_MACRO'!$K$23<='IN_MACRO'!$D$11),'IN_FIN'!$D$9*'IN_FIN'!$H$9*((1-'IN_FIN'!$E$9)*'ENG_SCEN'!$K$32+'IN_FIN'!$E$9*'ENG_SCEN'!$K$36)*'ENG_SCEN'!$G$16,0)) | L31: =IF(OR('IN_FIN'!$F$9<=0,'IN_FIN'!$G$9<=0,'IN_MACRO'!$L$23=0),0,IF(AND(MOD('IN_MACRO'!$L$23,'IN_FIN'!$G$9)=0,'IN_MACRO'!$L$23<='IN_MACRO'!$D$11),'IN_FIN'!$D$9*'IN_FIN'!$H$9*((1-'IN_FIN'!$E$9)*'ENG_SCEN'!$L$32+'IN_FIN'!$E$9*'ENG_SCEN'!$L$36)*'ENG_SCEN'!$G$16,0)) | M31: =IF(OR('IN_FIN'!$F$9<=0,'IN_FIN'!$G$9<=0,'IN_MACRO'!$M$23=0),0,IF(AND(MOD('IN_MACRO'!$M$23,'IN_FIN'!$G$9)=0,'IN_MACRO'!$M$23<='IN_MACRO'!$D$11),'IN_FIN'!$D$9*'IN_FIN'!$H$9*((1-'IN_FIN'!$E$9)*'ENG_SCEN'!$M$32+'IN_FIN'!$E$9*'ENG_SCEN'!$M$36)*'ENG_SCEN'!$G$16,0)) | N31: =IF(OR('IN_FIN'!$F$9<=0,'IN_FIN'!$G$9<=0,'IN_MACRO'!$N$23=0),0,IF(AND(MOD('IN_MACRO'!$N$23,'IN_FIN'!$G$9)=0,'IN_MACRO'!$N$23<='IN_MACRO'!$D$11),'IN_FIN'!$D$9*'IN_FIN'!$H$9*((1-'IN_FIN'!$E$9)*'ENG_SCEN'!$N$32+'IN_FIN'!$E$9*'ENG_SCEN'!$N$36)*'ENG_SCEN'!$G$16,0)) | O31: =IF(OR('IN_FIN'!$F$9<=0,'IN_FIN'!$G$9<=0,'IN_MACRO'!$O$23=0),0,IF(AND(MOD('IN_MACRO'!$O$23,'IN_FIN'!$G$9)=0,'IN_MACRO'!$O$23<='IN_MACRO'!$D$11),'IN_FIN'!$D$9*'IN_FIN'!$H$9*((1-'IN_FIN'!$E$9)*'ENG_SCEN'!$O$32+'IN_FIN'!$E$9*'ENG_SCEN'!$O$36)*'ENG_SCEN'!$G$16,0)) | P31: =IF(OR('IN_FIN'!$F$9<=0,'IN_FIN'!$G$9<=0,'IN_MACRO'!$P$23=0),0,IF(AND(MOD('IN_MACRO'!$P$23,'IN_FIN'!$G$9)=0,'IN_MACRO'!$P$23<='IN_MACRO'!$D$11),'IN_FIN'!$D$9*'IN_FIN'!$H$9*((1-'IN_FIN'!$E$9)*'ENG_SCEN'!$P$32+'IN_FIN'!$E$9*'ENG_SCEN'!$P$36)*'ENG_SCEN'!$G$16,0))
